Workbook
Name UPDATE: '[1]Data Sheet'!$E$1
Name UPDATE: '[1]Data Sheet'!$E$1
Name UPDATE: '[1]Data Sheet'!$E$1
Name UPDATE: 'Data Sheet'!$E$1

Sheet Title
A1: One Page Company Profile
A2: Historical Financial Statement Analysis
A3: Ratio Analysis
A4: Forecasting
A5: Common Size Statement
A6: WACC (Weighted Average Cost of Capital)
A7: Beta Regression
A8: Market Returns Analysis
A9: Intrinsic Growth Rate
A10: Discounted Cash Flow (DCF) Valuation
A11: Value at Risk (VAR)
A12: Monte Carlo Simulation
... A16: Altman's Z-Score

Sheet Data Sheet
A1: COMPANY NAME | B1: BRITANNIA INDUSTRIES LTD | E1: =IF(B2<>B3, "A NEW VERSION OF THE WORKSHEET IS AVAILABLE", "")
A2: LATEST VERSION | B2: 2.1 | E2: PLEASE DO NOT MAKE ANY CHANGES TO THIS SHEET
A3: CURRENT VERSION | B3: 2.1
A5: META
A6: Number of shares | B6: =IF(B9>0, B9/B8, 0) -> 24.077305
A7: Face Value | B7: 1
A8: Current Price | B8: 5250
A9: Market Capitalization | B9: 126405.85
A15: PROFIT & LOSS
A16: Report Date | B16: 42825 | C16: 43190 | D16: 43555 | E16: 43921 | F16: 44286 | G16: 44651 | H16: 45016 | I16: 45382 | J16: 45747 | K16: 46112
A17: Sales | B17: 9054.09 | C17: 9913.99 | D17: 11054.67 | E17: 11599.55 | F17: 13136.14 | G17: 14136.26 | H17: 16300.55 | I17: 16769.27 | J17: 17942.67 | K17: 19151.59
A18: Raw Material Cost | B18: 5642.88 | C18: 6100.8 | D18: 6616.64 | E18: 6874.9 | F18: 7663.22 | G18: 8835.56 | H18: 9663.83 | I18: 9488.37 | J18: 10668.8 | K18: 11155.25
A19: Change in Inventory | B19: 54.2 | C19: -6.3 | D19: 55.18 | E19: -52.57 | F19: 37.12 | G19: 75.26 | H19: 72.53 | I19: -3.66 | J19: 64.75 | K19: 22.37
A20: Power and Fuel | B20: 104.28 | C20: 128.83 | D20: 175.17 | E20: 177.7 | F20: 182.29 | G20: 217.68 | H20: 272.2 | I20: 327.25 | J20: 357.98 | K20: 342.87
A21: Other Mfr. Exp | B21: 509.93 | C21: 487.59 | D21: 621.32 | E21: 610.68 | F21: 672.21 | G21: 752.29 | H21: 893.75 | I21: 876.12 | J21: 954.03 | K21: 920.68
A22: Employee Cost | B22: 352.61 | C22: 401.6 | D22: 441.82 | E22: 486.69 | F22: 527.38 | G22: 542.26 | H22: 658.38 | I22: 708.7 | J22: 704.59 | K22: 823.8
A23: Selling and admin | B23: 915.01 | C23: 953.48 | D23: 1107.49 | E23: 1125.23 | F23: 1163.82 | G23: 1187.32 | H23: 1473.86 | I23: 1525.52 | J23: 1360 | K23: 1575.23
A24: Other Expenses | B24: 305.4 | C24: 333.92 | D24: 414.96 | E24: 428.6 | F24: 455.05 | G24: 475.1 | H24: 580.15 | I24: 673 | J24: 785.61 | K24: 841.79
A25: Other Income | B25: 150.54 | C25: 166.37 | D25: 206.45 | E25: 262.83 | F25: 313.07 | G25: 221.85 | H25: 596.87 | I25: 211.28 | J25: 202.3 | K25: 224.03
A26: Depreciation | B26: 119.27 | C26: 142.07 | D26: 161.88 | E26: 184.81 | F26: 197.85 | G26: 200.54 | H26: 225.91 | I26: 300.46 | J26: 313.34 | K26: 336.83
A27: Interest | B27: 5.45 | C27: 7.59 | D27: 9.09 | E27: 76.9 | F27: 110.9 | G27: 144.29 | H27: 169.1 | I27: 164 | J27: 138.8 | K27: 112.76
... A31: Dividend Amount | B31: 264 | C31: 300.12 | D31: 360.45 | E31: 841.75 | F31: 3794.18 | G31: 1361.08 | H31: 1734.48 | I31: 1770.62 | J31: 1806.75 | K31: 2180.14
A40: Quarters
A41: Report Date | B41: 45382 | C41: 45473 | D41: 45565 | E41: 45657 | F41: 45747 | G41: 45838 | H41: 45930 | I41: 46022 | J41: 46112 | K41: 46203
A42: Sales | B42: 4069.36 | C42: 4250.29 | D42: 4667.57 | E42: 4592.61 | F42: 4432.19 | G42: 4622.22 | H42: 4840.63 | I42: 4969.82 | J42: 4718.92 | K42: 4999.97
A43: Expenses | B43: 3285.71 | C43: 3497.28 | D43: 3887.56 | E43: 3749.75 | F43: 3631.67 | G43: 3870.02 | H43: 3889.39 | I43: 3992.49 | J43: 3885.35 | K43: 4161.65
A44: Other Income | B44: 57.34 | C44: 30.97 | D44: 45.85 | E44: 62.46 | F44: 63.02 | G44: 57.01 | H44: 52.11 | I44: 59.46 | J44: 55.45 | K44: 61.41
A45: Depreciation | B45: 79.93 | C45: 73.93 | D45: 76.07 | E45: 82.38 | F45: 80.96 | G45: 82.04 | H45: 85.05 | I45: 84.51 | J45: 85.23 | K45: 79.51
A46: Interest | B46: 26.44 | C46: 28.95 | D46: 34.64 | E46: 44.56 | F46: 30.65 | G46: 26.15 | H46: 34.68 | I46: 33.25 | J46: 18.68 | K46: 22.87
A47: Profit before tax | B47: 734.62 | C47: 681.1 | D47: 715.15 | E47: 778.38 | F47: 751.93 | G47: 701.02 | H47: 883.62 | I47: 919.03 | J47: 785.11 | K47: 797.35
A48: Tax | B48: 198.01 | C48: 176.22 | D48: 183.6 | E48: 196.08 | F48: 192.8 | G48: 180.89 | H48: 228.56 | I48: 236.89 | J48: 105.43 | K48: 203.97
A49: Net profit | B49: 538.28 | C49: 505.64 | D49: 531.45 | E49: 581.69 | F49: 559.95 | G49: 520.72 | H49: 654.47 | I49: 679.96 | J49: 678.34 | K49: 591.35
A50: Operating Profit | B50: 783.65 | C50: 753.01 | D50: 780.01 | E50: 842.86 | F50: 800.52 | G50: 752.2 | H50: 951.24 | I50: 977.33 | J50: 833.57 | K50: 838.32
A55: BALANCE SHEET
A56: Report Date | B56: 42825 | C56: 43190 | D56: 43555 | E56: 43921 | F56: 44286 | G56: 44651 | H56: 45016 | I56: 45382 | J56: 45747 | K56: 46112
A57: Equity Share Capital | B57: 24 | C57: 24.01 | D57: 24.03 | E57: 24.05 | F57: 24.09 | G57: 24.09 | H57: 24.09 | I57: 24.09 | J57: 24.09 | K57: 24.09
A58: Reserves | B58: 2672.42 | C58: 3382.22 | D58: 4229.22 | E58: 4378.78 | F58: 3523.57 | G58: 2534.01 | H58: 3510.18 | I58: 3917.43 | J58: 4331.63 | K58: 5082.47
A59: Borrowings | B59: 124.56 | C59: 200.7 | D59: 156.02 | E59: 1537.59 | F59: 2106.94 | G59: 2481.2 | H59: 2997.37 | I59: 2064.96 | J59: 1246.51 | K59: 1380.28
A60: Other Liabilities | B60: 1287.82 | C60: 1580.99 | D60: 1828.68 | E60: 1889.12 | F60: 2345.49 | G60: 2487.3 | H60: 2819.21 | I60: 3065.02 | J60: 3234.52 | K60: 3243.48
A61: Total | B61: 4108.8 | C61: 5187.92 | D61: 6237.95 | E61: 7829.54 | F61: 8000.09 | G61: 7526.6 | H61: 9350.85 | I61: 9071.5 | J61: 8836.75 | K61: 9730.32
A62: Net Block | B62: 1159.99 | C62: 1345.6 | D62: 1688.3 | E62: 1878.18 | F62: 1792.95 | G62: 1753.21 | H62: 2655.22 | I62: 2771.14 | J62: 2903.8 | K62: 2849.92
A63: Capital Work in Progress | B63: 30.07 | C63: 202.82 | D63: 101.24 | E63: 39.55 | F63: 116.52 | G63: 535.68 | H63: 105 | I63: 187.54 | J63: 89.2 | K63: 39.04
A64: Investments | B64: 486.85 | C64: 1079.28 | D64: 1476.28 | E64: 2893.23 | F64: 2780.69 | G64: 1762.37 | H64: 3324.24 | I64: 2766.72 | J64: 2865.43 | K64: 3609.76
A65: Other Assets | B65: 2431.89 | C65: 2560.22 | D65: 2972.13 | E65: 3018.58 | F65: 3309.93 | G65: 3475.34 | H65: 3266.39 | I65: 3346.1 | J65: 2978.32 | K65: 3231.6
A66: Total | B66: 4108.8 | C66: 5187.92 | D66: 6237.95 | E66: 7829.54 | F66: 8000.09 | G66: 7526.6 | H66: 9350.85 | I66: 9071.5 | J66: 8836.75 | K66: 9730.32
A67: Receivables | B67: 179.16 | C67: 304.6 | D67: 394.24 | E67: 320.36 | F67: 257.27 | G67: 331.93 | H67: 328.94 | I67: 393.33 | J67: 448.61 | K67: 469.21
... A70: No. of Equity Shares | B70: 120000815 | C70: 120059148 | D70: 240318294 | E70: 240318294 | F70: 240868296 | G70: 240868296 | H70: 240868296 | I70: 240868296 | J70: 240868296 | K70: 240868296
A71: New Bonus Shares
A72: Face value | B72: 2 | C72: 2 | D72: 1 | E72: 1 | F72: 1 | G72: 1 | H72: 1 | I72: 1 | J72: 1 | K72: 1
A80: CASH FLOW:
A81: Report Date | B81: 42825 | C81: 43190 | D81: 43555 | E81: 43921 | F81: 44286 | G81: 44651 | H81: 45016 | I81: 45382 | J81: 45747 | K81: 46112
A82: Cash from Operating Activity | B82: 441.28 | C82: 1248.77 | D82: 1155.78 | E82: 1484.53 | F82: 1851.07 | G82: 1299.52 | H82: 2526.21 | I82: 2572.98 | J82: 2490.62 | K82: 2611.6
A83: Cash from Investing Activity | B83: -149.85 | C83: -956.52 | D83: -852.22 | E83: -1525.93 | F83: 458.82 | G83: 914.19 | H83: -1507 | I83: 485.44 | J83: 69.07 | K83: -741.38
A84: Cash from Financing Activity | B84: -295.08 | C84: -231.75 | D84: -352.68 | E84: 57.94 | F84: -2243.69 | G84: -2245.84 | H84: -1028.37 | I84: -2839.13 | J84: -2753.9 | K84: -1782.62
A85: Net Cash Flow | B85: -3.65 | C85: 60.5 | D85: -49.12 | E85: 16.54 | F85: 66.2 | G85: -32.13 | H85: -9.16 | I85: 219.29 | J85: -194.21 | K85: 87.6
A90: PRICE: | B90: 1687 | C90: 2485.3 | D90: 3085.5 | E90: 2688.95 | F90: 3625.05 | G90: 3206.4 | H90: 4322.15 | I90: 4911.25 | J90: 4936.9 | K90: 5423
A92: DERIVED:
A93: Adjusted Equity Shares in Cr | B93: 24 | C93: 24.01 | D93: 24.03 | E93: 24.05 | F93: 24.09 | G93: 24.09 | H93: 24.09 | I93: 24.09 | J93: 24.09 | K93: 24.09

Sheet Profit & Loss
A1: ='[1]Data Sheet'!B1 -> BRITANNIA INDUSTRIES LTD | H1: =UPDATE -> 0 | M1: SCREENER.IN
A3: Narration | B3: ='[1]Data Sheet'!B16 -> 42825 | C3: ='[1]Data Sheet'!C16 -> 43190 | D3: ='[1]Data Sheet'!D16 -> 43555 | E3: ='[1]Data Sheet'!E16 -> 43921 | F3: ='[1]Data Sheet'!F16 -> 44286 | G3: ='[1]Data Sheet'!G16 -> 44651 | H3: ='[1]Data Sheet'!H16 -> 45016 | I3: ='[1]Data Sheet'!I16 -> 45382 | ... K3: ='[1]Data Sheet'!K16 -> 46112 | L3: Trailing | M3: Best Case | N3: Worst Case
A4: Sales | B4: ='[1]Data Sheet'!B17 -> 9054.09 | C4: ='[1]Data Sheet'!C17 -> 9913.99 | D4: ='[1]Data Sheet'!D17 -> 11054.67 | E4: ='[1]Data Sheet'!E17 -> 11599.55 | F4: ='[1]Data Sheet'!F17 -> 13136.14 | G4: ='[1]Data Sheet'!G17 -> 14136.26 | H4: ='[1]Data Sheet'!H17 -> 16300.55 | I4: ='[1]Data Sheet'!I17 -> 16769.27 | ... K4: ='[1]Data Sheet'!K17 -> 19151.59 | L4: =SUM([1]Quarters!H4:K4) -> 0 | M4: =$K4+M23*K4 -> 20441.963 | N4: =$K4+N23*L4 -> 19151.59
A5: Expenses | B5: =SUM('[1]Data Sheet'!B18,'[1]Data Sheet'!B20:B24, -1*'[1]Data Sheet'!B19) -> 7775.91 | C5: =SUM('[1]Data Sheet'!C18,'[1]Data Sheet'!C20:C24, -1*'[1]Data Sheet'!C19) -> 8412.52 | D5: =SUM('[1]Data Sheet'!D18,'[1]Data Sheet'!D20:D24, -1*'[1]Data Sheet'!D19) -> 9322.22 | E5: =SUM('[1]Data Sheet'!E18,'[1]Data Sheet'!E20:E24, -1*'[1]Data Sheet'!E19) -> 9756.37 | F5: =SUM('[1]Data Sheet'!F18,'[1]Data Sheet'!F20:F24, -1*'[1]Data Sheet'!F19) -> 10626.85 | G5: =SUM('[1]Data Sheet'!G18,'[1]Data Sheet'!G20:G24, -1*'[1]Data Sheet'!G19) -> 11934.95 | H5: =SUM('[1]Data Sheet'!H18,'[1]Data Sheet'!H20:H24, -1*'[1]Data Sheet'!H19) -> 13469.64 | I5: =SUM('[1]Data Sheet'!I18,'[1]Data Sheet'!I20:I24, -1*'[1]Data Sheet'!I19) -> 13602.62 | ... K5: =SUM('[1]Data Sheet'!K18,'[1]Data Sheet'!K20:K24, -1*'[1]Data Sheet'!K19) -> 15637.25 | L5: =SUM([1]Quarters!H5:K5) -> 0 | M5: =M4-M6 -> 16700.942 | N5: =N4-N6 -> 19151.59
A6: Operating Profit | B6: =B4-B5 -> 1278.18 | C6: =C4-C5 -> 1501.47 | D6: =D4-D5 -> 1732.45 | E6: =E4-E5 -> 1843.18 | F6: =F4-F5 -> 2509.29 | G6: =G4-G5 -> 2201.31 | H6: =H4-H5 -> 2830.91 | I6: =I4-I5 -> 3166.65 | ... K6: =K4-K5 -> 3514.34 | L6: =SUM([1]Quarters!H6:K6) -> 0 | M6: =M4*M24 -> 3741.0212 | N6: =N4*N24 -> 0
A7: Other Income | B7: ='[1]Data Sheet'!B25 -> 150.54 | C7: ='[1]Data Sheet'!C25 -> 166.37 | D7: ='[1]Data Sheet'!D25 -> 206.45 | E7: ='[1]Data Sheet'!E25 -> 262.83 | F7: ='[1]Data Sheet'!F25 -> 313.07 | G7: ='[1]Data Sheet'!G25 -> 221.85 | H7: ='[1]Data Sheet'!H25 -> 596.87 | I7: ='[1]Data Sheet'!I25 -> 211.28 | ... K7: ='[1]Data Sheet'!K25 -> 224.03 | L7: =SUM([1]Quarters!H7:K7) -> 0 | M7: 0 | N7: 0
A8: Depreciation | B8: ='[1]Data Sheet'!B26 -> 119.27 | C8: ='[1]Data Sheet'!C26 -> 142.07 | D8: ='[1]Data Sheet'!D26 -> 161.88 | E8: ='[1]Data Sheet'!E26 -> 184.81 | F8: ='[1]Data Sheet'!F26 -> 197.85 | G8: ='[1]Data Sheet'!G26 -> 200.54 | H8: ='[1]Data Sheet'!H26 -> 225.91 | I8: ='[1]Data Sheet'!I26 -> 300.46 | ... K8: ='[1]Data Sheet'!K26 -> 336.83 | L8: =SUM([1]Quarters!H8:K8) -> 0 | M8: =+$L8 -> 0 | N8: =+$L8 -> 0
A9: Interest | B9: ='[1]Data Sheet'!B27 -> 5.45 | C9: ='[1]Data Sheet'!C27 -> 7.59 | D9: ='[1]Data Sheet'!D27 -> 9.09 | E9: ='[1]Data Sheet'!E27 -> 76.9 | F9: ='[1]Data Sheet'!F27 -> 110.9 | G9: ='[1]Data Sheet'!G27 -> 144.29 | H9: ='[1]Data Sheet'!H27 -> 169.1 | I9: ='[1]Data Sheet'!I27 -> 164 | ... K9: ='[1]Data Sheet'!K27 -> 112.76 | L9: =SUM([1]Quarters!H9:K9) -> 0 | M9: =+$L9 -> 0 | N9: =+$L9 -> 0
A10: Profit before tax | B10: ='[1]Data Sheet'!B28 -> 1304 | C10: ='[1]Data Sheet'!C28 -> 1518.18 | D10: ='[1]Data Sheet'!D28 -> 1767.93 | E10: ='[1]Data Sheet'!E28 -> 1844.3 | F10: ='[1]Data Sheet'!F28 -> 2513.61 | G10: ='[1]Data Sheet'!G28 -> 2078.33 | H10: ='[1]Data Sheet'!H28 -> 3032.77 | I10: ='[1]Data Sheet'!I28 -> 2913.47 | ... K10: ='[1]Data Sheet'!K28 -> 3288.78 | L10: =SUM([1]Quarters!H10:K10) -> 0 | M10: =M6+M7-SUM(M8:M9) -> 3741.0212 | N10: =N6+N7-SUM(N8:N9) -> 0
A11: Tax | B11: ='[1]Data Sheet'!B29 -> 419.67 | C11: ='[1]Data Sheet'!C29 -> 514.22 | D11: ='[1]Data Sheet'!D29 -> 612.47 | E11: ='[1]Data Sheet'!E29 -> 450.7 | F11: ='[1]Data Sheet'!F29 -> 663.02 | G11: ='[1]Data Sheet'!G29 -> 562.35 | H11: ='[1]Data Sheet'!H29 -> 716.45 | I11: ='[1]Data Sheet'!I29 -> 779.25 | ... K11: ='[1]Data Sheet'!K29 -> 751.77 | L11: =SUM([1]Quarters!H11:K11) -> 0 | M11: =IF($L10>0,$L11/$L10,0) -> 0 | N11: =IF($L10>0,$L11/$L10,0) -> 0
A12: Net profit | B12: ='[1]Data Sheet'!B30 -> 884.47 | C12: ='[1]Data Sheet'!C30 -> 1004.23 | D12: ='[1]Data Sheet'!D30 -> 1159.12 | E12: ='[1]Data Sheet'!E30 -> 1402.63 | F12: ='[1]Data Sheet'!F30 -> 1863.9 | G12: ='[1]Data Sheet'!G30 -> 1524.82 | H12: ='[1]Data Sheet'!H30 -> 2321.77 | I12: ='[1]Data Sheet'!I30 -> 2139.81 | ... K12: ='[1]Data Sheet'!K30 -> 2533.49 | L12: =SUM([1]Quarters!H12:K12) -> 0 | M12: =M10-M11*M10 -> 3741.0212 | N12: =N10-N11*N10 -> 0
A13: EPS | B13: =IF('[1]Data Sheet'!B93>0,B12/'[1]Data Sheet'!B93,0) -> 36.852917 | C13: =IF('[1]Data Sheet'!C93>0,C12/'[1]Data Sheet'!C93,0) -> 41.825489 | D13: =IF('[1]Data Sheet'!D93>0,D12/'[1]Data Sheet'!D93,0) -> 48.236371 | E13: =IF('[1]Data Sheet'!E93>0,E12/'[1]Data Sheet'!E93,0) -> 58.321414 | F13: =IF('[1]Data Sheet'!F93>0,F12/'[1]Data Sheet'!F93,0) -> 77.372354 | G13: =IF('[1]Data Sheet'!G93>0,G12/'[1]Data Sheet'!G93,0) -> 63.296804 | H13: =IF('[1]Data Sheet'!H93>0,H12/'[1]Data Sheet'!H93,0) -> 96.378995 | I13: =IF('[1]Data Sheet'!I93>0,I12/'[1]Data Sheet'!I93,0) -> 88.825654 | ... K13: =IF('[1]Data Sheet'!K93>0,K12/'[1]Data Sheet'!K93,0) -> 105.1677 | L13: =IF('[1]Data Sheet'!$B6>0,'Profit & Loss'!L12/'[1]Data Sheet'!$B6,0) -> 0 | M13: =IF('[1]Data Sheet'!$B6>0,'Profit & Loss'!M12/'[1]Data Sheet'!$B6,0) -> 0 | N13: =IF('[1]Data Sheet'!$B6>0,'Profit & Loss'!N12/'[1]Data Sheet'!$B6,0) -> 0
A14: Price to earning | B14: =IF(B15>0,B15/B13,"") -> 45.776567 | C14: =IF(C15>0,C15/C13,"") -> 59.420703 | D14: =IF(D15>0,D15/D13,"") -> 63.966255 | E14: =IF(E15>0,E15/E13,"") -> 46.105707 | F14: =IF(F15>0,F15/F13,"") -> 46.852006 | G14: =IF(G15>0,G15/G13,"") -> 50.656586 | H14: =IF(H15>0,H15/H13,"") -> 44.845352 | I14: =IF(I15>0,I15/I13,"") -> 55.290896 | ... K14: =IF(K15>0,K15/K13,"") -> 51.56526 | L14: =IF(L13>0,L15/L13,0) -> 0 | M14: =M25 -> 53.814322 | N14: =N25 -> 0
A15: Price | B15: ='[1]Data Sheet'!B90 -> 1687 | C15: ='[1]Data Sheet'!C90 -> 2485.3 | D15: ='[1]Data Sheet'!D90 -> 3085.5 | E15: ='[1]Data Sheet'!E90 -> 2688.95 | F15: ='[1]Data Sheet'!F90 -> 3625.05 | G15: ='[1]Data Sheet'!G90 -> 3206.4 | H15: ='[1]Data Sheet'!H90 -> 4322.15 | I15: ='[1]Data Sheet'!I90 -> 4911.25 | ... K15: ='[1]Data Sheet'!K90 -> 5423 | L15: ='[1]Data Sheet'!B8 -> 5250 | M15: =M13*M14 -> 0 | N15: =N13*N14 -> 0
A17: RATIOS:
A18: Dividend Payout | B18: =IF('[1]Data Sheet'!B30>0, '[1]Data Sheet'!B31/'[1]Data Sheet'!B30, 0) -> 0.29848384 | C18: =IF('[1]Data Sheet'!C30>0, '[1]Data Sheet'!C31/'[1]Data Sheet'!C30, 0) -> 0.29885584 | D18: =IF('[1]Data Sheet'!D30>0, '[1]Data Sheet'!D31/'[1]Data Sheet'!D30, 0) -> 0.31096867 | E18: =IF('[1]Data Sheet'!E30>0, '[1]Data Sheet'!E31/'[1]Data Sheet'!E30, 0) -> 0.60012263 | F18: =IF('[1]Data Sheet'!F30>0, '[1]Data Sheet'!F31/'[1]Data Sheet'!F30, 0) -> 2.0356135 | G18: =IF('[1]Data Sheet'!G30>0, '[1]Data Sheet'!G31/'[1]Data Sheet'!G30, 0) -> 0.89261683 | H18: =IF('[1]Data Sheet'!H30>0, '[1]Data Sheet'!H31/'[1]Data Sheet'!H30, 0) -> 0.74705074 | I18: =IF('[1]Data Sheet'!I30>0, '[1]Data Sheet'!I31/'[1]Data Sheet'!I30, 0) -> 0.82746599 | ... K18: =IF('[1]Data Sheet'!K30>0, '[1]Data Sheet'!K31/'[1]Data Sheet'!K30, 0) -> 0.86052836
A19: OPM | B19: =IF(B6>0,B6/B4,0) -> 0.14117156 | C19: =IF(C6>0,C6/C4,0) -> 0.15144962 | D19: =IF(D6>0,D6/D4,0) -> 0.15671657 | E19: =IF(E6>0,E6/E4,0) -> 0.15890099 | F19: =IF(F6>0,F6/F4,0) -> 0.19102187 | G19: =IF(G6>0,G6/G4,0) -> 0.15572082 | H19: =IF(H6>0,H6/H4,0) -> 0.1736696 | I19: =IF(I6>0,I6/I4,0) -> 0.18883648 | ... L19: =IF(L6>0,L6/L4,0) -> 0
G22: TRENDS: | H22: 10 YEARS | I22: 7 YEARS | J22: 5 YEARS | K22: 3 YEARS | L22: RECENT | M22: BEST | N22: WORST
G23: Sales Growth | H23: =IF(B4=0,"",POWER($K4/B4,1/9)-1) -> 0.086803715 | I23: =IF(D4=0,"",POWER($K4/D4,1/7)-1) -> 0.08166842 | J23: =IF(F4=0,"",POWER($K4/F4,1/5)-1) -> 0.078319387 | K23: =IF(H4=0,"",POWER($K4/H4, 1/3)-1) -> 0.055198566 | L23: =IF(ISERROR(MAX(IF(J4=0,"",(K4-J4)/J4),IF(K4=0,"",(L4-K4)/K4))),"",MAX(IF(J4=0,"",(K4-J4)/J4),IF(K4=0,"",(L4-K4)/K4))) -> 0.067376817 | M23: =MAX(K23:L23) -> 0.067376817 | N23: =MIN(H23:L23) -> 0.055198566
G24: OPM | H24: =IF(SUM(B4:$K$4)=0,"",SUMPRODUCT(B19:$K$19,B4:$K$4)/SUM(B4:$K$4)) -> 0.17082122 | I24: =IF(SUM(E4:$K$4)=0,"",SUMPRODUCT(E19:$K$19,E4:$K$4)/SUM(E4:$K$4)) -> 0.1764746 | J24: =IF(SUM(G4:$K$4)=0,"",SUMPRODUCT(G19:$K$19,G4:$K$4)/SUM(G4:$K$4)) -> 0.17662586 | K24: =IF(SUM(I4:$K$4)=0, "", SUMPRODUCT(I19:$K$19,I4:$K$4)/SUM(I4:$K$4)) -> 0.18300694 | L24: =L19 -> 0 | M24: =MAX(K24:L24) -> 0.18300694 | N24: =MIN(H24:L24) -> 0
G25: Price to Earning | H25: =IF(ISERROR(AVERAGEIF(B14:$L14,">0")),"",AVERAGEIF(B14:$L14,">0")) -> 51.906614 | I25: =IF(ISERROR(AVERAGEIF(E14:$L14,">0")),"",AVERAGEIF(E14:$L14,">0")) -> 49.986088 | J25: =IF(ISERROR(AVERAGEIF(G14:$L14,">0")),"",AVERAGEIF(G14:$L14,">0")) -> 51.388981 | K25: =IF(ISERROR(AVERAGEIF(I14:$L14,">0")),"",AVERAGEIF(I14:$L14,">0")) -> 53.814322 | L25: =L14 -> 0 | M25: =MAX(K25:L25) -> 53.814322 | N25: =MIN(H25:L25) -> 0
A28: Sales growth Y-O-Y | C28: =C4/B4-1 -> 0.094973653 | D28: =D4/C4-1 -> 0.11505761 | E28: =E4/D4-1 -> 0.049289576 | F28: =F4/E4-1 -> 0.13246979 | G28: =G4/F4-1 -> 0.076134999 | H28: =H4/G4-1 -> 0.15310202 | I28: =I4/H4-1 -> 0.028754858 | J28: =J4/I4-1 -> 0.069973231 | K28: =K4/J4-1 -> 0.067376817
A29: Market Capitalization | B29: ='Data Sheet'!B93*'Data Sheet'!B90 -> 40488 | C29: ='Data Sheet'!C93*'Data Sheet'!C90 -> 59672.053 | D29: ='Data Sheet'!D93*'Data Sheet'!D90 -> 74144.565 | E29: ='Data Sheet'!E93*'Data Sheet'!E90 -> 64669.247 | F29: ='Data Sheet'!F93*'Data Sheet'!F90 -> 87327.455 | G29: ='Data Sheet'!G93*'Data Sheet'!G90 -> 77242.176 | H29: ='Data Sheet'!H93*'Data Sheet'!H90 -> 104120.59 | I29: ='Data Sheet'!I93*'Data Sheet'!I90 -> 118312.01 | ... K29: ='Data Sheet'!K93*'Data Sheet'!K90 -> 130640.07
A30: Debt | B30: ='Data Sheet'!B59 -> 124.56 | C30: ='Data Sheet'!C59 -> 200.7 | D30: ='Data Sheet'!D59 -> 156.02 | E30: ='Data Sheet'!E59 -> 1537.59 | F30: ='Data Sheet'!F59 -> 2106.94 | G30: ='Data Sheet'!G59 -> 2481.2 | H30: ='Data Sheet'!H59 -> 2997.37 | I30: ='Data Sheet'!I59 -> 2064.96 | ... K30: ='Data Sheet'!K59 -> 1380.28
A31: Cash | B31: ='Data Sheet'!B69 -> 120.76 | C31: ='Data Sheet'!C69 -> 186.42 | D31: ='Data Sheet'!D69 -> 109.82 | E31: ='Data Sheet'!E69 -> 122.85 | F31: ='Data Sheet'!F69 -> 211.34 | G31: ='Data Sheet'!G69 -> 184.9 | H31: ='Data Sheet'!H69 -> 197.98 | I31: ='Data Sheet'!I69 -> 446.35 | ... K31: ='Data Sheet'!K69 -> 352.44
A32: EV | B32: =B29+B30-B31 -> 40491.8 | C32: =C29+C30-C31 -> 59686.333 | D32: =D29+D30-D31 -> 74190.765 | E32: =E29+E30-E31 -> 66083.987 | F32: =F29+F30-F31 -> 89223.055 | G32: =G29+G30-G31 -> 79538.476 | H32: =H29+H30-H31 -> 106919.98 | I32: =I29+I30-I31 -> 119930.62 | ... K32: =K29+K30-K31 -> 131667.91
A34: EBITDA | B34: ='Historical FS'!C24 -> 1278.18 | C34: ='Historical FS'!D24 -> 1501.47 | D34: ='Historical FS'!E24 -> 1732.45 | E34: ='Historical FS'!F24 -> 1843.18 | F34: ='Historical FS'!G24 -> 2509.29 | G34: ='Historical FS'!H24 -> 2201.31 | H34: ='Historical FS'!I24 -> 2830.91 | I34: ='Historical FS'!J24 -> 3166.65 | ... K34: ='Historical FS'!L24 -> 3514.34
A35: EV/EBITDA | B35: =B32/B34 -> 31.679263 | C35: =C32/C34 -> 39.751932 | D35: =D32/D34 -> 42.824188 | E35: =E32/E34 -> 35.853247 | F35: =F32/F34 -> 35.557092 | G35: =G32/G34 -> 36.132338 | H35: =H32/H34 -> 37.768768 | I35: =I32/I34 -> 37.873027 | ... K35: =K32/K34 -> 37.4659
A36: EV/Sales | B36: =B32/B4 -> 4.4722109 | C36: =C32/C4 -> 6.0204149 | D36: =D32/D4 -> 6.71126 | E36: =E32/E4 -> 5.6971165 | F36: =F32/F4 -> 6.7921821 | G36: =G32/G4 -> 5.6265572 | H36: =H32/H4 -> 6.5592869 | I36: =I32/I4 -> 7.1518094 | ... K36: =K32/K4 -> 6.8750381
A38: Book Value of Equity | B38: ='Balance Sheet'!B4+'Balance Sheet'!B5 -> 2696.42 | C38: ='Balance Sheet'!C4+'Balance Sheet'!C5 -> 3406.23 | D38: ='Balance Sheet'!D4+'Balance Sheet'!D5 -> 4253.25 | E38: ='Balance Sheet'!E4+'Balance Sheet'!E5 -> 4402.83 | F38: ='Balance Sheet'!F4+'Balance Sheet'!F5 -> 3547.66 | G38: ='Balance Sheet'!G4+'Balance Sheet'!G5 -> 2558.1 | H38: ='Balance Sheet'!H4+'Balance Sheet'!H5 -> 3534.27 | I38: ='Balance Sheet'!I4+'Balance Sheet'!I5 -> 3941.52 | ... K38: ='Balance Sheet'!K4+'Balance Sheet'!K5 -> 5106.56
A39: Price/Book Value | B39: =B29/B38 -> 15.015465 | C39: =C29/C38 -> 17.518504 | D39: =D29/D38 -> 17.432449 | E39: =E29/E38 -> 14.688109 | F39: =F29/F38 -> 24.615508 | G39: =G29/G38 -> 30.195135 | H39: =H29/H38 -> 29.460283 | I39: =I29/I38 -> 30.016849 | ... K39: =K29/K38 -> 25.582794

Sheet Balance Sheet
A1: ='[1]Profit & Loss'!A1 -> 0 | E1: =UPDATE -> 0 | J1: SCREENER.IN
A3: Narration | B3: ='[1]Data Sheet'!B56 -> 42825 | C3: ='[1]Data Sheet'!C56 -> 43190 | D3: ='[1]Data Sheet'!D56 -> 43555 | E3: ='[1]Data Sheet'!E56 -> 43921 | F3: ='[1]Data Sheet'!F56 -> 44286 | G3: ='[1]Data Sheet'!G56 -> 44651 | H3: ='[1]Data Sheet'!H56 -> 45016 | I3: ='[1]Data Sheet'!I56 -> 45382 | ... K3: ='[1]Data Sheet'!K56 -> 46112
A4: Equity Share Capital | B4: ='[1]Data Sheet'!B57 -> 24 | C4: ='[1]Data Sheet'!C57 -> 24.01 | D4: ='[1]Data Sheet'!D57 -> 24.03 | E4: ='[1]Data Sheet'!E57 -> 24.05 | F4: ='[1]Data Sheet'!F57 -> 24.09 | G4: ='[1]Data Sheet'!G57 -> 24.09 | H4: ='[1]Data Sheet'!H57 -> 24.09 | I4: ='[1]Data Sheet'!I57 -> 24.09 | ... K4: ='[1]Data Sheet'!K57 -> 24.09
A5: Reserves | B5: ='[1]Data Sheet'!B58 -> 2672.42 | C5: ='[1]Data Sheet'!C58 -> 3382.22 | D5: ='[1]Data Sheet'!D58 -> 4229.22 | E5: ='[1]Data Sheet'!E58 -> 4378.78 | F5: ='[1]Data Sheet'!F58 -> 3523.57 | G5: ='[1]Data Sheet'!G58 -> 2534.01 | H5: ='[1]Data Sheet'!H58 -> 3510.18 | I5: ='[1]Data Sheet'!I58 -> 3917.43 | ... K5: ='[1]Data Sheet'!K58 -> 5082.47
A6: Borrowings | B6: ='[1]Data Sheet'!B59 -> 124.56 | C6: ='[1]Data Sheet'!C59 -> 200.7 | D6: ='[1]Data Sheet'!D59 -> 156.02 | E6: ='[1]Data Sheet'!E59 -> 1537.59 | F6: ='[1]Data Sheet'!F59 -> 2106.94 | G6: ='[1]Data Sheet'!G59 -> 2481.2 | H6: ='[1]Data Sheet'!H59 -> 2997.37 | I6: ='[1]Data Sheet'!I59 -> 2064.96 | ... K6: ='[1]Data Sheet'!K59 -> 1380.28
A7: Other Liabilities | B7: ='[1]Data Sheet'!B60 -> 1287.82 | C7: ='[1]Data Sheet'!C60 -> 1580.99 | D7: ='[1]Data Sheet'!D60 -> 1828.68 | E7: ='[1]Data Sheet'!E60 -> 1889.12 | F7: ='[1]Data Sheet'!F60 -> 2345.49 | G7: ='[1]Data Sheet'!G60 -> 2487.3 | H7: ='[1]Data Sheet'!H60 -> 2819.21 | I7: ='[1]Data Sheet'!I60 -> 3065.02 | ... K7: ='[1]Data Sheet'!K60 -> 3243.48
A8: Total | B8: ='[1]Data Sheet'!B61 -> 4108.8 | C8: ='[1]Data Sheet'!C61 -> 5187.92 | D8: ='[1]Data Sheet'!D61 -> 6237.95 | E8: ='[1]Data Sheet'!E61 -> 7829.54 | F8: ='[1]Data Sheet'!F61 -> 8000.09 | G8: ='[1]Data Sheet'!G61 -> 7526.6 | H8: ='[1]Data Sheet'!H61 -> 9350.85 | I8: ='[1]Data Sheet'!I61 -> 9071.5 | ... K8: ='[1]Data Sheet'!K61 -> 9730.32
A10: Net Block | B10: ='[1]Data Sheet'!B62 -> 1159.99 | C10: ='[1]Data Sheet'!C62 -> 1345.6 | D10: ='[1]Data Sheet'!D62 -> 1688.3 | E10: ='[1]Data Sheet'!E62 -> 1878.18 | F10: ='[1]Data Sheet'!F62 -> 1792.95 | G10: ='[1]Data Sheet'!G62 -> 1753.21 | H10: ='[1]Data Sheet'!H62 -> 2655.22 | I10: ='[1]Data Sheet'!I62 -> 2771.14 | ... K10: ='[1]Data Sheet'!K62 -> 2849.92
A11: Capital Work in Progress | B11: ='[1]Data Sheet'!B63 -> 30.07 | C11: ='[1]Data Sheet'!C63 -> 202.82 | D11: ='[1]Data Sheet'!D63 -> 101.24 | E11: ='[1]Data Sheet'!E63 -> 39.55 | F11: ='[1]Data Sheet'!F63 -> 116.52 | G11: ='[1]Data Sheet'!G63 -> 535.68 | H11: ='[1]Data Sheet'!H63 -> 105 | I11: ='[1]Data Sheet'!I63 -> 187.54 | ... K11: ='[1]Data Sheet'!K63 -> 39.04
A12: Investments | B12: ='[1]Data Sheet'!B64 -> 486.85 | C12: ='[1]Data Sheet'!C64 -> 1079.28 | D12: ='[1]Data Sheet'!D64 -> 1476.28 | E12: ='[1]Data Sheet'!E64 -> 2893.23 | F12: ='[1]Data Sheet'!F64 -> 2780.69 | G12: ='[1]Data Sheet'!G64 -> 1762.37 | H12: ='[1]Data Sheet'!H64 -> 3324.24 | I12: ='[1]Data Sheet'!I64 -> 2766.72 | ... K12: ='[1]Data Sheet'!K64 -> 3609.76
A13: Other Assets | B13: ='[1]Data Sheet'!B65 -> 2431.89 | C13: ='[1]Data Sheet'!C65 -> 2560.22 | D13: ='[1]Data Sheet'!D65 -> 2972.13 | E13: ='[1]Data Sheet'!E65 -> 3018.58 | F13: ='[1]Data Sheet'!F65 -> 3309.93 | G13: ='[1]Data Sheet'!G65 -> 3475.34 | H13: ='[1]Data Sheet'!H65 -> 3266.39 | I13: ='[1]Data Sheet'!I65 -> 3346.1 | ... K13: ='[1]Data Sheet'!K65 -> 3231.6
A14: Total | B14: ='[1]Data Sheet'!B66 -> 4108.8 | C14: ='[1]Data Sheet'!C66 -> 5187.92 | D14: ='[1]Data Sheet'!D66 -> 6237.95 | E14: ='[1]Data Sheet'!E66 -> 7829.54 | F14: ='[1]Data Sheet'!F66 -> 8000.09 | G14: ='[1]Data Sheet'!G66 -> 7526.6 | H14: ='[1]Data Sheet'!H66 -> 9350.85 | I14: ='[1]Data Sheet'!I66 -> 9071.5 | ... K14: ='[1]Data Sheet'!K66 -> 9730.32
A16: Working Capital | B16: =B13-B7 -> 1144.07 | C16: =C13-C7 -> 979.23 | D16: =D13-D7 -> 1143.45 | E16: =E13-E7 -> 1129.46 | F16: =F13-F7 -> 964.44 | G16: =G13-G7 -> 988.04 | H16: =H13-H7 -> 447.18 | I16: =I13-I7 -> 281.08 | ... K16: =K13-K7 -> -11.88
A17: Debtors | B17: ='[1]Data Sheet'!B67 -> 179.16 | C17: ='[1]Data Sheet'!C67 -> 304.6 | D17: ='[1]Data Sheet'!D67 -> 394.24 | E17: ='[1]Data Sheet'!E67 -> 320.36 | F17: ='[1]Data Sheet'!F67 -> 257.27 | G17: ='[1]Data Sheet'!G67 -> 331.93 | H17: ='[1]Data Sheet'!H67 -> 328.94 | I17: ='[1]Data Sheet'!I67 -> 393.33 | ... K17: ='[1]Data Sheet'!K67 -> 469.21
A18: Inventory | B18: ='[1]Data Sheet'!B68 -> 661.45 | C18: ='[1]Data Sheet'!C68 -> 652.79 | D18: ='[1]Data Sheet'!D68 -> 781.38 | E18: ='[1]Data Sheet'!E68 -> 740.96 | F18: ='[1]Data Sheet'!F68 -> 1091.49 | G18: ='[1]Data Sheet'!G68 -> 1367.49 | H18: ='[1]Data Sheet'!H68 -> 1193.26 | I18: ='[1]Data Sheet'!I68 -> 1181.22 | ... K18: ='[1]Data Sheet'!K68 -> 1345.93
A20: Debtor Days | B20: =IF('[1]Profit & Loss'!B4>0,'Balance Sheet'!B17/('[1]Profit & Loss'!B4/365),0) -> 0 | C20: =IF('[1]Profit & Loss'!C4>0,'Balance Sheet'!C17/('[1]Profit & Loss'!C4/365),0) -> 0 | D20: =IF('[1]Profit & Loss'!D4>0,'Balance Sheet'!D17/('[1]Profit & Loss'!D4/365),0) -> 0 | E20: =IF('[1]Profit & Loss'!E4>0,'Balance Sheet'!E17/('[1]Profit & Loss'!E4/365),0) -> 0 | F20: =IF('[1]Profit & Loss'!F4>0,'Balance Sheet'!F17/('[1]Profit & Loss'!F4/365),0) -> 0 | G20: =IF('[1]Profit & Loss'!G4>0,'Balance Sheet'!G17/('[1]Profit & Loss'!G4/365),0) -> 0 | H20: =IF('[1]Profit & Loss'!H4>0,'Balance Sheet'!H17/('[1]Profit & Loss'!H4/365),0) -> 0 | I20: =IF('[1]Profit & Loss'!I4>0,'Balance Sheet'!I17/('[1]Profit & Loss'!I4/365),0) -> 0 | ... K20: =IF('[1]Profit & Loss'!K4>0,'Balance Sheet'!K17/('[1]Profit & Loss'!K4/365),0) -> 0
A21: Inventory Turnover | B21: =IF('Balance Sheet'!B18>0,'[1]Profit & Loss'!B4/'Balance Sheet'!B18,0) -> 0 | C21: =IF('Balance Sheet'!C18>0,'[1]Profit & Loss'!C4/'Balance Sheet'!C18,0) -> 0 | D21: =IF('Balance Sheet'!D18>0,'[1]Profit & Loss'!D4/'Balance Sheet'!D18,0) -> 0 | E21: =IF('Balance Sheet'!E18>0,'[1]Profit & Loss'!E4/'Balance Sheet'!E18,0) -> 0 | F21: =IF('Balance Sheet'!F18>0,'[1]Profit & Loss'!F4/'Balance Sheet'!F18,0) -> 0 | G21: =IF('Balance Sheet'!G18>0,'[1]Profit & Loss'!G4/'Balance Sheet'!G18,0) -> 0 | H21: =IF('Balance Sheet'!H18>0,'[1]Profit & Loss'!H4/'Balance Sheet'!H18,0) -> 0 | I21: =IF('Balance Sheet'!I18>0,'[1]Profit & Loss'!I4/'Balance Sheet'!I18,0) -> 0 | ... K21: =IF('Balance Sheet'!K18>0,'[1]Profit & Loss'!K4/'Balance Sheet'!K18,0) -> 0
A23: Return on Equity | B23: =IF(SUM('Balance Sheet'!B4:B5)>0,'[1]Profit & Loss'!B12/SUM('Balance Sheet'!B4:B5),"") -> 0 | C23: =IF(SUM('Balance Sheet'!C4:C5)>0,'[1]Profit & Loss'!C12/SUM('Balance Sheet'!C4:C5),"") -> 0 | D23: =IF(SUM('Balance Sheet'!D4:D5)>0,'[1]Profit & Loss'!D12/SUM('Balance Sheet'!D4:D5),"") -> 0 | E23: =IF(SUM('Balance Sheet'!E4:E5)>0,'[1]Profit & Loss'!E12/SUM('Balance Sheet'!E4:E5),"") -> 0 | F23: =IF(SUM('Balance Sheet'!F4:F5)>0,'[1]Profit & Loss'!F12/SUM('Balance Sheet'!F4:F5),"") -> 0 | G23: =IF(SUM('Balance Sheet'!G4:G5)>0,'[1]Profit & Loss'!G12/SUM('Balance Sheet'!G4:G5),"") -> 0 | H23: =IF(SUM('Balance Sheet'!H4:H5)>0,'[1]Profit & Loss'!H12/SUM('Balance Sheet'!H4:H5),"") -> 0 | I23: =IF(SUM('Balance Sheet'!I4:I5)>0,'[1]Profit & Loss'!I12/SUM('Balance Sheet'!I4:I5),"") -> 0 | ... K23: =IF(SUM('Balance Sheet'!K4:K5)>0,'[1]Profit & Loss'!K12/SUM('Balance Sheet'!K4:K5),"") -> 0
A24: Return on Capital Emp | C24: =IF((B4+B5+B6+C4+C5+C6)>0,('[1]Profit & Loss'!C10+'[1]Profit & Loss'!C9)*2/(B4+B5+B6+C4+C5+C6),"") -> 0 | D24: =IF((C4+C5+C6+D4+D5+D6)>0,('[1]Profit & Loss'!D10+'[1]Profit & Loss'!D9)*2/(C4+C5+C6+D4+D5+D6),"") -> 0 | E24: =IF((D4+D5+D6+E4+E5+E6)>0,('[1]Profit & Loss'!E10+'[1]Profit & Loss'!E9)*2/(D4+D5+D6+E4+E5+E6),"") -> 0 | F24: =IF((E4+E5+E6+F4+F5+F6)>0,('[1]Profit & Loss'!F10+'[1]Profit & Loss'!F9)*2/(E4+E5+E6+F4+F5+F6),"") -> 0 | G24: =IF((F4+F5+F6+G4+G5+G6)>0,('[1]Profit & Loss'!G10+'[1]Profit & Loss'!G9)*2/(F4+F5+F6+G4+G5+G6),"") -> 0 | H24: =IF((G4+G5+G6+H4+H5+H6)>0,('[1]Profit & Loss'!H10+'[1]Profit & Loss'!H9)*2/(G4+G5+G6+H4+H5+H6),"") -> 0 | I24: =IF((H4+H5+H6+I4+I5+I6)>0,('[1]Profit & Loss'!I10+'[1]Profit & Loss'!I9)*2/(H4+H5+H6+I4+I5+I6),"") -> 0 | J24: =IF((I4+I5+I6+J4+J5+J6)>0,('[1]Profit & Loss'!J10+'[1]Profit & Loss'!J9)*2/(I4+I5+I6+J4+J5+J6),"") -> 0 | K24: =IF((J4+J5+J6+K4+K5+K6)>0,('[1]Profit & Loss'!K10+'[1]Profit & Loss'!K9)*2/(J4+J5+J6+K4+K5+K6),"") -> 0

Sheet Cash Flow
A1: ='[1]Balance Sheet'!A1 -> 0 | E1: =UPDATE -> 0 | J1: SCREENER.IN
A3: Narration | B3: ='[1]Data Sheet'!B81 -> 42825 | C3: ='[1]Data Sheet'!C81 -> 43190 | D3: ='[1]Data Sheet'!D81 -> 43555 | E3: ='[1]Data Sheet'!E81 -> 43921 | F3: ='[1]Data Sheet'!F81 -> 44286 | G3: ='[1]Data Sheet'!G81 -> 44651 | H3: ='[1]Data Sheet'!H81 -> 45016 | I3: ='[1]Data Sheet'!I81 -> 45382 | ... K3: ='[1]Data Sheet'!K81 -> 46112
A4: Cash from Operating Activity | B4: ='[1]Data Sheet'!B82 -> 441.28 | C4: ='[1]Data Sheet'!C82 -> 1248.77 | D4: ='[1]Data Sheet'!D82 -> 1155.78 | E4: ='[1]Data Sheet'!E82 -> 1484.53 | F4: ='[1]Data Sheet'!F82 -> 1851.07 | G4: ='[1]Data Sheet'!G82 -> 1299.52 | H4: ='[1]Data Sheet'!H82 -> 2526.21 | I4: ='[1]Data Sheet'!I82 -> 2572.98 | ... K4: ='[1]Data Sheet'!K82 -> 2611.6
A5: Cash from Investing Activity | B5: ='[1]Data Sheet'!B83 -> -149.85 | C5: ='[1]Data Sheet'!C83 -> -956.52 | D5: ='[1]Data Sheet'!D83 -> -852.22 | E5: ='[1]Data Sheet'!E83 -> -1525.93 | F5: ='[1]Data Sheet'!F83 -> 458.82 | G5: ='[1]Data Sheet'!G83 -> 914.19 | H5: ='[1]Data Sheet'!H83 -> -1507 | I5: ='[1]Data Sheet'!I83 -> 485.44 | ... K5: ='[1]Data Sheet'!K83 -> -741.38
A6: Cash from Financing Activity | B6: ='[1]Data Sheet'!B84 -> -295.08 | C6: ='[1]Data Sheet'!C84 -> -231.75 | D6: ='[1]Data Sheet'!D84 -> -352.68 | E6: ='[1]Data Sheet'!E84 -> 57.94 | F6: ='[1]Data Sheet'!F84 -> -2243.69 | G6: ='[1]Data Sheet'!G84 -> -2245.84 | H6: ='[1]Data Sheet'!H84 -> -1028.37 | I6: ='[1]Data Sheet'!I84 -> -2839.13 | ... K6: ='[1]Data Sheet'!K84 -> -1782.62
A7: Net Cash Flow | B7: ='[1]Data Sheet'!B85 -> -3.65 | C7: ='[1]Data Sheet'!C85 -> 60.5 | D7: ='[1]Data Sheet'!D85 -> -49.12 | E7: ='[1]Data Sheet'!E85 -> 16.54 | F7: ='[1]Data Sheet'!F85 -> 66.2 | G7: ='[1]Data Sheet'!G85 -> -32.13 | H7: ='[1]Data Sheet'!H85 -> -9.16 | I7: ='[1]Data Sheet'!I85 -> 219.29 | ... K7: ='[1]Data Sheet'!K85 -> 87.6

Sheet Raw FS
C1: BRITANNIA INDUSTRIES LIMITED
B3: ="Income Statement"&" "&"-"&" "&'Data Sheet'!B1 -> Income Statement - BRITANNIA INDUSTRIES LTD
B5: Particulars | C5: ='Cash Flow Data'!D2 -> 42795 | D5: =C5+365 -> 43160 | E5: =D5+365 -> 43525 | F5: =E5+366 -> 43891 | G5: =F5+366 -> 44257 | H5: =G5+366 -> 44623 | I5: =H5+366 -> 44989 | J5: =I5+366 -> 45355 | K5: =J5+366 -> 45721 | L5: =K5+366 -> 46087
B7: Equity Capital | C7: 24 | D7: 24 | E7: 24 | F7: 24 | G7: 24 | H7: 24 | I7: 24 | J7: 24 | K7: 24 | L7: 24
B8: Reserves | C8: 2672 | D8: 3382 | E8: 4229 | F8: 4379 | G8: 3524 | H8: 2534 | I8: 3510 | J8: 3917 | K8: 4332 | L8: 5082
B9: Borrowings -
B10: Long term Borrowings | C10: 31 | D10: 85 | E10: 62 | F10: 766 | G10: 748 | H10: 707 | I10: 1552 | J10: 905 | K10: 713 | L10: 286
B11: Short term Borrowings | C11: 84 | D11: 94 | E11: 76 | F11: 748 | G11: 1339 | H11: 1759 | I11: 1429 | J11: 1136 | K11: 512 | L11: 1072
B12: Lease Liabilities | C12: 0 | D12: 0 | E12: 0 | F12: 0 | G12: 0 | H12: 16 | I12: 17 | J12: 24 | K12: 22 | L12: 22
B13: Other Borrowings | C13: 9 | D13: 22 | E13: 18 | F13: 24 | G13: 20 | H13: 0 | I13: 0 | J13: 0 | K13: 0 | L13: 0
B14: Other Liabilities -
B15: Non controlling int | C15: 3 | D15: 13 | E15: 33 | F15: 36 | G15: 36 | H15: 28 | I15: 30 | J15: 24 | K15: 26 | L15: 29
B16: Trade Payables | C16: 757 | D16: 994 | E16: 1141 | F16: 1047 | G16: 1315 | H16: 1323 | I16: 1449 | J16: 1627 | K16: 1752 | L16: 1896
B17: Advance from Customers | C17: 17 | D17: 31 | E17: 41 | F17: 78 | G17: 55 | H17: 34 | I17: 55 | J17: 42 | K17: 46 | L17: 53
B18: Other liability items | C18: 511 | D18: 543 | E18: 615 | F18: 729 | G18: 940 | H18: 1103 | I18: 1285 | J18: 1371 | K18: 1410 | L18: 1265
B19: Total Liabilities | C19: =SUM(C7:C18) -> 4108 | D19: =SUM(D7:D18) -> 5188 | E19: =SUM(E7:E18) -> 6239 | F19: =SUM(F7:F18) -> 7831 | G19: =SUM(G7:G18) -> 8001 | H19: =SUM(H7:H18) -> 7528 | I19: =SUM(I7:I18) -> 9351 | J19: =SUM(J7:J18) -> 9070 | ... L19: =SUM(L7:L18) -> 9729
B21: Fixed Assets -
B22: Land | C22: 128 | D22: 246 | E22: 247 | F22: 319 | G22: 326 | H22: 334 | I22: 376 | J22: 384 | K22: 395 | L22: 397
B23: Building | C23: 376 | D23: 515 | E23: 660 | F23: 732 | G23: 758 | H23: 782 | I23: 1143 | J23: 1298 | K23: 1395 | L23: 1429
B24: Plant Machinery | C24: 641 | D24: 705 | E24: 1053 | F24: 1305 | G24: 1407 | H24: 1546 | I24: 2303 | J24: 2543 | K24: 2844 | L24: 3028
B25: Equipments | C25: 22 | D25: 25 | E25: 31 | F25: 40 | G25: 46 | H25: 52 | I25: 61 | J25: 75 | K25: 81 | L25: 79
B26: Furniture n fittings | C26: 25 | D26: 25 | E26: 28 | F26: 31 | G26: 32 | H26: 32 | I26: 43 | J26: 46 | K26: 49 | L26: 50
B27: Vehicles | C27: 2 | D27: 2 | E27: 3 | F27: 5 | G27: 5 | H27: 6 | I27: 10 | J27: 10 | K27: 9 | L27: 9
B28: Intangible Assets | C28: 128 | D28: 128 | E28: 134 | F28: 143 | G28: 139 | H28: 140 | I28: 130 | J28: 131 | K28: 134 | L28: 146
B29: Other fixed assets | C29: 36 | D29: 36 | E29: 40 | F29: 43 | G29: 46 | H29: 57 | I29: 86 | J29: 72 | K29: 67 | L29: 67
B30: Gross Block | C30: =SUM(C22:C29) -> 1358 | D30: =SUM(D22:D29) -> 1682 | E30: =SUM(E22:E29) -> 2196 | F30: =SUM(F22:F29) -> 2618 | G30: =SUM(G22:G29) -> 2759 | H30: =SUM(H22:H29) -> 2949 | I30: =SUM(I22:I29) -> 4152 | J30: =SUM(J22:J29) -> 4559 | ... L30: =SUM(L22:L29) -> 5205
B31: Accumulated Depreciation | C31: 199 | D31: 338 | E31: 507 | F31: 739 | G31: 967 | H31: 1195 | I31: 1495 | J31: 1788 | K31: 2070 | L31: 2356
B32: Net Block | C32: =C30-C31 -> 1159 | D32: =D30-D31 -> 1344 | E32: =E30-E31 -> 1689 | F32: =F30-F31 -> 1879 | G32: =G30-G31 -> 1792 | H32: =H30-H31 -> 1754 | I32: =I30-I31 -> 2657 | J32: =J30-J31 -> 2771 | ... L32: =L30-L31 -> 2849
B34: CWIP | C34: 30 | D34: 203 | E34: 101 | F34: 40 | G34: 117 | H34: 536 | I34: 105 | J34: 188 | K34: 89 | L34: 39
B35: Investments | C35: 487 | D35: 1079 | E35: 1476 | F35: 2893 | G35: 2781 | H35: 1762 | I35: 3324 | J35: 2767 | K35: 2865 | L35: 3610
B37: Other Assets -
B38: Inventories | C38: 661 | D38: 653 | E38: 781 | F38: 741 | G38: 1091 | H38: 1367 | I38: 1193 | J38: 1181 | K38: 1237 | L38: 1346
B39: Trade receivables - | C39: 179 | D39: 305 | E39: 394 | F39: 320 | G39: 257 | H39: 332 | I39: 329 | J39: 393 | K39: 449 | L39: 469
B40: Cash Equivalents | C40: 121 | D40: 186 | E40: 110 | F40: 123 | G40: 211 | H40: 185 | I40: 198 | J40: 446 | K40: 312 | L40: 352
B41: Loans n Advances | C41: 217 | D41: 150 | E41: 63 | F41: 50 | G41: 45 | H41: 63 | I41: 83 | J41: 62 | K41: 67 | L41: 55
B42: Other asset items | C42: 1254 | D42: 1267 | E42: 1623 | F42: 1784 | G42: 1705 | H42: 1528 | I42: 1463 | J42: 1263 | K42: 914 | L42: 1009
B43: Total Assets | C43: =SUM(C32:C42) -> 4108 | D43: =SUM(D32:D42) -> 5187 | E43: =SUM(E32:E42) -> 6237 | F43: =SUM(F32:F42) -> 7830 | G43: =SUM(G32:G42) -> 7999 | H43: =SUM(H32:H42) -> 7527 | I43: =SUM(I32:I42) -> 9352 | J43: =SUM(J32:J42) -> 9071 | ... L43: =SUM(L32:L42) -> 9729
B46: Particulars | C46: =C5 -> 42795 | D46: =C46+365 -> 43160 | E46: =D46+365 -> 43525 | F46: =E46+366 -> 43891 | G46: =F46+366 -> 44257 | H46: =G46+366 -> 44623 | I46: =H46+366 -> 44989 | J46: =I46+366 -> 45355 | K46: =J46+366 -> 45721 | L46: =K46+366 -> 46087
B48: Cash from Operating Activity - | C48: 441 | D48: 1249 | E48: 1156 | F48: 1485 | G48: 1851 | H48: 1300 | I48: 2526 | J48: 2573 | K48: 2491 | L48: 2612
B49: Profit from operations | C49: 1289 | D49: 1517 | E49: 1754 | F49: 1860 | G49: 2540 | H49: 2214 | I49: 2846 | J49: 3177 | K49: 3174 | L49: 3555
B50: Receivables | C50: -9 | D50: -125 | E50: -87 | F50: 79 | G50: 61 | H50: -72 | I50: 1 | J50: -64 | K50: -53 | L50: -13
B51: Inventory | C51: -221 | D51: 9 | E51: -127 | F51: 43 | G51: -351 | H51: -275 | I51: 177 | J51: 13 | K51: -54 | L51: -105
B52: Payables | C52: 0 | D52: 0 | E52: 0 | F52: 0 | G52: 0 | H52: 64 | I52: 292 | J52: 237 | K52: 202 | L52: 25
B53: Loans Advances | C53: 0 | D53: 0 | E53: 0 | F53: 0 | G53: 0 | H53: 0 | I53: 0 | J53: 0 | K53: 0 | L53: 0
B54: Other WC items | C54: -221 | D54: 345 | E54: 211 | F54: 6 | G54: 234 | H54: -44 | I54: -65 | J54: -25 | K54: -89 | L54: -28
B55: Working capital changes | C55: -451 | D55: 228 | E55: -2 | F55: 127 | G55: -56 | H55: -327 | I55: 406 | J55: 161 | K55: 6 | L55: -121
B56: Direct taxes | C56: -397 | D56: -496 | E56: -596 | F56: -503 | G56: -633 | H56: -587 | I56: -726 | J56: -765 | K56: -689 | L56: -822
B57: Cash from Investing Activity - | C57: -150 | D57: -957 | E57: -852 | F57: -1526 | G57: 459 | H57: 914 | I57: -1507 | J57: 485 | K57: 69 | L57: -741
B58: Fixed assets purchased | C58: -360 | D58: -423 | E58: -401 | F58: -244 | G58: -242 | H58: -550 | I58: -711 | J58: -553 | K58: -375 | L58: -206
B59: Fixed assets sold | C59: 8 | D59: 2 | E59: 2 | F59: 1 | G59: 2 | H59: 3 | I59: 78 | J59: 65 | K59: 5 | L59: 2
... B80: CFO/OP | C80: 0.66 | D80: 1.16 | E80: 1.01 | F80: 1.08 | G80: 0.99 | H80: 0.86 | I80: 1.15 | J80: 1.05 | K80: 1 | L80: 0.98

Sheet One Page Profile
B2: ='Data Sheet'!B1 -> BRITANNIA INDUSTRIES LTD
B3: (BRITANNIA) | BSE Code: 500825)
B4: INR 5,181.50 1st Sept 2026
B5: 52 Week (High - INR 6,336.95 & Low - 5,038)
L6: Prepared by Pushti Gandhi
B8: Britannia Industries Limited is an Indian multinational food products company, which sells biscuits, breads, and dairy products. Founded
B9: in 1892, it is one of India's oldest existing companies and currently part of the Wadia Group headed by Nusli Wadia. As of 2023, about 80%
B10: of its revenues came from biscuit products. It is one of India's leading food companies with a 100 year legacy and annual revenues in excess
B11: of Rs. 16,000 Cr. Britannia is among the most trusted food brands, and manufactures India's favorite brands like Good Day, Tiger, NutriChoice,
B12: Milk Bikis and Marigold.
B14: INR (Crs.)
B15: Key Financial Metrics | C15: ='Data Sheet'!G16 -> 44651 | D15: ='Data Sheet'!H16 -> 45016 | E15: ='Data Sheet'!I16 -> 45382 | F15: ='Data Sheet'!J16 -> 45747 | G15: ='Data Sheet'!K16 -> 46112 | I15: Share Price - 5year
B17: Total Sales | C17: ='Profit & Loss'!G4 -> 14136.26 | D17: ='Profit & Loss'!H4 -> 16300.55 | E17: ='Profit & Loss'!I4 -> 16769.27 | F17: ='Profit & Loss'!J4 -> 17942.67 | G17: ='Profit & Loss'!K4 -> 19151.59
B18: Sales Growth (y-o-y) | C18: ='Profit & Loss'!G28 -> 0.076134999 | D18: ='Profit & Loss'!H28 -> 0.15310202 | E18: ='Profit & Loss'!I28 -> 0.028754858 | F18: ='Profit & Loss'!J28 -> 0.069973231 | G18: ='Profit & Loss'!K28 -> 0.067376817
B19: Gross Profit Margin (%) | C19: ='Historical FS'!H19 -> 0.27332052 | D19: ='Historical FS'!I19 -> 0.29967823 | E19: ='Historical FS'!J19 -> 0.31994058 | F19: ='Historical FS'!K19 -> 0.29661249 | G19: ='Historical FS'!L19 -> 0.30970588
B20: EBITDA Margin (%) | C20: ='Historical FS'!H25 -> 0.15572082 | D20: ='Historical FS'!I25 -> 0.1736696 | E20: ='Historical FS'!J25 -> 0.18883648 | F20: ='Historical FS'!K25 -> 0.17703107 | G20: ='Historical FS'!L25 -> 0.18350121
B21: EBIT Margin (%) | C21: ='Historical FS'!H34 -> 0.14153461 | D21: ='Historical FS'!I34 -> 0.15981056 | E21: ='Historical FS'!J34 -> 0.17091919 | F21: ='Historical FS'!K34 -> 0.15956767 | G21: ='Historical FS'!L34 -> 0.16591364
B22: Net Profit Margin (%) | C22: ='Historical FS'!H43 -> 0.091546845 | D22: ='Historical FS'!I43 -> 0.10548417 | E22: ='Historical FS'!J43 -> 0.11467047 | F22: ='Historical FS'!K43 -> 0.11010401 | G22: ='Historical FS'!L43 -> 0.12077222
B23: Earnings Per Share (in Rs.) | C23: ='Historical FS'!H47 -> 53.720631 | D23: ='Historical FS'!I47 -> 71.37609 | E23: ='Historical FS'!J47 -> 79.823163 | F23: ='Historical FS'!K47 -> 82.007472 | G23: ='Historical FS'!L47 -> 96.014114
B24: EPS Growth (y-o-y) | C24: ='Historical FS'!H48 -> -0.15830038 | D24: ='Historical FS'!I48 -> 0.32865323 | E24: ='Historical FS'!J48 -> 0.11834598 | F24: ='Historical FS'!K48 -> 0.027364348 | G24: ='Historical FS'!L48 -> 0.17079714
B25: Dividend Per Share (in Rs) | C25: ='Historical FS'!H50 -> 56.499792 | D25: ='Historical FS'!I50 -> 72 | E25: ='Historical FS'!J50 -> 73.500208 | F25: ='Historical FS'!K50 -> 75 | G25: ='Historical FS'!L50 -> 90.499792
B26: DPS Growth (y-o-y) | C26: ='Historical FS'!H50/'Historical FS'!G50-1 -> -0.64127163 | D26: ='Historical FS'!I50/'Historical FS'!H50-1 -> 0.27434096 | E26: ='Historical FS'!J50/'Historical FS'!I50-1 -> 0.020836216 | F26: ='Historical FS'!K50/'Historical FS'!J50-1 -> 0.020405282 | G26: ='Historical FS'!L50/'Historical FS'!K50-1 -> 0.2066639
B28: Key Financial Ratios | C28: =C15 -> 44651 | D28: =D15 -> 45016 | E28: =E15 -> 45382 | F28: =F15 -> 45747 | G28: =G15 -> 46112 | I28: Volume - 5year
B30: Price to Earnings | C30: ='Profit & Loss'!G14 -> 50.656586 | D30: ='Profit & Loss'!H14 -> 44.845352 | E30: ='Profit & Loss'!I14 -> 55.290896 | F30: ='Profit & Loss'!J14 -> 54.58681 | G30: ='Profit & Loss'!K14 -> 51.56526
B31: EV/EBITDA | C31: ='Profit & Loss'!G35 -> 36.132338 | D31: ='Profit & Loss'!H35 -> 37.768768 | E31: ='Profit & Loss'!I35 -> 37.873027 | F31: ='Profit & Loss'!J35 -> 37.735667 | G31: ='Profit & Loss'!K35 -> 37.4659
B32: EV/Sales | C32: ='Profit & Loss'!G36 -> 5.6265572 | D32: ='Profit & Loss'!H36 -> 6.5592869 | E32: ='Profit & Loss'!I36 -> 7.1518094 | F32: ='Profit & Loss'!J36 -> 6.6803854 | G32: ='Profit & Loss'!K36 -> 6.8750381
B33: Price to Book Value | C33: ='Profit & Loss'!G39 -> 30.195135 | D33: ='Profit & Loss'!H39 -> 29.460283 | E33: ='Profit & Loss'!I39 -> 30.016849 | F33: ='Profit & Loss'!J39 -> 27.304308 | G33: ='Profit & Loss'!K39 -> 25.582794
B34: Return on Equity (%) | C34: ='Ratio Analysis'!H29 -> 0.505895 | D34: ='Ratio Analysis'!I29 -> 0.48650782 | E34: ='Ratio Analysis'!J29 -> 0.48786762 | F34: ='Ratio Analysis'!K29 -> 0.45355532 | G34: ='Ratio Analysis'!L29 -> 0.45294288
B35: Return on Capital Employed (%) | C35: ='Ratio Analysis'!H27 -> 0.39703332 | D35: ='Ratio Analysis'!I27 -> 0.39882786 | E35: ='Ratio Analysis'!J27 -> 0.47718298 | F35: ='Ratio Analysis'!K27 -> 0.51105899 | G35: ='Ratio Analysis'!L27 -> 0.48983943
B37: Top Shareholders of BRITANNIA | C37: N. of Shares Held (In Crs.) | E37: (%) Holding | F37: Market Value (In Crs.) | I37: Shareholding Pattern
B38: ASSOCIATED BISCUITS INTERNATIONAL LIMITED | D38: 10.7809 | E38: 0.4476 | G38: 51865.832
B39: ICICI PRUDENTIAL INDIA OPPORTUNITIES FUND | D39: 1.0450013 | E39: 0.0434 | G39: 5027.3968
B40: LIFE INSURANCE CORPORATION OF INDIA | D40: 0.6534873 | E40: 0.0271 | G40: 3143.8621
B41: HDFC MUTUAL FUND - HDFC MNC FUND | D41: 0.4236895 | E41: 0.0176 | G41: 2038.3278
B42: LICI ASM NON PAR | D42: 0.3060463 | E42: 0.0127 | G42: 1472.3581
B44: Managerial Remuneration | C44: Designation | D44: Remuneration (In Crs.) | F44: X of Median Salary | I44: Capital Structure
B46: Mr. Nusli N. Wadia | C46: Chairman | D46: 5.32 | F46: 85.94X | I46: Share Price on XXX | N46: ='Data Sheet'!B8 -> 5250
B47: Mr. Rakshit Hargave | C47: CEO & MD | D47: 8.5 | F47: 50.2X | I47: No. of Share O/s | N47: ='Data Sheet'!B6 -> 24.077305
B48: Mr. N. Venkataraman | C48: ED & CFO | D48: 4.4 | F48: 69.20X | I48: Market Capitalization | N48: =N46*N47 -> 126405.85
I49: Less: Cash & Equivalents | N49: ='Data Sheet'!K69*-1 -> -352.44
B50: Britannia Industries had 5,682 employees as of March 31, 2026. The number of employees decreased by -1.90% | I50: Add: Debt | N50: ='Data Sheet'!K59 -> 1380.28
B51: compared to the previous year. | I51: Add: Minority Interest | N51: 29.32
I52: Enterprise Value | N52: =SUM(N48:N51) -> 127463.01
B55: Recent Updates
B57: * Britannia Industries Ltd recently appointed N.Venkataraman as Deputy MD and Ramamurthy Jayaraman as CFO, effective October 1 2026.
B58: * The Net Profit rose 14% year on year to Rs. 593 Cr. And revenue reached Rs. 4,964 crores, marking a 9.5% increase YoY and strong volume expansion at roughly 9% beating estimates.
B59: * To actively counter deep regional biscuit setups and local pricing plays, the company reorganized its core sales and marketing teams into decentralized regional clusters. The strategy
B60: is leaning towards digital models, as quick-commere and e-commerce retail networks scaled significantly.
B61: * Management is tracking acute commodity headwinds, specifically regarding near term cost inflation vectors across palm oil, sugar, and industrial fuel.
B62: * Biscuits remain the company's financial powerhouse. Recent performance was boosted by healthy volume recovery as retail pricing stabilized. Strategic pushes feature the premiumization
B63: of mass products, including the 50-50 Dipped range and Doodh Marie Gold. Under its "Many Indias" operating framework, Britannia is reclustering its sales teams to launch hyper-local
B64: flavor variants to fight regional biscuit brands.
B65: * The cake segment has refreshed its portfolio with holiday-focused launches inluding Double Choco Chip, Veg Plum Cake, and Nut & Raisin Romance Cake. The company deployed generative
B66: AI modelling to launch nationwide digital campaigns for its premium cake selections.
B67: * Britannia entered into a definitive agreement to acquire a controlling stake in Northeast India's leading snacks manufacturer, Kishlay Foods. Valued around INR600-700 Crore, this acquisition
... B75: basis of this report. It is advisable to consult SEBI registered research analyst before making any investments.

Sheet Britannia 5 Yrs data
A1: Britannia Industries
J3: 10000000
A4: Date | B4: Adj Close | C4: Volume
A5: 44469 | B5: 3657.86 | C5: 0.217501 | E5: 1000000
A6: 44470 | B6: 3632.06 | C6: 0.181917 | H6: Shareholder's name | I6: Total Shares Held | J6: Shareholding (%) | K6: Quarter Ending | L6: Share Price
A7: 44473 | B7: 3605.94 | C7: 0.372752 | H7: ASSOCIATED BISCUITS INTERNATIONAL LIMITED | I7: 10.7809 | J7: 44.76 | K7: 46174 | L7: =4810.9*I7 -> 51865.832
A8: 44474 | B8: 3596.03 | C8: 0.131731 | H8: ICICI PRUDENTIAL INDIA OPPORTUNITIES FUND | I8: 1.0450013 | J8: 4.34 | K8: 46174 | L8: =4810.9*I8 -> 5027.3968
A9: 44475 | B9: 3648.27 | C9: 0.40984 | H9: LIFE INSURANCE CORPORATION OF INDIA | I9: 0.6534873 | J9: 2.71 | K9: 46174 | L9: =4810.9*I9 -> 3143.8621
A10: 44476 | B10: 3613.07 | C10: 0.187556 | H10: HDFC MUTUAL FUND - HDFC MNC FUND | I10: 0.4236895 | J10: 1.76 | K10: 46174 | L10: =4810.9*I10 -> 2038.3278
A11: 44477 | B11: 3597.05 | C11: 0.31687 | H11: LICI ASM NON PAR | I11: 0.3060463 | J11: 1.27 | K11: 46174 | L11: =4810.9*I11 -> 1472.3581
A12: 44480 | B12: 3557.5 | C12: 0.253051 | H12: VALLETORT ENTERPRISES PTE LTD | I12: 0.278502 | J12: 1.16 | K12: 46174 | L12: =4810.9*I12 -> 1339.8453
A13: 44481 | B13: 3582.83 | C13: 0.253262 | H13: NACUPA ENTERPRISES PTE LTD | I13: 0.278502 | J13: 1.16 | K13: 46174 | L13: =4810.9*I13 -> 1339.8453
A14: 44482 | B14: 3597.42 | C14: 0.174222 | H14: DOWBIGGIN ENTERPRISES PTE LTD | I14: 0.278502 | J14: 1.16 | K14: 46174 | L14: =4810.9*I14 -> 1339.8453
A15: 44483 | B15: 3607.75 | C15: 0.299078 | H15: BANNATYNE ENTERPRISES PTE LTD | I15: 0.278311 | J15: 1.16 | K15: 46174 | L15: =4810.9*I15 -> 1338.9264
A16: 44487 | B16: 3554.49 | C16: 0.256837 | H16: SPARGO ENTERPRISES PTE LTD | I16: 0.278502 | J16: 1.16 | K16: 46174 | L16: =4810.9*I16 -> 1339.8453
A17: 44488 | B17: 3516.09 | C17: 0.282932
A18: 44489 | B18: 3484.69 | C18: 0.523002
A19: 44490 | B19: 3440.55 | C19: 0.335589
A20: 44491 | B20: 3418 | C20: 0.192033 | H20: FII | I20: 0.134
A21: 44494 | B21: 3363.39 | C21: 0.289025 | H21: DII | I21: 0.2088
A22: 44495 | B22: 3420.59 | C22: 0.326825 | H22: Public & Government | I22: 0.1517
A23: 44496 | B23: 3425.27 | C23: 0.441016 | H23: Promoter | I23: 0.5055
A24: 44497 | B24: 3410.5 | C24: 0.193658
A25: 44498 | B25: 3404.8 | C25: 0.283538
A26: 44501 | B26: 3407.02 | C26: 0.139766
A27: 44502 | B27: 3411.42 | C27: 0.151547
A28: 44503 | B28: 3362.28 | C28: 0.185296
A29: 44504 | B29: 3362.28 | C29: -
A30: 44508 | B30: 3443.66 | C30: 0.336938
A31: 44509 | B31: 3354.64 | C31: 1.399094
A32: 44510 | B32: 3425.87 | C32: 0.706755
A33: 44511 | B33: 3374.83 | C33: 0.298625
A34: 44512 | B34: 3416.1 | C34: 0.27506
A35: 44515 | B35: 3466.72 | C35: 0.320669
A36: 44516 | B36: 3418.69 | C36: 0.199179
A37: 44517 | B37: 3348.57 | C37: 0.250996
A38: 44518 | B38: 3308.33 | C38: 0.248828
A39: 44522 | B39: 3317.59 | C39: 0.364653
A40: 44523 | B40: 3392.2 | C40: 0.365672
A41: 44524 | B41: 3356.26 | C41: 0.149025
... A182: 44729 | B182: 3086.48 | C182: 0.52737
A183: 44732 | C183: 0
A184: 44732 | B184: 3183.53 | C184: 0.364703
A185: 44733 | B185: 3231.31 | C185: 0.223641
A186: 44734 | B186: 3207.14 | C186: 0.170854
A187: 44735 | B187: 3214.49 | C187: 0.351311
A188: 44736 | B188: 3269.04 | C188: 0.301133
A189: 44739 | B189: 3259.39 | C189: 0.41973
A190: 44740 | B190: 3236.39 | C190: 0.182574
A191: 44741 | B191: 3207.61 | C191: 0.374478
A192: 44742 | B192: 3266.26 | C192: 0.479308
A193: 44743 | B193: 3377.4 | C193: 0.292487
A194: 44746 | B194: 3486.8 | C194: 0.614359
A195: 44747 | B195: 3445.48 | C195: 0.612519
... A240: 44813 | B240: 3438.79 | C240: 0.134487
A241: 44816 | B241: 3438.79 | C241: -
A242: 44817 | B242: 3540.75 | C242: 0.398871
A243: 44818 | B243: 3530.66 | C243: 0.389253
A244: 44819 | B244: 3506.68 | C244: 0.311462
A245: 44820 | B245: 3429.42 | C245: 0.559137
A246: 44823 | B246: 3384.94 | C246: 0.211795
A247: 44824 | B247: 3439.83 | C247: 0.346604
A248: 44825 | B248: 3548.24 | C248: 0.773841
A249: 44826 | B249: 3605.06 | C249: 0.687172
A250: 44827 | B250: 3577.49 | C250: 0.326581
A251: 44830 | B251: 3568.83 | C251: 0.626882
A252: 44831 | B252: 3603.36 | C252: 0.58476
A253: 44832 | B253: 3630.73 | C253: 0.364917
... A269: 44855 | B269: 3573.73 | C269: 0.404955
A270: 44858 | B270: 3573.73 | C270: -
A271: 44859 | B271: 3498.72 | C271: 0.228569
A272: 44861 | B272: 3538.48 | C272: 0.317971
A273: 44862 | B273: 3559.59 | C273: 0.215005
A274: 44865 | B274: 3549.09 | C274: 0.198318
A275: 44866 | B275: 3569.3 | C275: 0.338873
A276: 44867 | B276: 3508.94 | C276: 0.185469
A277: 44868 | B277: 3537.31 | C277: 0.140994
A278: 44869 | B278: 3584.56 | C278: 0.25849
A279: 44872 | B279: 3900.27 | C279: 3.142443
A280: 44874 | B280: 3934.28 | C280: 1.198458
A281: 44875 | B281: 3895.93 | C281: 0.417581
A282: 44876 | B282: 3862.01 | C282: 0.344558
... A385: 45028 | B385: 4024.69 | C385: 0.325329
A386: 45029 | C386: 0
A387: 45029 | B387: 4086.89 | C387: 0.454438
A388: 45033 | B388: 4158.2 | C388: 0.631457
A389: 45034 | B389: 4122.98 | C389: 0.190132
A390: 45035 | B390: 4115.31 | C390: 0.347248
A391: 45036 | B391: 4079.42 | C391: 0.164008
A392: 45037 | B392: 4147.85 | C392: 0.273401
A393: 45040 | B393: 4131.75 | C393: 0.182843
A394: 45041 | B394: 4219.49 | C394: 0.353719
A395: 45042 | B395: 4221.84 | C395: 0.306037
A396: 45043 | B396: 4232.24 | C396: 0.179769
A397: 45044 | B397: 4364.21 | C397: 0.482939
A398: 45048 | B398: 4323.48 | C398: 0.261449
... A707: 45506 | B707: 5482.5 | C707: 0.406998
A708: 45509 | C708: 0
A709: 45509 | B709: 5532.06 | C709: 1.114298
A710: 45510 | B710: 5684.1 | C710: 0.727869
...

Sheet Historical FS
B2: ='Data Sheet'!B1 -> BRITANNIA INDUSTRIES LTD
B3: (BRITANNIA) | BSE Code: 500825)
B4: INR 5,181.50 1st Sept 2026
B5: 52 Week (High - INR 6,336.95 & Low - 5,038)
K7: Prepared by Pushti Gandhi
B8: ="Historical Financial Statement"&" "&"-"&" "&'Data Sheet'!B1 -> Historical Financial Statement - BRITANNIA INDUSTRIES LTD
B9: Years | C9: ='Data Sheet'!B16 -> 42825 | D9: =C9+365 -> 43190 | E9: =D9+365 -> 43555 | F9: =E9+365 -> 43920 | G9: =F9+365 -> 44285 | H9: =G9+365 -> 44650 | I9: =H9+365 -> 45015 | J9: =I9+365 -> 45380 | K9: =J9+365 -> 45745 | L9: =K9+365 -> 46110 | M9: LTM
A11: # | B11: Income Statement
B12: Sales | C12: =IFERROR('Data Sheet'!B17,0) -> 9054.09 | D12: =IFERROR('Data Sheet'!C17,0) -> 9913.99 | E12: =IFERROR('Data Sheet'!D17,0) -> 11054.67 | F12: =IFERROR('Data Sheet'!E17,0) -> 11599.55 | G12: =IFERROR('Data Sheet'!F17,0) -> 13136.14 | H12: =IFERROR('Data Sheet'!G17,0) -> 14136.26 | I12: =IFERROR('Data Sheet'!H17,0) -> 16300.55 | J12: =IFERROR('Data Sheet'!I17,0) -> 16769.27 | ... L12: =IFERROR('Data Sheet'!K17,0) -> 19151.59 | M12: =IFERROR(SUM('Data Sheet'!G42:J42),0) -> 19151.59
B13: Sales Growth | C13: - | D13: =(D12/C12-1) -> 0.094973653 | E13: =(E12/D12-1) -> 0.11505761 | F13: =(F12/E12-1) -> 0.049289576 | G13: =(G12/F12-1) -> 0.13246979 | H13: =(H12/G12-1) -> 0.076134999 | I13: =(I12/H12-1) -> 0.15310202 | J13: =(J12/I12-1) -> 0.028754858 | K13: =(K12/J12-1) -> 0.069973231 | ... M13: =(M12/L12-1) -> 0
B15: COGS | C15: =IFERROR(SUM('Data Sheet'!B18,'Data Sheet'!B20:B22)-1*'Data Sheet'!B19,0) -> 6555.5 | D15: =IFERROR(SUM('Data Sheet'!C18,'Data Sheet'!C20:C22)-1*'Data Sheet'!C19,0) -> 7125.12 | E15: =IFERROR(SUM('Data Sheet'!D18,'Data Sheet'!D20:D22)-1*'Data Sheet'!D19,0) -> 7799.77 | F15: =IFERROR(SUM('Data Sheet'!E18,'Data Sheet'!E20:E22)-1*'Data Sheet'!E19,0) -> 8202.54 | G15: =IFERROR(SUM('Data Sheet'!F18,'Data Sheet'!F20:F22)-1*'Data Sheet'!F19,0) -> 9007.98 | H15: =IFERROR(SUM('Data Sheet'!G18,'Data Sheet'!G20:G22)-1*'Data Sheet'!G19,0) -> 10272.53 | I15: =IFERROR(SUM('Data Sheet'!H18,'Data Sheet'!H20:H22)-1*'Data Sheet'!H19,0) -> 11415.63 | J15: =IFERROR(SUM('Data Sheet'!I18,'Data Sheet'!I20:I22)-1*'Data Sheet'!I19,0) -> 11404.1 | ... L15: =IFERROR(SUM('Data Sheet'!K18,'Data Sheet'!K20:K22)-1*'Data Sheet'!K19,0) -> 13220.23 | M15: =IFERROR(SUM('Data Sheet'!G43:J43),0) -> 15637.25
B16: Gross Margins (COGS% of Sales) | C16: =(C15/C12) -> 0.72403742 | D16: =(D15/D12) -> 0.71869348 | E16: =(E15/E12) -> 0.70556335 | F16: =(F15/F12) -> 0.70714295 | G16: =(G15/G12) -> 0.68574026 | H16: =(H15/H12) -> 0.72667948 | I16: =(I15/I12) -> 0.70032177 | J16: =(J15/J12) -> 0.68005942 | ... M16: =(M15/M12) -> 0.81649879
B18: Gross Profit | C18: =IFERROR(C12-C15,0) -> 2498.59 | D18: =IFERROR(D12-D15,0) -> 2788.87 | E18: =IFERROR(E12-E15,0) -> 3254.9 | F18: =IFERROR(F12-F15,0) -> 3397.01 | G18: =IFERROR(G12-G15,0) -> 4128.16 | H18: =IFERROR(H12-H15,0) -> 3863.73 | I18: =IFERROR(I12-I15,0) -> 4884.92 | J18: =IFERROR(J12-J15,0) -> 5365.17 | ... M18: =IFERROR(M12-M15,0) -> 3514.34
B19: Gross Margins (GP % of Sales) | C19: =IFERROR(C18/C12,0) -> 0.27596258 | D19: =IFERROR(D18/D12,0) -> 0.28130652 | E19: =IFERROR(E18/E12,0) -> 0.29443665 | F19: =IFERROR(F18/F12,0) -> 0.29285705 | G19: =IFERROR(G18/G12,0) -> 0.31425974 | H19: =IFERROR(H18/H12,0) -> 0.27332052 | I19: =IFERROR(I18/I12,0) -> 0.29967823 | J19: =IFERROR(J18/J12,0) -> 0.31994058 | ... M19: =IFERROR(M18/M12,0) -> 0.18350121
B21: Selling & General Expense | C21: =IFERROR(SUM('Data Sheet'!B23:B24),0) -> 1220.41 | D21: =IFERROR(SUM('Data Sheet'!C23:C24),0) -> 1287.4 | E21: =IFERROR(SUM('Data Sheet'!D23:D24),0) -> 1522.45 | F21: =IFERROR(SUM('Data Sheet'!E23:E24),0) -> 1553.83 | G21: =IFERROR(SUM('Data Sheet'!F23:F24),0) -> 1618.87 | H21: =IFERROR(SUM('Data Sheet'!G23:G24),0) -> 1662.42 | I21: =IFERROR(SUM('Data Sheet'!H23:H24),0) -> 2054.01 | J21: =IFERROR(SUM('Data Sheet'!I23:I24),0) -> 2198.52 | ... L21: =IFERROR(SUM('Data Sheet'!K23:K24),0) -> 2417.02
B22: S&G % of Sales | C22: =IFERROR(C21/C12,0) -> 0.13479102 | D22: =IFERROR(D21/D12,0) -> 0.1298569 | E22: =IFERROR(E21/E12,0) -> 0.13772008 | F22: =IFERROR(F21/F12,0) -> 0.13395606 | G22: =IFERROR(G21/G12,0) -> 0.12323788 | H22: =IFERROR(H21/H12,0) -> 0.1175997 | I22: =IFERROR(I21/I12,0) -> 0.12600863 | J22: =IFERROR(J21/J12,0) -> 0.1311041 | ... M22: =IFERROR(M21/M12,0) -> 0
B24: EBITDA | C24: =IFERROR(C18-C21,0) -> 1278.18 | D24: =IFERROR(D18-D21,0) -> 1501.47 | E24: =IFERROR(E18-E21,0) -> 1732.45 | F24: =IFERROR(F18-F21,0) -> 1843.18 | G24: =IFERROR(G18-G21,0) -> 2509.29 | H24: =IFERROR(H18-H21,0) -> 2201.31 | I24: =IFERROR(I18-I21,0) -> 2830.91 | J24: =IFERROR(J18-J21,0) -> 3166.65 | ... M24: =IFERROR(M18-M21,0) -> 3514.34
B25: EBITDA Margin | C25: =IFERROR(C24/C12,0) -> 0.14117156 | D25: =IFERROR(D24/D12,0) -> 0.15144962 | E25: =IFERROR(E24/E12,0) -> 0.15671657 | F25: =IFERROR(F24/F12,0) -> 0.15890099 | G25: =IFERROR(G24/G12,0) -> 0.19102187 | H25: =IFERROR(H24/H12,0) -> 0.15572082 | I25: =IFERROR(I24/I12,0) -> 0.1736696 | J25: =IFERROR(J24/J12,0) -> 0.18883648 | ... M25: =IFERROR(M24/M12,0) -> 0.18350121
B27: Interest | C27: =IFERROR('Data Sheet'!B27,0) -> 5.45 | D27: =IFERROR('Data Sheet'!C27,0) -> 7.59 | E27: =IFERROR('Data Sheet'!D27,0) -> 9.09 | F27: =IFERROR('Data Sheet'!E27,0) -> 76.9 | G27: =IFERROR('Data Sheet'!F27,0) -> 110.9 | H27: =IFERROR('Data Sheet'!G27,0) -> 144.29 | I27: =IFERROR('Data Sheet'!H27,0) -> 169.1 | J27: =IFERROR('Data Sheet'!I27,0) -> 164 | ... L27: =IFERROR('Data Sheet'!K27,0) -> 112.76 | M27: =IFERROR(SUM('Data Sheet'!H46:K46),0) -> 109.48
B28: Interest % of Sales | C28: =IFERROR(C27/C12,0) -> 0.00060193791 | D28: =IFERROR(D27/D12,0) -> 0.00076558479 | E28: =IFERROR(E27/E12,0) -> 0.00082227692 | F28: =IFERROR(F27/F12,0) -> 0.0066295675 | G28: =IFERROR(G27/G12,0) -> 0.0084423583 | H28: =IFERROR(H27/H12,0) -> 0.010207084 | I28: =IFERROR(I27/I12,0) -> 0.010373883 | J28: =IFERROR(J27/J12,0) -> 0.0097797936 | ... M28: =IFERROR(M27/M12,0) -> 0.0057164966
B30: Depreciation | C30: =IFERROR('Data Sheet'!B26,0) -> 119.27 | D30: =IFERROR('Data Sheet'!C26,0) -> 142.07 | E30: =IFERROR('Data Sheet'!D26,0) -> 161.88 | F30: =IFERROR('Data Sheet'!E26,0) -> 184.81 | G30: =IFERROR('Data Sheet'!F26,0) -> 197.85 | H30: =IFERROR('Data Sheet'!G26,0) -> 200.54 | I30: =IFERROR('Data Sheet'!H26,0) -> 225.91 | J30: =IFERROR('Data Sheet'!I26,0) -> 300.46 | ... L30: =IFERROR('Data Sheet'!K26,0) -> 336.83 | M30: =IFERROR(SUM('Data Sheet'!H45:K45),0) -> 334.3
B31: Depreciation % of Sales | C31: =IFERROR(C30/C12,0) -> 0.013173052 | D31: =IFERROR(D30/D12,0) -> 0.014330255 | E31: =IFERROR(E30/E12,0) -> 0.014643585 | F31: =IFERROR(F30/F12,0) -> 0.015932515 | G31: =IFERROR(G30/G12,0) -> 0.015061502 | H31: =IFERROR(H30/H12,0) -> 0.014186213 | I31: =IFERROR(I30/I12,0) -> 0.013859042 | J31: =IFERROR(J30/J12,0) -> 0.017917298 | ... M31: =IFERROR(M30/M12,0) -> 0.01745547
B33: EBIT | C33: =IFERROR(C24-C30,0) -> 1158.91 | D33: =IFERROR(D24-D30,0) -> 1359.4 | E33: =IFERROR(E24-E30,0) -> 1570.57 | F33: =IFERROR(F24-F30,0) -> 1658.37 | G33: =IFERROR(G24-G30,0) -> 2311.44 | H33: =IFERROR(H24-H30,0) -> 2000.77 | I33: =IFERROR(I24-I30,0) -> 2605 | J33: =IFERROR(J24-J30,0) -> 2866.19 | ... M33: =IFERROR(M24-M30,0) -> 3180.04
B34: EBIT Margin | C34: =IFERROR(C33/C12,0) -> 0.12799851 | D34: =IFERROR(D33/D12,0) -> 0.13711936 | E34: =IFERROR(E33/E12,0) -> 0.14207299 | F34: =IFERROR(F33/F12,0) -> 0.14296848 | G34: =IFERROR(G33/G12,0) -> 0.17596037 | H34: =IFERROR(H33/H12,0) -> 0.14153461 | I34: =IFERROR(I33/I12,0) -> 0.15981056 | J34: =IFERROR(J33/J12,0) -> 0.17091919 | ... M34: =IFERROR(M33/M12,0) -> 0.16604574
B36: Earnings Before Tax (EBT) | C36: =IFERROR(C24-SUM(C27,C30),0) -> 1153.46 | D36: =IFERROR(D24-SUM(D27,D30),0) -> 1351.81 | E36: =IFERROR(E24-SUM(E27,E30),0) -> 1561.48 | F36: =IFERROR(F24-SUM(F27,F30),0) -> 1581.47 | G36: =IFERROR(G24-SUM(G27,G30),0) -> 2200.54 | H36: =IFERROR(H24-SUM(H27,H30),0) -> 1856.48 | I36: =IFERROR(I24-SUM(I27,I30),0) -> 2435.9 | J36: =IFERROR(J24-SUM(J27,J30),0) -> 2702.19 | ... M36: =IFERROR(M24-SUM(M27,M30),0) -> 3070.56
B37: EBT % of Sales (EBT Margin) | C37: =IFERROR(C36/C12,0) -> 0.12739657 | D37: =IFERROR(D36/D12,0) -> 0.13635378 | E37: =IFERROR(E36/E12,0) -> 0.14125071 | F37: =IFERROR(F36/F12,0) -> 0.13633891 | G37: =IFERROR(G36/G12,0) -> 0.16751801 | H37: =IFERROR(H36/H12,0) -> 0.13132752 | I37: =IFERROR(I36/I12,0) -> 0.14943668 | J37: =IFERROR(J36/J12,0) -> 0.16113939 | ... M37: =IFERROR(M36/M12,0) -> 0.16032925
B39: Tax | C39: =IFERROR('Data Sheet'!B29,0) -> 419.67 | D39: =IFERROR('Data Sheet'!C29,0) -> 514.22 | E39: =IFERROR('Data Sheet'!D29,0) -> 612.47 | F39: =IFERROR('Data Sheet'!E29,0) -> 450.7 | G39: =IFERROR('Data Sheet'!F29,0) -> 663.02 | H39: =IFERROR('Data Sheet'!G29,0) -> 562.35 | I39: =IFERROR('Data Sheet'!H29,0) -> 716.45 | J39: =IFERROR('Data Sheet'!I29,0) -> 779.25 | ... L39: =IFERROR('Data Sheet'!K29,0) -> 751.77 | M39: =IFERROR(SUM('Data Sheet'!H48:K48),0) -> 774.85
B40: Effective Tax Rate (Tax/EBT) | C40: =IFERROR(C39/C36,0) -> 0.36383576 | D40: =IFERROR(D39/D36,0) -> 0.38039369 | E40: =IFERROR(E39/E36,0) -> 0.39223685 | F40: =IFERROR(F39/F36,0) -> 0.28498802 | G40: =IFERROR(G39/G36,0) -> 0.30129877 | H40: =IFERROR(H39/H36,0) -> 0.30291196 | I40: =IFERROR(I39/I36,0) -> 0.29412127 | J40: =IFERROR(J39/J36,0) -> 0.28837721 | ... M40: =IFERROR(M39/M36,0) -> 0.25234811
B42: Net Profit (EBT - Tax) | C42: =IFERROR(C36-C39,0) -> 733.79 | D42: =IFERROR(D36-D39,0) -> 837.59 | E42: =IFERROR(E36-E39,0) -> 949.01 | F42: =IFERROR(F36-F39,0) -> 1130.77 | G42: =IFERROR(G36-G39,0) -> 1537.52 | H42: =IFERROR(H36-H39,0) -> 1294.13 | I42: =IFERROR(I36-I39,0) -> 1719.45 | J42: =IFERROR(J36-J39,0) -> 1922.94 | ... M42: =IFERROR(M36-M39,0) -> 2295.71
B43: Net Profit Margin (NP / Sales) | C43: =IFERROR(C42/C12,0) -> 0.081045141 | D43: =IFERROR(D42/D12,0) -> 0.084485661 | E43: =IFERROR(E42/E12,0) -> 0.085846977 | F43: =IFERROR(F42/F12,0) -> 0.097483954 | G43: =IFERROR(G42/G12,0) -> 0.11704504 | H43: =IFERROR(H42/H12,0) -> 0.091546845 | I43: =IFERROR(I42/I12,0) -> 0.10548417 | J43: =IFERROR(J42/J12,0) -> 0.11467047 | ... M43: =IFERROR(M42/M12,0) -> 0.11987047
B45: No. Of Equity Shares | C45: =IFERROR('Data Sheet'!B93,0) -> 24 | D45: =IFERROR('Data Sheet'!C93,0) -> 24.01 | E45: =IFERROR('Data Sheet'!D93,0) -> 24.03 | F45: =IFERROR('Data Sheet'!E93,0) -> 24.05 | G45: =IFERROR('Data Sheet'!F93,0) -> 24.09 | H45: =IFERROR('Data Sheet'!G93,0) -> 24.09 | I45: =IFERROR('Data Sheet'!H93,0) -> 24.09 | J45: =IFERROR('Data Sheet'!I93,0) -> 24.09 | ... L45: =IFERROR('Data Sheet'!K93,0) -> 24.09
B47: Earning Per Share | C47: =IFERROR(C42/C45,0) -> 30.574583 | D47: =IFERROR(D42/D45,0) -> 34.885048 | E47: =IFERROR(E42/E45,0) -> 39.492717 | F47: =IFERROR(F42/F45,0) -> 47.017464 | G47: =IFERROR(G42/G45,0) -> 63.823993 | H47: =IFERROR(H42/H45,0) -> 53.720631 | I47: =IFERROR(I42/I45,0) -> 71.37609 | J47: =IFERROR(J42/J45,0) -> 79.823163 | ... M47: =IFERROR(M42/M45,0) -> 0
B48: EPS Growth % | C48: - | D48: =(D47/C47-1) -> 0.14098196 | E48: =(E47/D47-1) -> 0.1320815 | F48: =(F47/E47-1) -> 0.19053503 | G48: =(G47/F47-1) -> 0.35745292 | H48: =(H47/G47-1) -> -0.15830038 | I48: =(I47/H47-1) -> 0.32865323 | J48: =(J47/I47-1) -> 0.11834598 | K48: =(K47/J47-1) -> 0.027364348 | ... M48: =(M47/L47-1) -> -1
B50: DPS (Dividend Per Share) | C50: =IFERROR('Data Sheet'!B31/'Data Sheet'!B93,0) -> 11 | D50: =IFERROR('Data Sheet'!C31/'Data Sheet'!C93,0) -> 12.499792 | E50: =IFERROR('Data Sheet'!D31/'Data Sheet'!D93,0) -> 15 | F50: =IFERROR('Data Sheet'!E31/'Data Sheet'!E93,0) -> 35 | G50: =IFERROR('Data Sheet'!F31/'Data Sheet'!F93,0) -> 157.50021 | H50: =IFERROR('Data Sheet'!G31/'Data Sheet'!G93,0) -> 56.499792 | I50: =IFERROR('Data Sheet'!H31/'Data Sheet'!H93,0) -> 72 | J50: =IFERROR('Data Sheet'!I31/'Data Sheet'!I93,0) -> 73.500208 | ... M50: =IFERROR('Data Sheet'!L31/'Data Sheet'!L93,0) -> 0
B51: Dividend Payout Ratio (DPS/EPS) | C51: =IFERROR(C50/C47,0) -> 0.35977596 | D51: =IFERROR(D50/D47,0) -> 0.35831373 | E51: =IFERROR(E50/E47,0) -> 0.37981686 | F51: =IFERROR(F50/F47,0) -> 0.74440426 | G51: =IFERROR(G50/G47,0) -> 2.4677272 | H51: =IFERROR(H50/H47,0) -> 1.0517336 | I51: =IFERROR(I50/I47,0) -> 1.0087412 | J51: =IFERROR(J50/J47,0) -> 0.92078796 | ... M51: =IFERROR(M50/M47,0) -> 0
B53: Retained Earnings | C53: =IF(C47>C50,1-C51,0) -> 0.64022404 | D53: =IF(D47>D50,1-D51,0) -> 0.64168627 | E53: =IF(E47>E50,1-E51,0) -> 0.62018314 | F53: =IF(F47>F50,1-F51,0) -> 0.25559574 | G53: =IF(G47>G50,1-G51,0) -> 0 | H53: =IF(H47>H50,1-H51,0) -> 0 | I53: =IF(I47>I50,1-I51,0) -> 0 | J53: =IF(J47>J50,1-J51,0) -> 0.07921204 | ... M53: =IF(M47>M50,1-M51,0) -> 0
A56: # | B56: Balance Sheet
B57: Equity Share Capital | C57: =IFERROR('Data Sheet'!B57,0) -> 24 | D57: =IFERROR('Data Sheet'!C57,0) -> 24.01 | E57: =IFERROR('Data Sheet'!D57,0) -> 24.03 | F57: =IFERROR('Data Sheet'!E57,0) -> 24.05 | G57: =IFERROR('Data Sheet'!F57,0) -> 24.09 | H57: =IFERROR('Data Sheet'!G57,0) -> 24.09 | I57: =IFERROR('Data Sheet'!H57,0) -> 24.09 | J57: =IFERROR('Data Sheet'!I57,0) -> 24.09 | ... L57: =IFERROR('Data Sheet'!K57,0) -> 24.09
B58: Reserves | C58: =IFERROR('Data Sheet'!B58,0) -> 2672.42 | D58: =IFERROR('Data Sheet'!C58,0) -> 3382.22 | E58: =IFERROR('Data Sheet'!D58,0) -> 4229.22 | F58: =IFERROR('Data Sheet'!E58,0) -> 4378.78 | G58: =IFERROR('Data Sheet'!F58,0) -> 3523.57 | H58: =IFERROR('Data Sheet'!G58,0) -> 2534.01 | I58: =IFERROR('Data Sheet'!H58,0) -> 3510.18 | J58: =IFERROR('Data Sheet'!I58,0) -> 3917.43 | ... L58: =IFERROR('Data Sheet'!K58,0) -> 5082.47
B59: Borrowings | C59: =IFERROR('Data Sheet'!B59,0) -> 124.56 | D59: =IFERROR('Data Sheet'!C59,0) -> 200.7 | E59: =IFERROR('Data Sheet'!D59,0) -> 156.02 | F59: =IFERROR('Data Sheet'!E59,0) -> 1537.59 | G59: =IFERROR('Data Sheet'!F59,0) -> 2106.94 | H59: =IFERROR('Data Sheet'!G59,0) -> 2481.2 | I59: =IFERROR('Data Sheet'!H59,0) -> 2997.37 | J59: =IFERROR('Data Sheet'!I59,0) -> 2064.96 | ... L59: =IFERROR('Data Sheet'!K59,0) -> 1380.28
B60: Other Liabilities | C60: =IFERROR('Data Sheet'!B60,0) -> 1287.82 | D60: =IFERROR('Data Sheet'!C60,0) -> 1580.99 | E60: =IFERROR('Data Sheet'!D60,0) -> 1828.68 | F60: =IFERROR('Data Sheet'!E60,0) -> 1889.12 | G60: =IFERROR('Data Sheet'!F60,0) -> 2345.49 | H60: =IFERROR('Data Sheet'!G60,0) -> 2487.3 | I60: =IFERROR('Data Sheet'!H60,0) -> 2819.21 | J60: =IFERROR('Data Sheet'!I60,0) -> 3065.02 | ... L60: =IFERROR('Data Sheet'!K60,0) -> 3243.48
B61: Total Liabilities | C61: =IFERROR('Data Sheet'!B61,0) -> 4108.8 | D61: =IFERROR('Data Sheet'!C61,0) -> 5187.92 | E61: =IFERROR('Data Sheet'!D61,0) -> 6237.95 | F61: =IFERROR('Data Sheet'!E61,0) -> 7829.54 | G61: =IFERROR('Data Sheet'!F61,0) -> 8000.09 | H61: =IFERROR('Data Sheet'!G61,0) -> 7526.6 | I61: =IFERROR('Data Sheet'!H61,0) -> 9350.85 | J61: =IFERROR('Data Sheet'!I61,0) -> 9071.5 | ... L61: =IFERROR('Data Sheet'!K61,0) -> 9730.32
B63: Fixed Assets Net Block | C63: =IFERROR('Data Sheet'!B62,0) -> 1159.99 | D63: =IFERROR('Data Sheet'!C62,0) -> 1345.6 | E63: =IFERROR('Data Sheet'!D62,0) -> 1688.3 | F63: =IFERROR('Data Sheet'!E62,0) -> 1878.18 | G63: =IFERROR('Data Sheet'!F62,0) -> 1792.95 | H63: =IFERROR('Data Sheet'!G62,0) -> 1753.21 | I63: =IFERROR('Data Sheet'!H62,0) -> 2655.22 | J63: =IFERROR('Data Sheet'!I62,0) -> 2771.14 | ... L63: =IFERROR('Data Sheet'!K62,0) -> 2849.92
B64: Capital Work in Progress | C64: =IFERROR('Data Sheet'!B63,0) -> 30.07 | D64: =IFERROR('Data Sheet'!C63,0) -> 202.82 | E64: =IFERROR('Data Sheet'!D63,0) -> 101.24 | F64: =IFERROR('Data Sheet'!E63,0) -> 39.55 | G64: =IFERROR('Data Sheet'!F63,0) -> 116.52 | H64: =IFERROR('Data Sheet'!G63,0) -> 535.68 | I64: =IFERROR('Data Sheet'!H63,0) -> 105 | J64: =IFERROR('Data Sheet'!I63,0) -> 187.54 | ... L64: =IFERROR('Data Sheet'!K63,0) -> 39.04
B65: Investments | C65: =IFERROR('Data Sheet'!B64,0) -> 486.85 | D65: =IFERROR('Data Sheet'!C64,0) -> 1079.28 | E65: =IFERROR('Data Sheet'!D64,0) -> 1476.28 | F65: =IFERROR('Data Sheet'!E64,0) -> 2893.23 | G65: =IFERROR('Data Sheet'!F64,0) -> 2780.69 | H65: =IFERROR('Data Sheet'!G64,0) -> 1762.37 | I65: =IFERROR('Data Sheet'!H64,0) -> 3324.24 | J65: =IFERROR('Data Sheet'!I64,0) -> 2766.72 | ... L65: =IFERROR('Data Sheet'!K64,0) -> 3609.76
B66: Other Assets | C66: =IFERROR('Data Sheet'!B65-SUM('Data Sheet'!B67:B69),0) -> 1470.52 | D66: =IFERROR('Data Sheet'!C65-SUM('Data Sheet'!C67:C69),0) -> 1416.41 | E66: =IFERROR('Data Sheet'!D65-SUM('Data Sheet'!D67:D69),0) -> 1686.69 | F66: =IFERROR('Data Sheet'!E65-SUM('Data Sheet'!E67:E69),0) -> 1834.41 | G66: =IFERROR('Data Sheet'!F65-SUM('Data Sheet'!F67:F69),0) -> 1749.83 | H66: =IFERROR('Data Sheet'!G65-SUM('Data Sheet'!G67:G69),0) -> 1591.02 | I66: =IFERROR('Data Sheet'!H65-SUM('Data Sheet'!H67:H69),0) -> 1546.21 | J66: =IFERROR('Data Sheet'!I65-SUM('Data Sheet'!I67:I69),0) -> 1325.2 | ... L66: =IFERROR('Data Sheet'!K65-SUM('Data Sheet'!K67:K69),0) -> 1064.02
B67: Total Non-Current Assets | C67: =IFERROR(SUM(C63:C66),0) -> 3147.43 | D67: =IFERROR(SUM(D63:D66),0) -> 4044.11 | E67: =IFERROR(SUM(E63:E66),0) -> 4952.51 | F67: =IFERROR(SUM(F63:F66),0) -> 6645.37 | G67: =IFERROR(SUM(G63:G66),0) -> 6439.99 | H67: =IFERROR(SUM(H63:H66),0) -> 5642.28 | I67: =IFERROR(SUM(I63:I66),0) -> 7630.67 | J67: =IFERROR(SUM(J63:J66),0) -> 7050.6 | ... L67: =IFERROR(SUM(L63:L66),0) -> 7562.74
B69: Receivables | C69: =IFERROR('Data Sheet'!B67,0) -> 179.16 | D69: =IFERROR('Data Sheet'!C67,0) -> 304.6 | E69: =IFERROR('Data Sheet'!D67,0) -> 394.24 | F69: =IFERROR('Data Sheet'!E67,0) -> 320.36 | G69: =IFERROR('Data Sheet'!F67,0) -> 257.27 | H69: =IFERROR('Data Sheet'!G67,0) -> 331.93 | I69: =IFERROR('Data Sheet'!H67,0) -> 328.94 | J69: =IFERROR('Data Sheet'!I67,0) -> 393.33 | ... L69: =IFERROR('Data Sheet'!K67,0) -> 469.21
B70: Inventory | C70: =IFERROR('Data Sheet'!B68,0) -> 661.45 | D70: =IFERROR('Data Sheet'!C68,0) -> 652.79 | E70: =IFERROR('Data Sheet'!D68,0) -> 781.38 | F70: =IFERROR('Data Sheet'!E68,0) -> 740.96 | G70: =IFERROR('Data Sheet'!F68,0) -> 1091.49 | H70: =IFERROR('Data Sheet'!G68,0) -> 1367.49 | I70: =IFERROR('Data Sheet'!H68,0) -> 1193.26 | J70: =IFERROR('Data Sheet'!I68,0) -> 1181.22 | ... L70: =IFERROR('Data Sheet'!K68,0) -> 1345.93
B71: Cash & Bank | C71: =IFERROR('Data Sheet'!B69,0) -> 120.76 | D71: =IFERROR('Data Sheet'!C69,0) -> 186.42 | E71: =IFERROR('Data Sheet'!D69,0) -> 109.82 | F71: =IFERROR('Data Sheet'!E69,0) -> 122.85 | G71: =IFERROR('Data Sheet'!F69,0) -> 211.34 | H71: =IFERROR('Data Sheet'!G69,0) -> 184.9 | I71: =IFERROR('Data Sheet'!H69,0) -> 197.98 | J71: =IFERROR('Data Sheet'!I69,0) -> 446.35 | ... L71: =IFERROR('Data Sheet'!K69,0) -> 352.44
B72: Total Current Assets | C72: =IFERROR(SUM(C69:C71),0) -> 961.37 | D72: =IFERROR(SUM(D69:D71),0) -> 1143.81 | E72: =IFERROR(SUM(E69:E71),0) -> 1285.44 | F72: =IFERROR(SUM(F69:F71),0) -> 1184.17 | G72: =IFERROR(SUM(G69:G71),0) -> 1560.1 | H72: =IFERROR(SUM(H69:H71),0) -> 1884.32 | I72: =IFERROR(SUM(I69:I71),0) -> 1720.18 | J72: =IFERROR(SUM(J69:J71),0) -> 2020.9 | ... L72: =IFERROR(SUM(L69:L71),0) -> 2167.58
B74: Total Assets | C74: =IFERROR(C72+C67,0) -> 4108.8 | D74: =IFERROR(D72+D67,0) -> 5187.92 | E74: =IFERROR(E72+E67,0) -> 6237.95 | F74: =IFERROR(F72+F67,0) -> 7829.54 | G74: =IFERROR(G72+G67,0) -> 8000.09 | H74: =IFERROR(H72+H67,0) -> 7526.6 | I74: =IFERROR(I72+I67,0) -> 9350.85 | J74: =IFERROR(J72+J67,0) -> 9071.5 | ... L74: =IFERROR(L72+L67,0) -> 9730.32
B76: Check | C76: =C74=C61 -> TRUE | D76: =D74=D61 -> TRUE | E76: =E74=E61 -> TRUE | F76: =F74=F61 -> TRUE | G76: =G74=G61 -> TRUE | H76: =H74=H61 -> TRUE | I76: =I74=I61 -> TRUE | J76: =J74=J61 -> TRUE | ... L76: =L74=L61 -> TRUE
A79: # | B79: Cash Flow Statement
B80: Operating Activities
B81: Profit from operations | C81: =IFERROR('Cash Flow Data'!D69,0) -> 1289 | D81: =IFERROR('Cash Flow Data'!E69,0) -> 1517 | E81: =IFERROR('Cash Flow Data'!F69,0) -> 1754 | F81: =IFERROR('Cash Flow Data'!G69,0) -> 1860 | G81: =IFERROR('Cash Flow Data'!H69,0) -> 2540 | H81: =IFERROR('Cash Flow Data'!I69,0) -> 2214 | I81: =IFERROR('Cash Flow Data'!J69,0) -> 2846 | J81: =IFERROR('Cash Flow Data'!K69,0) -> 3177 | ... L81: =IFERROR('Cash Flow Data'!M69,0) -> 3555
B82: Receivables | C82: =IFERROR('Cash Flow Data'!D70,0) -> -9 | D82: =IFERROR('Cash Flow Data'!E70,0) -> -125 | E82: =IFERROR('Cash Flow Data'!F70,0) -> -87 | F82: =IFERROR('Cash Flow Data'!G70,0) -> 79 | G82: =IFERROR('Cash Flow Data'!H70,0) -> 61 | H82: =IFERROR('Cash Flow Data'!I70,0) -> -72 | I82: =IFERROR('Cash Flow Data'!J70,0) -> 1 | J82: =IFERROR('Cash Flow Data'!K70,0) -> -64 | ... L82: =IFERROR('Cash Flow Data'!M70,0) -> -13
B83: Inventory | C83: =IFERROR('Cash Flow Data'!D71,0) -> -221 | D83: =IFERROR('Cash Flow Data'!E71,0) -> 9 | E83: =IFERROR('Cash Flow Data'!F71,0) -> -127 | F83: =IFERROR('Cash Flow Data'!G71,0) -> 43 | G83: =IFERROR('Cash Flow Data'!H71,0) -> -351 | H83: =IFERROR('Cash Flow Data'!I71,0) -> -275 | I83: =IFERROR('Cash Flow Data'!J71,0) -> 177 | J83: =IFERROR('Cash Flow Data'!K71,0) -> 13 | ... L83: =IFERROR('Cash Flow Data'!M71,0) -> -105
B84: Payables | C84: =IFERROR('Cash Flow Data'!D72,0) -> 0 | D84: =IFERROR('Cash Flow Data'!E72,0) -> 0 | E84: =IFERROR('Cash Flow Data'!F72,0) -> 0 | F84: =IFERROR('Cash Flow Data'!G72,0) -> 0 | G84: =IFERROR('Cash Flow Data'!H72,0) -> 0 | H84: =IFERROR('Cash Flow Data'!I72,0) -> 64 | I84: =IFERROR('Cash Flow Data'!J72,0) -> 292 | J84: =IFERROR('Cash Flow Data'!K72,0) -> 237 | ... L84: =IFERROR('Cash Flow Data'!M72,0) -> 25
B85: Loans Advances | C85: =IFERROR('Cash Flow Data'!D73,0) -> 0 | D85: =IFERROR('Cash Flow Data'!E73,0) -> 0 | E85: =IFERROR('Cash Flow Data'!F73,0) -> 0 | F85: =IFERROR('Cash Flow Data'!G73,0) -> 0 | G85: =IFERROR('Cash Flow Data'!H73,0) -> 0 | H85: =IFERROR('Cash Flow Data'!I73,0) -> 0 | I85: =IFERROR('Cash Flow Data'!J73,0) -> 0 | J85: =IFERROR('Cash Flow Data'!K73,0) -> 0 | ... L85: =IFERROR('Cash Flow Data'!M73,0) -> 0
B86: Other WC items | C86: =IFERROR('Cash Flow Data'!D74,0) -> -221 | D86: =IFERROR('Cash Flow Data'!E74,0) -> 345 | E86: =IFERROR('Cash Flow Data'!F74,0) -> 211 | F86: =IFERROR('Cash Flow Data'!G74,0) -> 6 | G86: =IFERROR('Cash Flow Data'!H74,0) -> 234 | H86: =IFERROR('Cash Flow Data'!I74,0) -> -44 | I86: =IFERROR('Cash Flow Data'!J74,0) -> -65 | J86: =IFERROR('Cash Flow Data'!K74,0) -> -25 | ... L86: =IFERROR('Cash Flow Data'!M74,0) -> -28
B87: Working capital changes | C87: =IFERROR('Cash Flow Data'!D75,0) -> -451 | D87: =IFERROR('Cash Flow Data'!E75,0) -> 228 | E87: =IFERROR('Cash Flow Data'!F75,0) -> -2 | F87: =IFERROR('Cash Flow Data'!G75,0) -> 127 | G87: =IFERROR('Cash Flow Data'!H75,0) -> -56 | H87: =IFERROR('Cash Flow Data'!I75,0) -> -327 | I87: =IFERROR('Cash Flow Data'!J75,0) -> 406 | J87: =IFERROR('Cash Flow Data'!K75,0) -> 161 | ... L87: =IFERROR('Cash Flow Data'!M75,0) -> -121
B88: Direct taxes | C88: =IFERROR('Cash Flow Data'!D76,0) -> -397 | D88: =IFERROR('Cash Flow Data'!E76,0) -> -496 | E88: =IFERROR('Cash Flow Data'!F76,0) -> -596 | F88: =IFERROR('Cash Flow Data'!G76,0) -> -503 | G88: =IFERROR('Cash Flow Data'!H76,0) -> -633 | H88: =IFERROR('Cash Flow Data'!I76,0) -> -587 | I88: =IFERROR('Cash Flow Data'!J76,0) -> -726 | J88: =IFERROR('Cash Flow Data'!K76,0) -> -765 | ... L88: =IFERROR('Cash Flow Data'!M76,0) -> -822
B89: Cash from Operating Activities | C89: =SUM(C81:C88) -> -10 | D89: =SUM(D81:D88) -> 1478 | E89: =SUM(E81:E88) -> 1153 | F89: =SUM(F81:F88) -> 1612 | G89: =SUM(G81:G88) -> 1795 | H89: =SUM(H81:H88) -> 973 | I89: =SUM(I81:I88) -> 2931 | J89: =SUM(J81:J88) -> 2734 | ... L89: =SUM(L81:L88) -> 2491
B91: Investing Activities
B92: Fixed assets purchased | C92: =IFERROR('Cash Flow Data'!D78,0) -> -360 | D92: =IFERROR('Cash Flow Data'!E78,0) -> -423 | E92: =IFERROR('Cash Flow Data'!F78,0) -> -401 | F92: =IFERROR('Cash Flow Data'!G78,0) -> -244 | G92: =IFERROR('Cash Flow Data'!H78,0) -> -242 | H92: =IFERROR('Cash Flow Data'!I78,0) -> -550 | I92: =IFERROR('Cash Flow Data'!J78,0) -> -711 | J92: =IFERROR('Cash Flow Data'!K78,0) -> -553 | ... L92: =IFERROR('Cash Flow Data'!M78,0) -> -206
B93: Fixed assets sold | C93: =IFERROR('Cash Flow Data'!D79,0) -> 8 | D93: =IFERROR('Cash Flow Data'!E79,0) -> 2 | E93: =IFERROR('Cash Flow Data'!F79,0) -> 2 | F93: =IFERROR('Cash Flow Data'!G79,0) -> 1 | G93: =IFERROR('Cash Flow Data'!H79,0) -> 2 | H93: =IFERROR('Cash Flow Data'!I79,0) -> 3 | I93: =IFERROR('Cash Flow Data'!J79,0) -> 78 | J93: =IFERROR('Cash Flow Data'!K79,0) -> 65 | ... L93: =IFERROR('Cash Flow Data'!M79,0) -> 2
B94: Investments purchased | C94: =IFERROR('Cash Flow Data'!D80,0) -> 0 | D94: =IFERROR('Cash Flow Data'!E80,0) -> -537 | E94: =IFERROR('Cash Flow Data'!F80,0) -> -334 | F94: =IFERROR('Cash Flow Data'!G80,0) -> -1327 | G94: =IFERROR('Cash Flow Data'!H80,0) -> 0 | H94: =IFERROR('Cash Flow Data'!I80,0) -> -21 | I94: =IFERROR('Cash Flow Data'!J80,0) -> -1468 | J94: =IFERROR('Cash Flow Data'!K80,0) -> -191 | ... L94: =IFERROR('Cash Flow Data'!M80,0) -> -976
B95: Investments sold | C95: =IFERROR('Cash Flow Data'!D81,0) -> 359 | D95: =IFERROR('Cash Flow Data'!E81,0) -> 0 | E95: =IFERROR('Cash Flow Data'!F81,0) -> 0 | F95: =IFERROR('Cash Flow Data'!G81,0) -> 0 | G95: =IFERROR('Cash Flow Data'!H81,0) -> 179 | H95: =IFERROR('Cash Flow Data'!I81,0) -> 1069 | I95: =IFERROR('Cash Flow Data'!J81,0) -> 443 | J95: =IFERROR('Cash Flow Data'!K81,0) -> 771 | ... L95: =IFERROR('Cash Flow Data'!M81,0) -> 254
B96: Interest received | C96: =IFERROR('Cash Flow Data'!D82,0) -> 75 | D96: =IFERROR('Cash Flow Data'!E82,0) -> 109 | E96: =IFERROR('Cash Flow Data'!F82,0) -> 117 | F96: =IFERROR('Cash Flow Data'!G82,0) -> 128 | G96: =IFERROR('Cash Flow Data'!H82,0) -> 233 | H96: =IFERROR('Cash Flow Data'!I82,0) -> 207 | I96: =IFERROR('Cash Flow Data'!J82,0) -> 175 | J96: =IFERROR('Cash Flow Data'!K82,0) -> 170 | ... L96: =IFERROR('Cash Flow Data'!M82,0) -> 143
B97: Dividends received | C97: =IFERROR('Cash Flow Data'!D83,0) -> 0 | D97: =IFERROR('Cash Flow Data'!E83,0) -> 0 | E97: =IFERROR('Cash Flow Data'!F83,0) -> 0 | F97: =IFERROR('Cash Flow Data'!G83,0) -> 0 | G97: =IFERROR('Cash Flow Data'!H83,0) -> 0 | H97: =IFERROR('Cash Flow Data'!I83,0) -> 0 | I97: =IFERROR('Cash Flow Data'!J83,0) -> 0 | J97: =IFERROR('Cash Flow Data'!K83,0) -> 0 | ... L97: =IFERROR('Cash Flow Data'!M83,0) -> 0
B98: Investment in group cos | C98: =IFERROR('Cash Flow Data'!D84,0) -> -14 | D98: =IFERROR('Cash Flow Data'!E84,0) -> 0 | E98: =IFERROR('Cash Flow Data'!F84,0) -> 0 | F98: =IFERROR('Cash Flow Data'!G84,0) -> 0 | G98: =IFERROR('Cash Flow Data'!H84,0) -> 0 | H98: =IFERROR('Cash Flow Data'!I84,0) -> 0 | I98: =IFERROR('Cash Flow Data'!J84,0) -> -215 | J98: =IFERROR('Cash Flow Data'!K84,0) -> 0 | ... L98: =IFERROR('Cash Flow Data'!M84,0) -> 0
B99: Redemp n Canc of Shares | C99: =IFERROR('Cash Flow Data'!D85,0) -> 0 | D99: =IFERROR('Cash Flow Data'!E85,0) -> 0 | E99: =IFERROR('Cash Flow Data'!F85,0) -> 0 | F99: =IFERROR('Cash Flow Data'!G85,0) -> 0 | G99: =IFERROR('Cash Flow Data'!H85,0) -> 0 | H99: =IFERROR('Cash Flow Data'!I85,0) -> 0 | I99: =IFERROR('Cash Flow Data'!J85,0) -> 262 | J99: =IFERROR('Cash Flow Data'!K85,0) -> 0 | ... L99: =IFERROR('Cash Flow Data'!M85,0) -> 0
B100: Inter corporate deposits | C100: =IFERROR('Cash Flow Data'!D86,0) -> -218 | D100: =IFERROR('Cash Flow Data'!E86,0) -> -107 | E100: =IFERROR('Cash Flow Data'!F86,0) -> -239 | F100: =IFERROR('Cash Flow Data'!G86,0) -> -89 | G100: =IFERROR('Cash Flow Data'!H86,0) -> 289 | H100: =IFERROR('Cash Flow Data'!I86,0) -> 202 | I100: =IFERROR('Cash Flow Data'!J86,0) -> 88 | J100: =IFERROR('Cash Flow Data'!K86,0) -> 250 | ... L100: =IFERROR('Cash Flow Data'!M86,0) -> -15
B101: Other investing items | C101: =IFERROR('Cash Flow Data'!D87,0) -> 0 | D101: =IFERROR('Cash Flow Data'!E87,0) -> 0 | E101: =IFERROR('Cash Flow Data'!F87,0) -> 3 | F101: =IFERROR('Cash Flow Data'!G87,0) -> 6 | G101: =IFERROR('Cash Flow Data'!H87,0) -> -2 | H101: =IFERROR('Cash Flow Data'!I87,0) -> 5 | I101: =IFERROR('Cash Flow Data'!J87,0) -> -159 | J101: =IFERROR('Cash Flow Data'!K87,0) -> -27 | ... L101: =IFERROR('Cash Flow Data'!M87,0) -> 55
B102: Cash from Investing Activities | C102: =SUM(C92:C101) -> -150 | D102: =SUM(D92:D101) -> -956 | E102: =SUM(E92:E101) -> -852 | F102: =SUM(F92:F101) -> -1525 | G102: =SUM(G92:G101) -> 459 | H102: =SUM(H92:H101) -> 915 | I102: =SUM(I92:I101) -> -1507 | J102: =SUM(J92:J101) -> 485 | ... L102: =SUM(L92:L101) -> -743
B104: Financing Activities
B105: Proceeds from shares | C105: =IFERROR('Cash Flow Data'!D89,0) -> 6 | D105: =IFERROR('Cash Flow Data'!E89,0) -> 15 | E105: =IFERROR('Cash Flow Data'!F89,0) -> 30 | F105: =IFERROR('Cash Flow Data'!G89,0) -> 24 | G105: =IFERROR('Cash Flow Data'!H89,0) -> 103 | H105: =IFERROR('Cash Flow Data'!I89,0) -> 0 | I105: =IFERROR('Cash Flow Data'!J89,0) -> 0 | J105: =IFERROR('Cash Flow Data'!K89,0) -> 0 | ... L105: =IFERROR('Cash Flow Data'!M89,0) -> 0
B106: Proceeds from debentures | C106: =IFERROR('Cash Flow Data'!D90,0) -> 0 | D106: =IFERROR('Cash Flow Data'!E90,0) -> 0 | E106: =IFERROR('Cash Flow Data'!F90,0) -> 0 | F106: =IFERROR('Cash Flow Data'!G90,0) -> 721 | G106: =IFERROR('Cash Flow Data'!H90,0) -> 0 | H106: =IFERROR('Cash Flow Data'!I90,0) -> 699 | I106: =IFERROR('Cash Flow Data'!J90,0) -> 0 | J106: =IFERROR('Cash Flow Data'!K90,0) -> 0 | ... L106: =IFERROR('Cash Flow Data'!M90,0) -> 0
B107: Redemption of debentures | C107: =IFERROR('Cash Flow Data'!D91,0) -> 0 | D107: =IFERROR('Cash Flow Data'!E91,0) -> 0 | E107: =IFERROR('Cash Flow Data'!F91,0) -> 0 | F107: =IFERROR('Cash Flow Data'!G91,0) -> -869 | G107: =IFERROR('Cash Flow Data'!H91,0) -> 0 | H107: =IFERROR('Cash Flow Data'!I91,0) -> 0 | I107: =IFERROR('Cash Flow Data'!J91,0) -> -721 | J107: =IFERROR('Cash Flow Data'!K91,0) -> 0 | ... L107: =IFERROR('Cash Flow Data'!M91,0) -> 0
B108: Proceeds from borrowings | C108: =IFERROR('Cash Flow Data'!D92,0) -> 0 | D108: =IFERROR('Cash Flow Data'!E92,0) -> 0 | E108: =IFERROR('Cash Flow Data'!F92,0) -> 0 | F108: =IFERROR('Cash Flow Data'!G92,0) -> 641 | G108: =IFERROR('Cash Flow Data'!H92,0) -> 568 | H108: =IFERROR('Cash Flow Data'!I92,0) -> 645 | I108: =IFERROR('Cash Flow Data'!J92,0) -> 1312 | J108: =IFERROR('Cash Flow Data'!K92,0) -> 201 | ... L108: =IFERROR('Cash Flow Data'!M92,0) -> 324
B109: Repayment of borrowings | C109: =IFERROR('Cash Flow Data'!D93,0) -> 0 | D109: =IFERROR('Cash Flow Data'!E93,0) -> 0 | E109: =IFERROR('Cash Flow Data'!F93,0) -> -42 | F109: =IFERROR('Cash Flow Data'!G93,0) -> 0 | G109: =IFERROR('Cash Flow Data'!H93,0) -> 0 | H109: =IFERROR('Cash Flow Data'!I93,0) -> -984 | I109: =IFERROR('Cash Flow Data'!J93,0) -> -70 | J109: =IFERROR('Cash Flow Data'!K93,0) -> -1141 | ... L109: =IFERROR('Cash Flow Data'!M93,0) -> -192
B110: Interest paid fin | C110: =IFERROR('Cash Flow Data'!D94,0) -> -6 | D110: =IFERROR('Cash Flow Data'!E94,0) -> -7 | E110: =IFERROR('Cash Flow Data'!F94,0) -> -9 | F110: =IFERROR('Cash Flow Data'!G94,0) -> -36 | G110: =IFERROR('Cash Flow Data'!H94,0) -> -102 | H110: =IFERROR('Cash Flow Data'!I94,0) -> -119 | I110: =IFERROR('Cash Flow Data'!J94,0) -> -196 | J110: =IFERROR('Cash Flow Data'!K94,0) -> -165 | ... L110: =IFERROR('Cash Flow Data'!M94,0) -> -108
B111: Dividends paid | C111: =IFERROR('Cash Flow Data'!D95,0) -> -288 | D111: =IFERROR('Cash Flow Data'!E95,0) -> -317 | E111: =IFERROR('Cash Flow Data'!F95,0) -> -354 | F111: =IFERROR('Cash Flow Data'!G95,0) -> -433 | G111: =IFERROR('Cash Flow Data'!H95,0) -> -2824 | H111: =IFERROR('Cash Flow Data'!I95,0) -> -2485 | I111: =IFERROR('Cash Flow Data'!J95,0) -> -1359 | J111: =IFERROR('Cash Flow Data'!K95,0) -> -1732 | ... L111: =IFERROR('Cash Flow Data'!M95,0) -> -1804
B112: Financial liabilities | C112: =IFERROR('Cash Flow Data'!D96,0) -> 0 | D112: =IFERROR('Cash Flow Data'!E96,0) -> 0 | E112: =IFERROR('Cash Flow Data'!F96,0) -> 0 | F112: =IFERROR('Cash Flow Data'!G96,0) -> -2 | G112: =IFERROR('Cash Flow Data'!H96,0) -> -3 | H112: =IFERROR('Cash Flow Data'!I96,0) -> -2 | I112: =IFERROR('Cash Flow Data'!J96,0) -> -3 | J112: =IFERROR('Cash Flow Data'!K96,0) -> -2 | ... L112: =IFERROR('Cash Flow Data'!M96,0) -> -3
B113: Other financing items | C113: =IFERROR('Cash Flow Data'!D97,0) -> -7 | D113: =IFERROR('Cash Flow Data'!E97,0) -> 78 | E113: =IFERROR('Cash Flow Data'!F97,0) -> 23 | F113: =IFERROR('Cash Flow Data'!G97,0) -> 12 | G113: =IFERROR('Cash Flow Data'!H97,0) -> 14 | H113: =IFERROR('Cash Flow Data'!I97,0) -> 0 | I113: =IFERROR('Cash Flow Data'!J97,0) -> 9 | J113: =IFERROR('Cash Flow Data'!K97,0) -> 0 | ... L113: =IFERROR('Cash Flow Data'!M97,0) -> 0
B114: Cash from Financing Activities | C114: =SUM(C105:C113) -> -295 | D114: =SUM(D105:D113) -> -231 | E114: =SUM(E105:E113) -> -352 | F114: =SUM(F105:F113) -> 58 | G114: =SUM(G105:G113) -> -2244 | H114: =SUM(H105:H113) -> -2246 | I114: =SUM(I105:I113) -> -1028 | J114: =SUM(J105:J113) -> -2839 | ... L114: =SUM(L105:L113) -> -1783
B116: Net Cash Flow | C116: =IFERROR(C114+C102+C89,0) -> -455 | D116: =IFERROR(D114+D102+D89,0) -> 291 | E116: =IFERROR(E114+E102+E89,0) -> -51 | F116: =IFERROR(F114+F102+F89,0) -> 145 | G116: =IFERROR(G114+G102+G89,0) -> 10 | H116: =IFERROR(H114+H102+H89,0) -> -358 | I116: =IFERROR(I114+I102+I89,0) -> 396 | J116: =IFERROR(J114+J102+J89,0) -> 380 | ... L116: =IFERROR(L114+L102+L89,0) -> -35
A118: # | B118: Short Cash Flow Statement
B120: Cash from Operating Activity | C120: =IFERROR(C89,0) -> -10 | D120: =IFERROR(D89,0) -> 1478 | E120: =IFERROR(E89,0) -> 1153 | F120: =IFERROR(F89,0) -> 1612 | G120: =IFERROR(G89,0) -> 1795 | H120: =IFERROR(H89,0) -> 973 | I120: =IFERROR(I89,0) -> 2931 | J120: =IFERROR(J89,0) -> 2734 | ... L120: =IFERROR(L89,0) -> 2491
B122: Cash from Investing Activity | C122: =IFERROR(C102,0) -> -150 | D122: =IFERROR(D102,0) -> -956 | E122: =IFERROR(E102,0) -> -852 | F122: =IFERROR(F102,0) -> -1525 | G122: =IFERROR(G102,0) -> 459 | H122: =IFERROR(H102,0) -> 915 | I122: =IFERROR(I102,0) -> -1507 | J122: =IFERROR(J102,0) -> 485 | ... L122: =IFERROR(L102,0) -> -743
B124: Cash from Financing Activity | C124: =IFERROR(C114,0) -> -295 | D124: =IFERROR(D114,0) -> -231 | E124: =IFERROR(E114,0) -> -352 | F124: =IFERROR(F114,0) -> 58 | G124: =IFERROR(G114,0) -> -2244 | H124: =IFERROR(H114,0) -> -2246 | I124: =IFERROR(I114,0) -> -1028 | J124: =IFERROR(J114,0) -> -2839 | ... L124: =IFERROR(L114,0) -> -1783
B126: Net Cash Flow | C126: =IFERROR(C124+C122+C120,0) -> -455 | D126: =IFERROR(D124+D122+D120,0) -> 291 | E126: =IFERROR(E124+E122+E120,0) -> -51 | F126: =IFERROR(F124+F122+F120,0) -> 145 | G126: =IFERROR(G124+G122+G120,0) -> 10 | H126: =IFERROR(H124+H122+H120,0) -> -358 | I126: =IFERROR(I124+I122+I120,0) -> 396 | J126: =IFERROR(J124+J122+J120,0) -> 380 | ... L126: =IFERROR(L124+L122+L120,0) -> -35

Sheet Ratio Analysis
B2: ='Data Sheet'!B1 -> BRITANNIA INDUSTRIES LTD
B3: (BRITANNIA) | BSE Code: 500825)
B4: INR 5,181.50 1st Sept 2026
B5: 52 Week (High - INR 6,336.95 & Low - 5,038)
M7: Prepared by Pushti Gandhi
B8: ="Ratio Analysis of"&" "&"-"&" "&'Data Sheet'!B1 -> Ratio Analysis of - BRITANNIA INDUSTRIES LTD
B9: Years | C9: ='Data Sheet'!B16 -> 42825 | D9: =C9+365 -> 43190 | E9: =D9+365 -> 43555 | F9: =E9+365 -> 43920 | G9: =F9+365 -> 44285 | H9: =G9+365 -> 44650 | I9: =H9+365 -> 45015 | J9: =I9+365 -> 45380 | K9: =J9+365 -> 45745 | L9: =K9+365 -> 46110 | M9: Trend | N9: Mean | O9: Median
B11: Sales Growth | C11: 0 | D11: =IFERROR('Historical FS'!D13,0) -> 0.094973653 | E11: =IFERROR('Historical FS'!E13,0) -> 0.11505761 | F11: =IFERROR('Historical FS'!F13,0) -> 0.049289576 | G11: =IFERROR('Historical FS'!G13,0) -> 0.13246979 | H11: =IFERROR('Historical FS'!H13,0) -> 0.076134999 | I11: =IFERROR('Historical FS'!I13,0) -> 0.15310202 | J11: =IFERROR('Historical FS'!J13,0) -> 0.028754858 | K11: =IFERROR('Historical FS'!K13,0) -> 0.069973231 | L11: =IFERROR('Historical FS'!L13,0) -> 0.067376817 | N11: =IFERROR(AVERAGE(D11:L11),0) -> 0.087459173 | O11: =IFERROR(MEDIAN(C11:L11),0) -> 0.073054115
B12: EBITDA Growth | C12: 0 | D12: =IFERROR('Historical FS'!D24/'Historical FS'!C24-1,0) -> 0.17469371 | E12: =IFERROR('Historical FS'!E24/'Historical FS'!D24-1,0) -> 0.15383591 | F12: =IFERROR('Historical FS'!F24/'Historical FS'!E24-1,0) -> 0.063915265 | G12: =IFERROR('Historical FS'!G24/'Historical FS'!F24-1,0) -> 0.36139173 | H12: =IFERROR('Historical FS'!H24/'Historical FS'!G24-1,0) -> -0.12273591 | I12: =IFERROR('Historical FS'!I24/'Historical FS'!H24-1,0) -> 0.28601151 | J12: =IFERROR('Historical FS'!J24/'Historical FS'!I24-1,0) -> 0.11859791 | K12: =IFERROR('Historical FS'!K24/'Historical FS'!J24-1,0) -> 0.0030821215 | L12: =IFERROR('Historical FS'!L24/'Historical FS'!K24-1,0) -> 0.1063874 | N12: =IFERROR(AVERAGE(D12:L12),0) -> 0.12724218 | O12: =IFERROR(MEDIAN(C12:L12),0) -> 0.11249265
B13: EBIT Growth | C13: 0 | D13: =IFERROR('Historical FS'!D33/'Historical FS'!C33-1,0) -> 0.17299877 | E13: =IFERROR('Historical FS'!E33/'Historical FS'!D33-1,0) -> 0.15534059 | F13: =IFERROR('Historical FS'!F33/'Historical FS'!E33-1,0) -> 0.055903271 | G13: =IFERROR('Historical FS'!G33/'Historical FS'!F33-1,0) -> 0.39380235 | H13: =IFERROR('Historical FS'!H33/'Historical FS'!G33-1,0) -> -0.13440539 | I13: =IFERROR('Historical FS'!I33/'Historical FS'!H33-1,0) -> 0.30199873 | J13: =IFERROR('Historical FS'!J33/'Historical FS'!I33-1,0) -> 0.10026488 | K13: =IFERROR('Historical FS'!K33/'Historical FS'!J33-1,0) -> -0.0010885531 | L13: =IFERROR('Historical FS'!L33/'Historical FS'!K33-1,0) -> 0.10982617 | N13: =IFERROR(AVERAGE(D13:L13),0) -> 0.12829342 | O13: =IFERROR(MEDIAN(C13:L13),0) -> 0.10504552
B14: Net Profit Growth | C14: 0 | D14: =IFERROR('Historical FS'!D42/'Historical FS'!C42-1,0) -> 0.14145737 | E14: =IFERROR('Historical FS'!E42/'Historical FS'!D42-1,0) -> 0.13302451 | F14: =IFERROR('Historical FS'!F42/'Historical FS'!E42-1,0) -> 0.19152591 | G14: =IFERROR('Historical FS'!G42/'Historical FS'!F42-1,0) -> 0.35971064 | H14: =IFERROR('Historical FS'!H42/'Historical FS'!G42-1,0) -> -0.15830038 | I14: =IFERROR('Historical FS'!I42/'Historical FS'!H42-1,0) -> 0.32865323 | J14: =IFERROR('Historical FS'!J42/'Historical FS'!I42-1,0) -> 0.11834598 | K14: =IFERROR('Historical FS'!K42/'Historical FS'!J42-1,0) -> 0.027364348 | L14: =IFERROR('Historical FS'!L42/'Historical FS'!K42-1,0) -> 0.17079714 | N14: =IFERROR(AVERAGE(D14:L14),0) -> 0.14584208 | O14: =IFERROR(MEDIAN(C14:L14),0) -> 0.13724094
B15: Dividend Growth | C15: 0 | D15: =IFERROR('Historical FS'!D50/'Historical FS'!C50-1,0) -> 0.1363447 | E15: =IFERROR('Historical FS'!E50/'Historical FS'!D50-1,0) -> 0.20001999 | F15: =IFERROR('Historical FS'!F50/'Historical FS'!E50-1,0) -> 1.3333333 | G15: =IFERROR('Historical FS'!G50/'Historical FS'!F50-1,0) -> 3.5000059 | H15: =IFERROR('Historical FS'!H50/'Historical FS'!G50-1,0) -> -0.64127163 | I15: =IFERROR('Historical FS'!I50/'Historical FS'!H50-1,0) -> 0.27434096 | J15: =IFERROR('Historical FS'!J50/'Historical FS'!I50-1,0) -> 0.020836216 | K15: =IFERROR('Historical FS'!K50/'Historical FS'!J50-1,0) -> 0.020405282 | L15: =IFERROR('Historical FS'!L50/'Historical FS'!K50-1,0) -> 0.2066639 | N15: =IFERROR(AVERAGE(D15:L15),0) -> 0.56118652 | O15: =IFERROR(MEDIAN(C15:L15),0) -> 0.16818235
B17: Gross Margin | C17: =IFERROR('Historical FS'!C16,0) -> 0.72403742 | D17: =IFERROR('Historical FS'!D16,0) -> 0.71869348 | E17: =IFERROR('Historical FS'!E16,0) -> 0.70556335 | F17: =IFERROR('Historical FS'!F16,0) -> 0.70714295 | G17: =IFERROR('Historical FS'!G16,0) -> 0.68574026 | H17: =IFERROR('Historical FS'!H16,0) -> 0.72667948 | I17: =IFERROR('Historical FS'!I16,0) -> 0.70032177 | J17: =IFERROR('Historical FS'!J16,0) -> 0.68005942 | ... L17: =IFERROR('Historical FS'!L16,0) -> 0.69029412 | N17: =IFERROR(AVERAGE(C17:L17),0) -> 0.70419198 | O17: =IFERROR(MEDIAN(C17:L17),0) -> 0.70447543
B18: EBITDA Margin | C18: =IFERROR('Historical FS'!C25,0) -> 0.14117156 | D18: =IFERROR('Historical FS'!D25,0) -> 0.15144962 | E18: =IFERROR('Historical FS'!E25,0) -> 0.15671657 | F18: =IFERROR('Historical FS'!F25,0) -> 0.15890099 | G18: =IFERROR('Historical FS'!G25,0) -> 0.19102187 | H18: =IFERROR('Historical FS'!H25,0) -> 0.15572082 | I18: =IFERROR('Historical FS'!I25,0) -> 0.1736696 | J18: =IFERROR('Historical FS'!J25,0) -> 0.18883648 | ... L18: =IFERROR('Historical FS'!L25,0) -> 0.18350121 | N18: =IFERROR(AVERAGE(C18:L18),0) -> 0.16780198 | O18: =IFERROR(MEDIAN(C18:L18),0) -> 0.1662853
B19: EBIT Margin | C19: =IFERROR('Historical FS'!C34,0) -> 0.12799851 | D19: =IFERROR('Historical FS'!D34,0) -> 0.13711936 | E19: =IFERROR('Historical FS'!E34,0) -> 0.14207299 | F19: =IFERROR('Historical FS'!F34,0) -> 0.14296848 | G19: =IFERROR('Historical FS'!G34,0) -> 0.17596037 | H19: =IFERROR('Historical FS'!H34,0) -> 0.14153461 | I19: =IFERROR('Historical FS'!I34,0) -> 0.15981056 | J19: =IFERROR('Historical FS'!J34,0) -> 0.17091919 | ... L19: =IFERROR('Historical FS'!L34,0) -> 0.16591364 | N19: =IFERROR(AVERAGE(C19:L19),0) -> 0.15238654 | O19: =IFERROR(MEDIAN(C19:L19),0) -> 0.15126807
B20: EBT Margin | C20: =IFERROR('Historical FS'!C37,0) -> 0.12739657 | D20: =IFERROR('Historical FS'!D37,0) -> 0.13635378 | E20: =IFERROR('Historical FS'!E37,0) -> 0.14125071 | F20: =IFERROR('Historical FS'!F37,0) -> 0.13633891 | G20: =IFERROR('Historical FS'!G37,0) -> 0.16751801 | H20: =IFERROR('Historical FS'!H37,0) -> 0.13132752 | I20: =IFERROR('Historical FS'!I37,0) -> 0.14943668 | J20: =IFERROR('Historical FS'!J37,0) -> 0.16113939 | ... L20: =IFERROR('Historical FS'!L37,0) -> 0.16002588 | N20: =IFERROR(AVERAGE(C20:L20),0) -> 0.14626194 | O20: =IFERROR(MEDIAN(C20:L20),0) -> 0.14534369
B21: Net Profit Margin | C21: =IFERROR('Historical FS'!C43,0) -> 0.081045141 | D21: =IFERROR('Historical FS'!D43,0) -> 0.084485661 | E21: =IFERROR('Historical FS'!E43,0) -> 0.085846977 | F21: =IFERROR('Historical FS'!F43,0) -> 0.097483954 | G21: =IFERROR('Historical FS'!G43,0) -> 0.11704504 | H21: =IFERROR('Historical FS'!H43,0) -> 0.091546845 | I21: =IFERROR('Historical FS'!I43,0) -> 0.10548417 | J21: =IFERROR('Historical FS'!J43,0) -> 0.11467047 | ... L21: =IFERROR('Historical FS'!L43,0) -> 0.12077222 | N21: =IFERROR(AVERAGE(C21:L21),0) -> 0.10084845 | O21: =IFERROR(MEDIAN(C21:L21),0) -> 0.10148406
B23: Sales Expenses % Sales | C23: =IFERROR('Historical FS'!C22,0) -> 0.13479102 | D23: =IFERROR('Historical FS'!D22,0) -> 0.1298569 | E23: =IFERROR('Historical FS'!E22,0) -> 0.13772008 | F23: =IFERROR('Historical FS'!F22,0) -> 0.13395606 | G23: =IFERROR('Historical FS'!G22,0) -> 0.12323788 | H23: =IFERROR('Historical FS'!H22,0) -> 0.1175997 | I23: =IFERROR('Historical FS'!I22,0) -> 0.12600863 | J23: =IFERROR('Historical FS'!J22,0) -> 0.1311041 | ... L23: =IFERROR('Historical FS'!L22,0) -> 0.12620466 | N23: =IFERROR(AVERAGE(C23:L23),0) -> 0.12800604 | O23: =IFERROR(MEDIAN(C23:L23),0) -> 0.12803078
B24: Depreciation % Sales | C24: =IFERROR('Historical FS'!C31,0) -> 0.013173052 | D24: =IFERROR('Historical FS'!D31,0) -> 0.014330255 | E24: =IFERROR('Historical FS'!E31,0) -> 0.014643585 | F24: =IFERROR('Historical FS'!F31,0) -> 0.015932515 | G24: =IFERROR('Historical FS'!G31,0) -> 0.015061502 | H24: =IFERROR('Historical FS'!H31,0) -> 0.014186213 | I24: =IFERROR('Historical FS'!I31,0) -> 0.013859042 | J24: =IFERROR('Historical FS'!J31,0) -> 0.017917298 | ... L24: =IFERROR('Historical FS'!L31,0) -> 0.017587574 | N24: =IFERROR(AVERAGE(C24:L24),0) -> 0.015415443 | O24: =IFERROR(MEDIAN(C24:L24),0) -> 0.014852544
B25: Operating Income % Sales | C25: =IFERROR(C19,0) -> 0.12799851 | D25: =IFERROR(D19,0) -> 0.13711936 | E25: =IFERROR(E19,0) -> 0.14207299 | F25: =IFERROR(F19,0) -> 0.14296848 | G25: =IFERROR(G19,0) -> 0.17596037 | H25: =IFERROR(H19,0) -> 0.14153461 | I25: =IFERROR(I19,0) -> 0.15981056 | J25: =IFERROR(J19,0) -> 0.17091919 | ... L25: =IFERROR(L19,0) -> 0.16591364 | N25: =IFERROR(AVERAGE(C25:L25),0) -> 0.15238654 | O25: =IFERROR(MEDIAN(C25:L25),0) -> 0.15126807
B27: Return on Capital Employed | C27: =IFERROR('Historical FS'!C33/SUM('Historical FS'!C57:C59),0) -> 0.41081823 | D27: =IFERROR('Historical FS'!D33/SUM('Historical FS'!D57:D59),0) -> 0.37688561 | E27: =IFERROR('Historical FS'!E33/SUM('Historical FS'!E57:E59),0) -> 0.35619728 | F27: =IFERROR('Historical FS'!F33/SUM('Historical FS'!F57:F59),0) -> 0.27916713 | G27: =IFERROR('Historical FS'!G33/SUM('Historical FS'!G57:G59),0) -> 0.40877162 | H27: =IFERROR('Historical FS'!H33/SUM('Historical FS'!H57:H59),0) -> 0.39703332 | I27: =IFERROR('Historical FS'!I33/SUM('Historical FS'!I57:I59),0) -> 0.39882786 | J27: =IFERROR('Historical FS'!J33/SUM('Historical FS'!J57:J59),0) -> 0.47718298 | ... L27: =IFERROR('Historical FS'!L33/SUM('Historical FS'!L57:L59),0) -> 0.48983943 | N27: =IFERROR(AVERAGE(C27:L27),0) -> 0.41057824 | O27: =IFERROR(MEDIAN(C27:L27),0) -> 0.40379974
B28: Retained Earnings % | C28: =IFERROR('Historical FS'!C53,0) -> 0.64022404 | D28: =IFERROR('Historical FS'!D53,0) -> 0.64168627 | E28: =IFERROR('Historical FS'!E53,0) -> 0.62018314 | F28: =IFERROR('Historical FS'!F53,0) -> 0.25559574 | G28: =IFERROR('Historical FS'!G53,0) -> 0 | H28: =IFERROR('Historical FS'!H53,0) -> 0 | I28: =IFERROR('Historical FS'!I53,0) -> 0 | J28: =IFERROR('Historical FS'!J53,0) -> 0.07921204 | ... L28: =IFERROR('Historical FS'!L53,0) -> 0.057432403 | N28: =IFERROR(AVERAGE(C28:L28),0) -> 0.23797828 | O28: =IFERROR(MEDIAN(C28:L28),0) -> 0.082330614
B29: Return on Equity % | C29: =IFERROR('Historical FS'!C42/SUM('Historical FS'!C57:C58),0) -> 0.2721349 | D29: =IFERROR('Historical FS'!D42/SUM('Historical FS'!D57:D58),0) -> 0.24589943 | E29: =IFERROR('Historical FS'!E42/SUM('Historical FS'!E57:E58),0) -> 0.22312584 | F29: =IFERROR('Historical FS'!F42/SUM('Historical FS'!F57:F58),0) -> 0.25682799 | G29: =IFERROR('Historical FS'!G42/SUM('Historical FS'!G57:G58),0) -> 0.4333899 | H29: =IFERROR('Historical FS'!H42/SUM('Historical FS'!H57:H58),0) -> 0.505895 | I29: =IFERROR('Historical FS'!I42/SUM('Historical FS'!I57:I58),0) -> 0.48650782 | J29: =IFERROR('Historical FS'!J42/SUM('Historical FS'!J57:J58),0) -> 0.48786762 | ... L29: =IFERROR('Historical FS'!L42/SUM('Historical FS'!L57:L58),0) -> 0.45294288 | N29: =IFERROR(AVERAGE(C29:L29),0) -> 0.38181467 | O29: =IFERROR(MEDIAN(C29:L29),0) -> 0.44316639
B30: Self Sustained Growth Rate | C30: =IFERROR(C28*C29,0) -> 0.17422731 | D30: =IFERROR(D28*D29,0) -> 0.15779028 | E30: =IFERROR(E28*E29,0) -> 0.13837889 | F30: =IFERROR(F28*F29,0) -> 0.065644143 | G30: =IFERROR(G28*G29,0) -> 0 | H30: =IFERROR(H28*H29,0) -> 0 | I30: =IFERROR(I28*I29,0) -> 0 | J30: =IFERROR(J28*J29,0) -> 0.03864499 | ... L30: =IFERROR(L28*L29,0) -> 0.026013598 | N30: =IFERROR(AVERAGE(C30:L30),0) -> 0.063945514 | O30: =IFERROR(MEDIAN(C30:L30),0) -> 0.038700462
B31: Interest Coverage Ratio | C31: =IFERROR('Historical FS'!C33/'Historical FS'!C27,0) -> 212.64404 | D31: =IFERROR('Historical FS'!D33/'Historical FS'!D27,0) -> 179.10408 | E31: =IFERROR('Historical FS'!E33/'Historical FS'!E27,0) -> 172.77998 | F31: =IFERROR('Historical FS'!F33/'Historical FS'!F27,0) -> 21.56528 | G31: =IFERROR('Historical FS'!G33/'Historical FS'!G27,0) -> 20.842561 | H31: =IFERROR('Historical FS'!H33/'Historical FS'!H27,0) -> 13.866311 | I31: =IFERROR('Historical FS'!I33/'Historical FS'!I27,0) -> 15.405086 | J31: =IFERROR('Historical FS'!J33/'Historical FS'!J27,0) -> 17.476768 | ... L31: =IFERROR('Historical FS'!L33/'Historical FS'!L27,0) -> 28.179408 | N31: =IFERROR(AVERAGE(C31:L31),0) -> 70.249082 | O31: =IFERROR(MEDIAN(C31:L31),0) -> 21.20392
B33: Debtor Turnover Ratio | C33: =IFERROR('Historical FS'!C12/'Historical FS'!C69,0) -> 50.536336 | D33: =IFERROR('Historical FS'!D12/'Historical FS'!D69,0) -> 32.547571 | E33: =IFERROR('Historical FS'!E12/'Historical FS'!E69,0) -> 28.040458 | F33: =IFERROR('Historical FS'!F12/'Historical FS'!F69,0) -> 36.20786 | G33: =IFERROR('Historical FS'!G12/'Historical FS'!G69,0) -> 51.059743 | H33: =IFERROR('Historical FS'!H12/'Historical FS'!H69,0) -> 42.588076 | I33: =IFERROR('Historical FS'!I12/'Historical FS'!I69,0) -> 49.554782 | J33: =IFERROR('Historical FS'!J12/'Historical FS'!J69,0) -> 42.634099 | ... L33: =IFERROR('Historical FS'!L12/'Historical FS'!L69,0) -> 40.816671 | N33: =IFERROR(AVERAGE(C33:L33),0) -> 41.398174 | O33: =IFERROR(MEDIAN(C33:L33),0) -> 41.702373
B34: Creditor Turnover Ratio | C34: =IFERROR('Historical FS'!C12/'Historical FS'!C60,0) -> 7.0305555 | D34: =IFERROR('Historical FS'!D12/'Historical FS'!D60,0) -> 6.2707481 | E34: =IFERROR('Historical FS'!E12/'Historical FS'!E60,0) -> 6.0451637 | F34: =IFERROR('Historical FS'!F12/'Historical FS'!F60,0) -> 6.140187 | G34: =IFERROR('Historical FS'!G12/'Historical FS'!G60,0) -> 5.6005952 | H34: =IFERROR('Historical FS'!H12/'Historical FS'!H60,0) -> 5.6833755 | I34: =IFERROR('Historical FS'!I12/'Historical FS'!I60,0) -> 5.7819566 | J34: =IFERROR('Historical FS'!J12/'Historical FS'!J60,0) -> 5.471178 | ... L34: =IFERROR('Historical FS'!L12/'Historical FS'!L60,0) -> 5.9046425 | N34: =IFERROR(AVERAGE(C34:L34),0) -> 5.9475646 | O34: =IFERROR(MEDIAN(C34:L34),0) -> 5.8432996
B35: Inventory Turnover Ratio | C35: =IFERROR('Historical FS'!C12/'Historical FS'!C70,0) -> 13.688246 | D35: =IFERROR('Historical FS'!D12/'Historical FS'!D70,0) -> 15.187105 | E35: =IFERROR('Historical FS'!E12/'Historical FS'!E70,0) -> 14.147623 | F35: =IFERROR('Historical FS'!F12/'Historical FS'!F70,0) -> 15.654759 | G35: =IFERROR('Historical FS'!G12/'Historical FS'!G70,0) -> 12.035053 | H35: =IFERROR('Historical FS'!H12/'Historical FS'!H70,0) -> 10.337377 | I35: =IFERROR('Historical FS'!I12/'Historical FS'!I70,0) -> 13.660518 | J35: =IFERROR('Historical FS'!J12/'Historical FS'!J70,0) -> 14.196568 | ... L35: =IFERROR('Historical FS'!L12/'Historical FS'!L70,0) -> 14.229262 | N35: =IFERROR(AVERAGE(C35:L35),0) -> 13.764725 | O35: =IFERROR(MEDIAN(C35:L35),0) -> 14.172096
B36: Fixed Asset Turnover | C36: =IFERROR('Historical FS'!C12/'Historical FS'!C63,0) -> 7.8053173 | D36: =IFERROR('Historical FS'!D12/'Historical FS'!D63,0) -> 7.3677096 | E36: =IFERROR('Historical FS'!E12/'Historical FS'!E63,0) -> 6.5478114 | F36: =IFERROR('Historical FS'!F12/'Historical FS'!F63,0) -> 6.1759523 | G36: =IFERROR('Historical FS'!G12/'Historical FS'!G63,0) -> 7.3265512 | H36: =IFERROR('Historical FS'!H12/'Historical FS'!H63,0) -> 8.0630729 | I36: =IFERROR('Historical FS'!I12/'Historical FS'!I63,0) -> 6.1390582 | J36: =IFERROR('Historical FS'!J12/'Historical FS'!J63,0) -> 6.0513976 | ... L36: =IFERROR('Historical FS'!L12/'Historical FS'!L63,0) -> 6.7200448 | N36: =IFERROR(AVERAGE(C36:L36),0) -> 6.8375946 | O36: =IFERROR(MEDIAN(C36:L36),0) -> 6.6339281
B37: Capital Turnover Ratio | C37: =IFERROR('Historical FS'!C12/SUM('Historical FS'!C57:C58),0) -> 3.3578189 | D37: =IFERROR('Historical FS'!D12/SUM('Historical FS'!D57:D58),0) -> 2.9105463 | E37: =IFERROR('Historical FS'!E12/SUM('Historical FS'!E57:E58),0) -> 2.5991113 | F37: =IFERROR('Historical FS'!F12/SUM('Historical FS'!F57:F58),0) -> 2.6345669 | G37: =IFERROR('Historical FS'!G12/SUM('Historical FS'!G57:G58),0) -> 3.7027618 | H37: =IFERROR('Historical FS'!H12/SUM('Historical FS'!H57:H58),0) -> 5.5260779 | I37: =IFERROR('Historical FS'!I12/SUM('Historical FS'!I57:I58),0) -> 4.6121406 | J37: =IFERROR('Historical FS'!J12/SUM('Historical FS'!J57:J58),0) -> 4.2545186 | ... L37: =IFERROR('Historical FS'!L12/SUM('Historical FS'!L57:L58),0) -> 3.7503897 | N37: =IFERROR(AVERAGE(C37:L37),0) -> 3.7467267 | O37: =IFERROR(MEDIAN(C37:L37),0) -> 3.7265758
B39: Debtor Days | C39: =IFERROR(365/C33,0) -> 7.222526 | D39: =IFERROR(365/D33,0) -> 11.214355 | E39: =IFERROR(365/E33,0) -> 13.016906 | F39: =IFERROR(365/F33,0) -> 10.080684 | G39: =IFERROR(365/G33,0) -> 7.1484888 | H39: =IFERROR(365/H33,0) -> 8.5704741 | I39: =IFERROR(365/I33,0) -> 7.3655858 | J39: =IFERROR(365/J33,0) -> 8.5612224 | ... L39: =IFERROR(365/L33,0) -> 8.9424246 | N39: =IFERROR(AVERAGE(C39:L39),0) -> 9.1248546 | O39: =IFERROR(MEDIAN(C39:L39),0) -> 8.7564494
B40: Payable Days | C40: =IFERROR(365/C34,0) -> 51.916239 | D40: =IFERROR(365/D34,0) -> 58.206771 | E40: =IFERROR(365/E34,0) -> 60.378844 | F40: =IFERROR(365/F34,0) -> 59.444444 | G40: =IFERROR(365/G34,0) -> 65.171645 | H40: =IFERROR(365/H34,0) -> 64.222397 | I40: =IFERROR(365/I34,0) -> 63.127419 | J40: =IFERROR(365/J34,0) -> 66.713238 | ... L40: =IFERROR(365/L34,0) -> 61.815766 | N40: =IFERROR(AVERAGE(C40:L40),0) -> 61.679521 | O40: =IFERROR(MEDIAN(C40:L40),0) -> 62.471592
B41: Inventory Days | C41: =IFERROR(365/C35,0) -> 26.665214 | D41: =IFERROR(365/D35,0) -> 24.033548 | E41: =IFERROR(365/E35,0) -> 25.799386 | F41: =IFERROR(365/F35,0) -> 23.315594 | G41: =IFERROR(365/G35,0) -> 30.328076 | H41: =IFERROR(365/H35,0) -> 35.308763 | I41: =IFERROR(365/I35,0) -> 26.719338 | J41: =IFERROR(365/J35,0) -> 25.710439 | ... L41: =IFERROR(365/L35,0) -> 25.651366 | N41: =IFERROR(AVERAGE(C41:L41),0) -> 26.868551 | O41: =IFERROR(MEDIAN(C41:L41),0) -> 25.754913
B42: Cash Conversion Cycle (in days) | C42: =IFERROR(SUM(C39,C41)-C40,0) -> -18.028499 | D42: =IFERROR(SUM(D39,D41)-D40,0) -> -22.958869 | E42: =IFERROR(SUM(E39,E41)-E40,0) -> -21.562552 | F42: =IFERROR(SUM(F39,F41)-F40,0) -> -26.048166 | G42: =IFERROR(SUM(G39,G41)-G40,0) -> -27.69508 | H42: =IFERROR(SUM(H39,H41)-H40,0) -> -20.34316 | I42: =IFERROR(SUM(I39,I41)-I40,0) -> -29.042495 | J42: =IFERROR(SUM(J39,J41)-J40,0) -> -32.441576 | ... L42: =IFERROR(SUM(L39,L41)-L40,0) -> -27.221975 | N42: =IFERROR(AVERAGE(C42:L42),0) -> -25.686115 | O42: =IFERROR(MEDIAN(C42:L42),0) -> -26.63507
B44: CFO/Sales | C44: =IFERROR('Historical FS'!C89/'Historical FS'!C12,0) -> -0.0011044732 | D44: =IFERROR('Historical FS'!D89/'Historical FS'!D12,0) -> 0.14908226 | E44: =IFERROR('Historical FS'!E89/'Historical FS'!E12,0) -> 0.10429981 | F44: =IFERROR('Historical FS'!F89/'Historical FS'!F12,0) -> 0.13897091 | G44: =IFERROR('Historical FS'!G89/'Historical FS'!G12,0) -> 0.13664592 | H44: =IFERROR('Historical FS'!H89/'Historical FS'!H12,0) -> 0.068830087 | I44: =IFERROR('Historical FS'!I89/'Historical FS'!I12,0) -> 0.17980988 | J44: =IFERROR('Historical FS'!J89/'Historical FS'!J12,0) -> 0.16303632 | ... L44: =IFERROR('Historical FS'!L89/'Historical FS'!L12,0) -> 0.13006753 | N44: =IFERROR(AVERAGE(C44:L44),0) -> 0.12088037 | O44: =IFERROR(MEDIAN(C44:L44),0) -> 0.13780842
B45: CFO/Total Assets | C45: =IFERROR('Historical FS'!C89/'Historical FS'!C74,0) -> -0.0024338006 | D45: =IFERROR('Historical FS'!D89/'Historical FS'!D74,0) -> 0.2848926 | E45: =IFERROR('Historical FS'!E89/'Historical FS'!E74,0) -> 0.18483636 | F45: =IFERROR('Historical FS'!F89/'Historical FS'!F74,0) -> 0.20588694 | G45: =IFERROR('Historical FS'!G89/'Historical FS'!G74,0) -> 0.22437248 | H45: =IFERROR('Historical FS'!H89/'Historical FS'!H74,0) -> 0.12927484 | I45: =IFERROR('Historical FS'!I89/'Historical FS'!I74,0) -> 0.31344744 | J45: =IFERROR('Historical FS'!J89/'Historical FS'!J74,0) -> 0.30138345 | ... L45: =IFERROR('Historical FS'!L89/'Historical FS'!L74,0) -> 0.25600391 | N45: =IFERROR(AVERAGE(C45:L45),0) -> 0.21802342 | O45: =IFERROR(MEDIAN(C45:L45),0) -> 0.24018819
B46: CFO/Total Debt | C46: =IFERROR('Historical FS'!C89/'Historical FS'!C59,0) -> -0.080282595 | D46: =IFERROR('Historical FS'!D89/'Historical FS'!D59,0) -> 7.3642252 | E46: =IFERROR('Historical FS'!E89/'Historical FS'!E59,0) -> 7.3900782 | F46: =IFERROR('Historical FS'!F89/'Historical FS'!F59,0) -> 1.0483939 | G46: =IFERROR('Historical FS'!G89/'Historical FS'!G59,0) -> 0.85194642 | H46: =IFERROR('Historical FS'!H89/'Historical FS'!H59,0) -> 0.39214896 | I46: =IFERROR('Historical FS'!I89/'Historical FS'!I59,0) -> 0.97785725 | J46: =IFERROR('Historical FS'!J89/'Historical FS'!J59,0) -> 1.3239966 | ... L46: =IFERROR('Historical FS'!L89/'Historical FS'!L59,0) -> 1.8047063 | N46: =IFERROR(AVERAGE(C46:L46),0) -> 2.3076263 | O46: =IFERROR(MEDIAN(C46:L46),0) -> 1.1861953

Sheet Forecasting
B2: ='Data Sheet'!B1 -> BRITANNIA INDUSTRIES LTD
B3: (BRITANNIA) | BSE Code: 500825)
B4: INR 5,181.50 1st Sept 2026
B5: 52 Week (High - INR 6,336.95 & Low - 5,038)
M6: Prepared by Pushti Gandhi
B7: ='Data Sheet'!B1&" "&"-"&" "&'Data Sheet'!A17&" "&"Forecasting" -> BRITANNIA INDUSTRIES LTD - Sales Forecasting | G7: ='Data Sheet'!B1&" "&"-"&" "&'Historical FS'!B24&" "&"Forecasting" -> BRITANNIA INDUSTRIES LTD - EBITDA Forecasting | L7: ='Data Sheet'!B1&" "&"-"&" "&'Historical FS'!B47&" "&"Forecasting" -> BRITANNIA INDUSTRIES LTD - Earning Per Share Forecasting
B8: Year weight | C8: Year | D8: Sales | E8: Sales Growth | G8: Year weight | H8: Year | I8: EBITDA | J8: EBITDA Growth | L8: Year weight | M8: Year | N8: EPS | O8: EPS Growth
B9: 1 | C9: ='Data Sheet'!$B$16 -> 42825 | D9: {=TRANSPOSE('Data Sheet'!B17:K17)} -> 9054.09 | G9: 1 | H9: ='Data Sheet'!$B$16 -> 42825 | I9: {=TRANSPOSE('Historical FS'!C24:L24)} -> 1278.18 | L9: 1 | M9: ='Data Sheet'!$B$16 -> 42825 | N9: {=TRANSPOSE('Historical FS'!C47:L47)} -> 30.574583
B10: =B9+1 -> 2 | C10: =C9+365 -> 43190 | D10: 9913.99 | E10: =D10/D9-1 -> 0.094973653 | G10: =G9+1 -> 2 | H10: =H9+365 -> 43190 | I10: 1501.47 | J10: =I10/I9-1 -> 0.17469371 | L10: =L9+1 -> 2 | M10: =M9+365 -> 43190 | N10: 34.885048 | O10: =N10/N9-1 -> 0.14098196
B11: =B10+1 -> 3 | C11: =C10+365 -> 43555 | D11: 11054.67 | E11: =D11/D10-1 -> 0.11505761 | G11: =G10+1 -> 3 | H11: =H10+365 -> 43555 | I11: 1732.45 | J11: =I11/I10-1 -> 0.15383591 | L11: =L10+1 -> 3 | M11: =M10+365 -> 43555 | N11: 39.492717 | O11: =N11/N10-1 -> 0.1320815
B12: =B11+1 -> 4 | C12: =C11+365 -> 43920 | D12: 11599.55 | E12: =D12/D11-1 -> 0.049289576 | G12: =G11+1 -> 4 | H12: =H11+365 -> 43920 | I12: 1843.18 | J12: =I12/I11-1 -> 0.063915265 | L12: =L11+1 -> 4 | M12: =M11+365 -> 43920 | N12: 47.017464 | O12: =N12/N11-1 -> 0.19053503
B13: =B12+1 -> 5 | C13: =C12+365 -> 44285 | D13: 13136.14 | E13: =D13/D12-1 -> 0.13246979 | G13: =G12+1 -> 5 | H13: =H12+365 -> 44285 | I13: 2509.29 | J13: =I13/I12-1 -> 0.36139173 | L13: =L12+1 -> 5 | M13: =M12+365 -> 44285 | N13: 63.823993 | O13: =N13/N12-1 -> 0.35745292
B14: =B13+1 -> 6 | C14: =C13+365 -> 44650 | D14: 14136.26 | E14: =D14/D13-1 -> 0.076134999 | G14: =G13+1 -> 6 | H14: =H13+365 -> 44650 | I14: 2201.31 | J14: =I14/I13-1 -> -0.12273591 | L14: =L13+1 -> 6 | M14: =M13+365 -> 44650 | N14: 53.720631 | O14: =N14/N13-1 -> -0.15830038
B15: =B14+1 -> 7 | C15: =C14+365 -> 45015 | D15: 16300.55 | E15: =D15/D14-1 -> 0.15310202 | G15: =G14+1 -> 7 | H15: =H14+365 -> 45015 | I15: 2830.91 | J15: =I15/I14-1 -> 0.28601151 | L15: =L14+1 -> 7 | M15: =M14+365 -> 45015 | N15: 71.37609 | O15: =N15/N14-1 -> 0.32865323
B16: =B15+1 -> 8 | C16: =C15+365 -> 45380 | D16: 16769.27 | E16: =D16/D15-1 -> 0.028754858 | G16: =G15+1 -> 8 | H16: =H15+365 -> 45380 | I16: 3166.65 | J16: =I16/I15-1 -> 0.11859791 | L16: =L15+1 -> 8 | M16: =M15+365 -> 45380 | N16: 79.823163 | O16: =N16/N15-1 -> 0.11834598
B17: =B16+1 -> 9 | C17: =C16+365 -> 45745 | D17: 17942.67 | E17: =D17/D16-1 -> 0.069973231 | G17: =G16+1 -> 9 | H17: =H16+365 -> 45745 | I17: 3176.41 | J17: =I17/I16-1 -> 0.0030821215 | L17: =L16+1 -> 9 | M17: =M16+365 -> 45745 | N17: 82.007472 | O17: =N17/N16-1 -> 0.027364348
B18: =B17+1 -> 10 | C18: =C17+365 -> 46110 | D18: 19151.59 | E18: =D18/D17-1 -> 0.067376817 | G18: =G17+1 -> 10 | H18: =H17+365 -> 46110 | I18: 3514.34 | J18: =I18/I17-1 -> 0.1063874 | L18: =L17+1 -> 10 | M18: =M17+365 -> 46110 | N18: 96.014114 | O18: =N18/N17-1 -> 0.17079714
B19: =B18+1 -> 11 | C19: =C18+365 -> 46475 | D19: =_xlfn.FORECAST.ETS(B19,$D$9:$D$18,$B$9:$B$18) -> 20299.418 | E19: =D19/D18-1 -> 0.059933799 | G19: =G18+1 -> 11 | H19: =H18+365 -> 46475 | I19: =FORECAST(G19,$I$9:$I$18, $G$9:$G$18) -> 3764.6267 | J19: =I19/I18-1 -> 0.071218683 | L19: =L18+1 -> 11 | M19: =M18+365 -> 46475 | N19: =FORECAST(L19,$N$9:$N$18,$L$9:$L$18) -> 99.321444 | O19: =N19/N18-1 -> 0.03444629
B20: =B19+1 -> 12 | C20: =C19+365 -> 46840 | D20: =_xlfn.FORECAST.ETS(B20,$D$9:$D$18,$B$9:$B$18) -> 21454.283 | E20: =D20/D19-1 -> 0.056891575 | G20: =G19+1 -> 12 | H20: =H19+365 -> 46840 | I20: =FORECAST(G20,$I$9:$I$18, $G$9:$G$18) -> 4017.2099 | J20: =I20/I19-1 -> 0.067093827 | L20: =L19+1 -> 12 | M20: =M19+365 -> 46840 | N20: =FORECAST(L20,$N$9:$N$18,$L$9:$L$18) -> 106.49379 | O20: =N20/N19-1 -> 0.072213493
B21: =B20+1 -> 13 | C21: =C20+365 -> 47205 | D21: =_xlfn.FORECAST.ETS(B21,$D$9:$D$18,$B$9:$B$18) -> 22609.149 | E21: =D21/D20-1 -> 0.05382915 | G21: =G20+1 -> 13 | H21: =H20+365 -> 47205 | I21: =FORECAST(G21,$I$9:$I$18, $G$9:$G$18) -> 4269.7931 | J21: =I21/I20-1 -> 0.062875284 | L21: =L20+1 -> 13 | M21: =M20+365 -> 47205 | N21: =FORECAST(L21,$N$9:$N$18,$L$9:$L$18) -> 113.66614 | O21: =N21/N20-1 -> 0.06734992
B22: =B21+1 -> 14 | C22: =C21+365 -> 47570 | D22: =_xlfn.FORECAST.ETS(B22,$D$9:$D$18,$B$9:$B$18) -> 23764.015 | E22: =D22/D21-1 -> 0.05107958 | G22: =G21+1 -> 14 | H22: =H21+365 -> 47570 | I22: =FORECAST(G22,$I$9:$I$18, $G$9:$G$18) -> 4522.3763 | J22: =I22/I21-1 -> 0.059155844 | L22: =L21+1 -> 14 | M22: =M21+365 -> 47570 | N22: =FORECAST(L22,$N$9:$N$18,$L$9:$L$18) -> 120.83849 | O22: =N22/N21-1 -> 0.063100131
B23: =B22+1 -> 15 | C23: =C22+365 -> 47935 | D23: =_xlfn.FORECAST.ETS(B23,$D$9:$D$18,$B$9:$B$18) -> 24918.881 | E23: =D23/D22-1 -> 0.048597253 | G23: =G22+1 -> 15 | H23: =H22+365 -> 47935 | I23: =FORECAST(G23,$I$9:$I$18, $G$9:$G$18) -> 4774.9595 | J23: =I23/I22-1 -> 0.055851879 | L23: =L22+1 -> 15 | M23: =M22+365 -> 47935 | N23: =FORECAST(L23,$N$9:$N$18,$L$9:$L$18) -> 128.01084 | O23: =N23/N22-1 -> 0.059354834

Sheet Common Size Statement
B2: ='Data Sheet'!B1 -> BRITANNIA INDUSTRIES LTD
B3: (BRITANNIA) | BSE Code: 500825)
B4: INR 5,181.50 1st Sept 2026
B5: 52 Week (High - INR 6,336.95 & Low - 5,038)
J6: Prepared by Pushti Gandhi
B7: ="Common Size Income Statement"&" "&"-"&" "&'Data Sheet'!B1 -> Common Size Income Statement - BRITANNIA INDUSTRIES LTD
B9: Particulars | C9: ='Data Sheet'!B16 -> 42825 | D9: ='Data Sheet'!C16 -> 43190 | E9: ='Data Sheet'!D16 -> 43555 | F9: ='Data Sheet'!E16 -> 43921 | G9: ='Data Sheet'!F16 -> 44286 | H9: ='Data Sheet'!G16 -> 44651 | I9: ='Data Sheet'!H16 -> 45016 | J9: ='Data Sheet'!I16 -> 45382 | ... L9: ='Data Sheet'!K16 -> 46112
B11: ='Data Sheet'!A17 -> Sales | C11: ='Data Sheet'!B17/'Data Sheet'!B$17 -> 1 | D11: ='Data Sheet'!C17/'Data Sheet'!C$17 -> 1 | E11: ='Data Sheet'!D17/'Data Sheet'!D$17 -> 1 | F11: ='Data Sheet'!E17/'Data Sheet'!E$17 -> 1 | G11: ='Data Sheet'!F17/'Data Sheet'!F$17 -> 1 | H11: ='Data Sheet'!G17/'Data Sheet'!G$17 -> 1 | I11: ='Data Sheet'!H17/'Data Sheet'!H$17 -> 1 | J11: ='Data Sheet'!I17/'Data Sheet'!I$17 -> 1 | ... L11: ='Data Sheet'!K17/'Data Sheet'!K$17 -> 1
B12: ='Data Sheet'!A18 -> Raw Material Cost | C12: ='Data Sheet'!B18/'Data Sheet'!B$17 -> 0.62324099 | D12: ='Data Sheet'!C18/'Data Sheet'!C$17 -> 0.61537282 | E12: ='Data Sheet'!D18/'Data Sheet'!D$17 -> 0.59853799 | F12: ='Data Sheet'!E18/'Data Sheet'!E$17 -> 0.59268679 | G12: ='Data Sheet'!F18/'Data Sheet'!F$17 -> 0.58336924 | H12: ='Data Sheet'!G18/'Data Sheet'!G$17 -> 0.62502812 | I12: ='Data Sheet'!H18/'Data Sheet'!H$17 -> 0.592853 | J12: ='Data Sheet'!I18/'Data Sheet'!I$17 -> 0.56581891 | ... L12: ='Data Sheet'!K18/'Data Sheet'!K$17 -> 0.58247122
B13: ='Data Sheet'!A19 -> Change in Inventory | C13: ='Data Sheet'!B19/'Data Sheet'!B$17 -> 0.0059862449 | D13: ='Data Sheet'!C19/'Data Sheet'!C$17 -> -0.00063546564 | E13: ='Data Sheet'!D19/'Data Sheet'!D$17 -> 0.0049915556 | F13: ='Data Sheet'!E19/'Data Sheet'!E$17 -> -0.0045320724 | G13: ='Data Sheet'!F19/'Data Sheet'!F$17 -> 0.0028257921 | H13: ='Data Sheet'!G19/'Data Sheet'!G$17 -> 0.0053238976 | I13: ='Data Sheet'!H19/'Data Sheet'!H$17 -> 0.0044495431 | J13: ='Data Sheet'!I19/'Data Sheet'!I$17 -> -0.00021825637 | ... L13: ='Data Sheet'!K19/'Data Sheet'!K$17 -> 0.0011680492
B14: ='Data Sheet'!A20 -> Power and Fuel | C14: ='Data Sheet'!B20/'Data Sheet'!B$17 -> 0.011517447 | D14: ='Data Sheet'!C20/'Data Sheet'!C$17 -> 0.012994768 | E14: ='Data Sheet'!D20/'Data Sheet'!D$17 -> 0.015845792 | F14: ='Data Sheet'!E20/'Data Sheet'!E$17 -> 0.01531956 | G14: ='Data Sheet'!F20/'Data Sheet'!F$17 -> 0.013876984 | H14: ='Data Sheet'!G20/'Data Sheet'!G$17 -> 0.015398698 | I14: ='Data Sheet'!H20/'Data Sheet'!H$17 -> 0.016698823 | J14: ='Data Sheet'!I20/'Data Sheet'!I$17 -> 0.019514863 | ... L14: ='Data Sheet'!K20/'Data Sheet'!K$17 -> 0.017902952
B15: ='Data Sheet'!A21 -> Other Mfr. Exp | C15: ='Data Sheet'!B21/'Data Sheet'!B$17 -> 0.056320403 | D15: ='Data Sheet'!C21/'Data Sheet'!C$17 -> 0.049182015 | E15: ='Data Sheet'!D21/'Data Sheet'!D$17 -> 0.056204301 | F15: ='Data Sheet'!E21/'Data Sheet'!E$17 -> 0.05264687 | G15: ='Data Sheet'!F21/'Data Sheet'!F$17 -> 0.051172567 | H15: ='Data Sheet'!G21/'Data Sheet'!G$17 -> 0.053217046 | I15: ='Data Sheet'!H21/'Data Sheet'!H$17 -> 0.054829438 | J15: ='Data Sheet'!I21/'Data Sheet'!I$17 -> 0.052245566 | ... L15: ='Data Sheet'!K21/'Data Sheet'!K$17 -> 0.048073293
B16: ='Data Sheet'!A22 -> Employee Cost | C16: ='Data Sheet'!B22/'Data Sheet'!B$17 -> 0.03894483 | D16: ='Data Sheet'!C22/'Data Sheet'!C$17 -> 0.040508413 | E16: ='Data Sheet'!D22/'Data Sheet'!D$17 -> 0.039966819 | F16: ='Data Sheet'!E22/'Data Sheet'!E$17 -> 0.041957662 | G16: ='Data Sheet'!F22/'Data Sheet'!F$17 -> 0.040147258 | H16: ='Data Sheet'!G22/'Data Sheet'!G$17 -> 0.03835951 | I16: ='Data Sheet'!H22/'Data Sheet'!H$17 -> 0.040390048 | J16: ='Data Sheet'!I22/'Data Sheet'!I$17 -> 0.042261828 | ... L16: ='Data Sheet'!K22/'Data Sheet'!K$17 -> 0.043014705
B17: ='Data Sheet'!A23 -> Selling and admin | C17: ='Data Sheet'!B23/'Data Sheet'!B$17 -> 0.1010604 | D17: ='Data Sheet'!C23/'Data Sheet'!C$17 -> 0.096175203 | E17: ='Data Sheet'!D23/'Data Sheet'!D$17 -> 0.100183 | F17: ='Data Sheet'!E23/'Data Sheet'!E$17 -> 0.097006349 | G17: ='Data Sheet'!F23/'Data Sheet'!F$17 -> 0.088596802 | H17: ='Data Sheet'!G23/'Data Sheet'!G$17 -> 0.083991098 | I17: ='Data Sheet'!H23/'Data Sheet'!H$17 -> 0.090417808 | J17: ='Data Sheet'!I23/'Data Sheet'!I$17 -> 0.090971163 | ... L17: ='Data Sheet'!K23/'Data Sheet'!K$17 -> 0.082250612
B18: ='Data Sheet'!A24 -> Other Expenses | C18: ='Data Sheet'!B24/'Data Sheet'!B$17 -> 0.033730612 | D18: ='Data Sheet'!C24/'Data Sheet'!C$17 -> 0.033681696 | E18: ='Data Sheet'!D24/'Data Sheet'!D$17 -> 0.037537077 | F18: ='Data Sheet'!E24/'Data Sheet'!E$17 -> 0.036949709 | G18: ='Data Sheet'!F24/'Data Sheet'!F$17 -> 0.034641074 | H18: ='Data Sheet'!G24/'Data Sheet'!G$17 -> 0.033608607 | I18: ='Data Sheet'!H24/'Data Sheet'!H$17 -> 0.035590824 | J18: ='Data Sheet'!I24/'Data Sheet'!I$17 -> 0.040132934 | ... L18: ='Data Sheet'!K24/'Data Sheet'!K$17 -> 0.043954053
B19: ='Data Sheet'!A25 -> Other Income | C19: ='Data Sheet'!B25/'Data Sheet'!B$17 -> 0.01662674 | D19: ='Data Sheet'!C25/'Data Sheet'!C$17 -> 0.016781336 | E19: ='Data Sheet'!D25/'Data Sheet'!D$17 -> 0.018675365 | F19: ='Data Sheet'!E25/'Data Sheet'!E$17 -> 0.022658638 | G19: ='Data Sheet'!F25/'Data Sheet'!F$17 -> 0.023832724 | H19: ='Data Sheet'!G25/'Data Sheet'!G$17 -> 0.015693684 | I19: ='Data Sheet'!H25/'Data Sheet'!H$17 -> 0.036616556 | J19: ='Data Sheet'!I25/'Data Sheet'!I$17 -> 0.012599237 | ... L19: ='Data Sheet'!K25/'Data Sheet'!K$17 -> 0.011697723
B20: ='Data Sheet'!A26 -> Depreciation | C20: ='Data Sheet'!B26/'Data Sheet'!B$17 -> 0.013173052 | D20: ='Data Sheet'!C26/'Data Sheet'!C$17 -> 0.014330255 | E20: ='Data Sheet'!D26/'Data Sheet'!D$17 -> 0.014643585 | F20: ='Data Sheet'!E26/'Data Sheet'!E$17 -> 0.015932515 | G20: ='Data Sheet'!F26/'Data Sheet'!F$17 -> 0.015061502 | H20: ='Data Sheet'!G26/'Data Sheet'!G$17 -> 0.014186213 | I20: ='Data Sheet'!H26/'Data Sheet'!H$17 -> 0.013859042 | J20: ='Data Sheet'!I26/'Data Sheet'!I$17 -> 0.017917298 | ... L20: ='Data Sheet'!K26/'Data Sheet'!K$17 -> 0.017587574
B21: ='Data Sheet'!A27 -> Interest | C21: ='Data Sheet'!B27/'Data Sheet'!B$17 -> 0.00060193791 | D21: ='Data Sheet'!C27/'Data Sheet'!C$17 -> 0.00076558479 | E21: ='Data Sheet'!D27/'Data Sheet'!D$17 -> 0.00082227692 | F21: ='Data Sheet'!E27/'Data Sheet'!E$17 -> 0.0066295675 | G21: ='Data Sheet'!F27/'Data Sheet'!F$17 -> 0.0084423583 | H21: ='Data Sheet'!G27/'Data Sheet'!G$17 -> 0.010207084 | I21: ='Data Sheet'!H27/'Data Sheet'!H$17 -> 0.010373883 | J21: ='Data Sheet'!I27/'Data Sheet'!I$17 -> 0.0097797936 | ... L21: ='Data Sheet'!K27/'Data Sheet'!K$17 -> 0.0058877618
B22: ='Data Sheet'!A28 -> Profit before tax | C22: ='Data Sheet'!B28/'Data Sheet'!B17 -> 0.14402331 | D22: ='Data Sheet'!C28/'Data Sheet'!C17 -> 0.15313512 | E22: ='Data Sheet'!D28/'Data Sheet'!D17 -> 0.15992608 | F22: ='Data Sheet'!E28/'Data Sheet'!E17 -> 0.15899755 | G22: ='Data Sheet'!F28/'Data Sheet'!F17 -> 0.19135073 | H22: ='Data Sheet'!G28/'Data Sheet'!G17 -> 0.14702121 | I22: ='Data Sheet'!H28/'Data Sheet'!H17 -> 0.18605323 | J22: ='Data Sheet'!I28/'Data Sheet'!I17 -> 0.17373863 | ... L22: ='Data Sheet'!K28/'Data Sheet'!K17 -> 0.1717236
B23: ='Data Sheet'!A29 -> Tax | C23: ='Data Sheet'!B29/'Data Sheet'!B$17 -> 0.046351428 | D23: ='Data Sheet'!C29/'Data Sheet'!C$17 -> 0.051868118 | E23: ='Data Sheet'!D29/'Data Sheet'!D$17 -> 0.055403734 | F23: ='Data Sheet'!E29/'Data Sheet'!E$17 -> 0.038854956 | G23: ='Data Sheet'!F29/'Data Sheet'!F$17 -> 0.05047297 | H23: ='Data Sheet'!G29/'Data Sheet'!G$17 -> 0.039780677 | I23: ='Data Sheet'!H29/'Data Sheet'!H$17 -> 0.043952505 | J23: ='Data Sheet'!I29/'Data Sheet'!I$17 -> 0.046468928 | ... L23: ='Data Sheet'!K29/'Data Sheet'!K$17 -> 0.03925366
B24: ='Data Sheet'!A30 -> Net profit | C24: ='Data Sheet'!B30/'Data Sheet'!B$17 -> 0.097687344 | D24: ='Data Sheet'!C30/'Data Sheet'!C$17 -> 0.10129423 | E24: ='Data Sheet'!D30/'Data Sheet'!D$17 -> 0.10485342 | F24: ='Data Sheet'!E30/'Data Sheet'!E$17 -> 0.12092107 | G24: ='Data Sheet'!F30/'Data Sheet'!F$17 -> 0.141891 | H24: ='Data Sheet'!G30/'Data Sheet'!G$17 -> 0.10786587 | I24: ='Data Sheet'!H30/'Data Sheet'!H$17 -> 0.14243507 | J24: ='Data Sheet'!I30/'Data Sheet'!I$17 -> 0.12760305 | ... L24: ='Data Sheet'!K30/'Data Sheet'!K$17 -> 0.13228614
B25: ='Data Sheet'!A31 -> Dividend Amount | C25: ='Data Sheet'!B31/'Data Sheet'!B$17 -> 0.029158093 | D25: ='Data Sheet'!C31/'Data Sheet'!C$17 -> 0.030272373 | E25: ='Data Sheet'!D31/'Data Sheet'!D$17 -> 0.032606129 | F25: ='Data Sheet'!E31/'Data Sheet'!E$17 -> 0.07256747 | G25: ='Data Sheet'!F31/'Data Sheet'!F$17 -> 0.28883523 | H25: ='Data Sheet'!G31/'Data Sheet'!G$17 -> 0.096282892 | I25: ='Data Sheet'!H31/'Data Sheet'!H$17 -> 0.10640623 | J25: ='Data Sheet'!I31/'Data Sheet'!I$17 -> 0.10558718 | ... L25: ='Data Sheet'!K31/'Data Sheet'!K$17 -> 0.11383598
B26: EBITDA | C26: ='Historical FS'!C24/'Historical FS'!C$12 -> 0.14117156 | D26: ='Historical FS'!D24/'Historical FS'!D$12 -> 0.15144962 | E26: ='Historical FS'!E24/'Historical FS'!E$12 -> 0.15671657 | F26: ='Historical FS'!F24/'Historical FS'!F$12 -> 0.15890099 | G26: ='Historical FS'!G24/'Historical FS'!G$12 -> 0.19102187 | H26: ='Historical FS'!H24/'Historical FS'!H$12 -> 0.15572082 | I26: ='Historical FS'!I24/'Historical FS'!I$12 -> 0.1736696 | J26: ='Historical FS'!J24/'Historical FS'!J$12 -> 0.18883648 | ... L26: ='Historical FS'!L24/'Historical FS'!L$12 -> 0.18350121
B29: ="Common Size Balance Sheet"&" "&"-"&" "&'Data Sheet'!B1 -> Common Size Balance Sheet - BRITANNIA INDUSTRIES LTD
B31: Particulars | C31: ='Data Sheet'!B16 -> 42825 | D31: ='Data Sheet'!C16 -> 43190 | E31: ='Data Sheet'!D16 -> 43555 | F31: ='Data Sheet'!E16 -> 43921 | G31: ='Data Sheet'!F16 -> 44286 | H31: ='Data Sheet'!G16 -> 44651 | I31: ='Data Sheet'!H16 -> 45016 | J31: ='Data Sheet'!I16 -> 45382 | ... L31: ='Data Sheet'!K16 -> 46112
B33: Total Liabilities | C33: ='Data Sheet'!B61/'Data Sheet'!B61 -> 1 | D33: ='Data Sheet'!C61/'Data Sheet'!C61 -> 1 | E33: ='Data Sheet'!D61/'Data Sheet'!D61 -> 1 | F33: ='Data Sheet'!E61/'Data Sheet'!E61 -> 1 | G33: ='Data Sheet'!F61/'Data Sheet'!F61 -> 1 | H33: ='Data Sheet'!G61/'Data Sheet'!G61 -> 1 | I33: ='Data Sheet'!H61/'Data Sheet'!H61 -> 1 | J33: ='Data Sheet'!I61/'Data Sheet'!I61 -> 1 | ... L33: ='Data Sheet'!K61/'Data Sheet'!K61 -> 1
B34: Equity Share Capital | C34: ='Data Sheet'!B57/'Data Sheet'!B61 -> 0.0058411215 | D34: ='Data Sheet'!C57/'Data Sheet'!C61 -> 0.004628059 | E34: ='Data Sheet'!D57/'Data Sheet'!D61 -> 0.0038522271 | F34: ='Data Sheet'!E57/'Data Sheet'!E61 -> 0.0030717003 | G34: ='Data Sheet'!F57/'Data Sheet'!F61 -> 0.0030112161 | H34: ='Data Sheet'!G57/'Data Sheet'!G61 -> 0.0032006484 | I34: ='Data Sheet'!H57/'Data Sheet'!H61 -> 0.0025762364 | J34: ='Data Sheet'!I57/'Data Sheet'!I61 -> 0.0026555696 | ... L34: ='Data Sheet'!K57/'Data Sheet'!K61 -> 0.0024757665
B35: Reserves | C35: ='Data Sheet'!B58/'Data Sheet'!B61 -> 0.65041375 | D35: ='Data Sheet'!C58/'Data Sheet'!C61 -> 0.65194143 | E35: ='Data Sheet'!D58/'Data Sheet'!D61 -> 0.67798235 | F35: ='Data Sheet'!E58/'Data Sheet'!E61 -> 0.55926402 | G35: ='Data Sheet'!F58/'Data Sheet'!F61 -> 0.4404413 | H35: ='Data Sheet'!G58/'Data Sheet'!G61 -> 0.33667393 | I35: ='Data Sheet'!H58/'Data Sheet'!H61 -> 0.37538619 | J35: ='Data Sheet'!I58/'Data Sheet'!I61 -> 0.43183928 | ... L35: ='Data Sheet'!K58/'Data Sheet'!K61 -> 0.52233328
B36: Borrowings | C36: ='Data Sheet'!B59/'Data Sheet'!B61 -> 0.030315421 | D36: ='Data Sheet'!C59/'Data Sheet'!C61 -> 0.038686024 | E36: ='Data Sheet'!D59/'Data Sheet'!D61 -> 0.025011422 | F36: ='Data Sheet'!E59/'Data Sheet'!E61 -> 0.19638318 | G36: ='Data Sheet'!F59/'Data Sheet'!F61 -> 0.26336454 | H36: ='Data Sheet'!G59/'Data Sheet'!G61 -> 0.32965748 | I36: ='Data Sheet'!H59/'Data Sheet'!H61 -> 0.32054519 | J36: ='Data Sheet'!I59/'Data Sheet'!I61 -> 0.22763159 | ... L36: ='Data Sheet'!K59/'Data Sheet'!K61 -> 0.14185351
B37: Other Liabilities | C37: ='Data Sheet'!B60/'Data Sheet'!B61 -> 0.31342971 | D37: ='Data Sheet'!C60/'Data Sheet'!C61 -> 0.30474448 | E37: ='Data Sheet'!D60/'Data Sheet'!D61 -> 0.293154 | F37: ='Data Sheet'!E60/'Data Sheet'!E61 -> 0.2412811 | G37: ='Data Sheet'!F60/'Data Sheet'!F61 -> 0.29318295 | H37: ='Data Sheet'!G60/'Data Sheet'!G61 -> 0.33046794 | I37: ='Data Sheet'!H60/'Data Sheet'!H61 -> 0.30149238 | J37: ='Data Sheet'!I60/'Data Sheet'!I61 -> 0.33787356 | ... L37: ='Data Sheet'!K60/'Data Sheet'!K61 -> 0.33333744
B39: Total Assets | C39: ='Data Sheet'!B66/'Data Sheet'!B$66 -> 1 | D39: ='Data Sheet'!C66/'Data Sheet'!C$66 -> 1 | E39: ='Data Sheet'!D66/'Data Sheet'!D$66 -> 1 | F39: ='Data Sheet'!E66/'Data Sheet'!E$66 -> 1 | G39: ='Data Sheet'!F66/'Data Sheet'!F$66 -> 1 | H39: ='Data Sheet'!G66/'Data Sheet'!G$66 -> 1 | I39: ='Data Sheet'!H66/'Data Sheet'!H$66 -> 1 | J39: ='Data Sheet'!I66/'Data Sheet'!I$66 -> 1 | ... L39: ='Data Sheet'!K66/'Data Sheet'!K$66 -> 1
B40: Net Block | C40: ='Data Sheet'!B62/'Data Sheet'!B$66 -> 0.28231844 | D40: ='Data Sheet'!C62/'Data Sheet'!C$66 -> 0.25937177 | E40: ='Data Sheet'!D62/'Data Sheet'!D$66 -> 0.27064981 | F40: ='Data Sheet'!E62/'Data Sheet'!E$66 -> 0.23988382 | G40: ='Data Sheet'!F62/'Data Sheet'!F$66 -> 0.22411623 | H40: ='Data Sheet'!G62/'Data Sheet'!G$66 -> 0.23293519 | I40: ='Data Sheet'!H62/'Data Sheet'!H$66 -> 0.28395493 | J40: ='Data Sheet'!I62/'Data Sheet'!I$66 -> 0.30547759 | ... L40: ='Data Sheet'!K62/'Data Sheet'!K$66 -> 0.29289068
B41: Capital Work in Progress | C41: ='Data Sheet'!B63/'Data Sheet'!B$66 -> 0.0073184385 | D41: ='Data Sheet'!C63/'Data Sheet'!C$66 -> 0.039094666 | E41: ='Data Sheet'!D63/'Data Sheet'!D$66 -> 0.016229691 | F41: ='Data Sheet'!E63/'Data Sheet'!E$66 -> 0.0050513823 | G41: ='Data Sheet'!F63/'Data Sheet'!F$66 -> 0.014564836 | H41: ='Data Sheet'!G63/'Data Sheet'!G$66 -> 0.071171578 | I41: ='Data Sheet'!H63/'Data Sheet'!H$66 -> 0.011228926 | J41: ='Data Sheet'!I63/'Data Sheet'!I$66 -> 0.020673538 | ... L41: ='Data Sheet'!K63/'Data Sheet'!K$66 -> 0.004012201
B42: Investments | C42: ='Data Sheet'!B64/'Data Sheet'!B$66 -> 0.11848958 | D42: ='Data Sheet'!C64/'Data Sheet'!C$66 -> 0.20803713 | E42: ='Data Sheet'!D64/'Data Sheet'!D$66 -> 0.23666108 | F42: ='Data Sheet'!E64/'Data Sheet'!E$66 -> 0.36952746 | G42: ='Data Sheet'!F64/'Data Sheet'!F$66 -> 0.34758234 | H42: ='Data Sheet'!G64/'Data Sheet'!G$66 -> 0.23415221 | I42: ='Data Sheet'!H64/'Data Sheet'!H$66 -> 0.35550137 | J42: ='Data Sheet'!I64/'Data Sheet'!I$66 -> 0.30499035 | ... L42: ='Data Sheet'!K64/'Data Sheet'!K$66 -> 0.3709806
B43: Other Assets | C43: ='Data Sheet'!B65/'Data Sheet'!B66 -> 0.59187354 | D43: ='Data Sheet'!C65/'Data Sheet'!C66 -> 0.49349643 | E43: ='Data Sheet'!D65/'Data Sheet'!D66 -> 0.47645941 | F43: ='Data Sheet'!E65/'Data Sheet'!E66 -> 0.38553734 | G43: ='Data Sheet'!F65/'Data Sheet'!F66 -> 0.4137366 | H43: ='Data Sheet'!G65/'Data Sheet'!G66 -> 0.46174103 | I43: ='Data Sheet'!H65/'Data Sheet'!H66 -> 0.34931477 | J43: ='Data Sheet'!I65/'Data Sheet'!I66 -> 0.36885851 | ... L43: ='Data Sheet'!K65/'Data Sheet'!K66 -> 0.33211652
B44: Receivables | C44: ='Data Sheet'!B67/'Data Sheet'!B$66 -> 0.043603972 | D44: ='Data Sheet'!C67/'Data Sheet'!C$66 -> 0.058713319 | E44: ='Data Sheet'!D67/'Data Sheet'!D$66 -> 0.06320025 | F44: ='Data Sheet'!E67/'Data Sheet'!E$66 -> 0.040916835 | G44: ='Data Sheet'!F67/'Data Sheet'!F$66 -> 0.032158388 | H44: ='Data Sheet'!G67/'Data Sheet'!G$66 -> 0.044100922 | I44: ='Data Sheet'!H67/'Data Sheet'!H$66 -> 0.035177551 | J44: ='Data Sheet'!I67/'Data Sheet'!I$66 -> 0.043358871 | ... L44: ='Data Sheet'!K67/'Data Sheet'!K$66 -> 0.048221436
B45: Inventory | C45: ='Data Sheet'!B68/'Data Sheet'!B$66 -> 0.16098374 | D45: ='Data Sheet'!C68/'Data Sheet'!C$66 -> 0.12582885 | E45: ='Data Sheet'!D68/'Data Sheet'!D$66 -> 0.12526231 | F45: ='Data Sheet'!E68/'Data Sheet'!E$66 -> 0.094636467 | G45: ='Data Sheet'!F68/'Data Sheet'!F$66 -> 0.13643472 | H45: ='Data Sheet'!G68/'Data Sheet'!G$66 -> 0.18168761 | I45: ='Data Sheet'!H68/'Data Sheet'!H$66 -> 0.12760979 | J45: ='Data Sheet'!I68/'Data Sheet'!I$66 -> 0.1302122 | ... L45: ='Data Sheet'!K68/'Data Sheet'!K$66 -> 0.1383233
B46: Cash & Bank | C46: ='Data Sheet'!B69/'Data Sheet'!B$66 -> 0.029390576 | D46: ='Data Sheet'!C69/'Data Sheet'!C$66 -> 0.035933476 | E46: ='Data Sheet'!D69/'Data Sheet'!D$66 -> 0.017605143 | F46: ='Data Sheet'!E69/'Data Sheet'!E$66 -> 0.015690577 | G46: ='Data Sheet'!F69/'Data Sheet'!F$66 -> 0.026417203 | H46: ='Data Sheet'!G69/'Data Sheet'!G$66 -> 0.024566205 | I46: ='Data Sheet'!H69/'Data Sheet'!H$66 -> 0.021172407 | J46: ='Data Sheet'!I69/'Data Sheet'!I$66 -> 0.04920355 | ... L46: ='Data Sheet'!K69/'Data Sheet'!K$66 -> 0.036220803

Sheet WACC Modelling
B2: ='Data Sheet'!B1 -> BRITANNIA INDUSTRIES LTD
B3: (BRITANNIA) | BSE Code: 500825)
B4: INR 5,181.50 1st Sept 2026
B5: 52 Week (High - INR 6,336.95 & Low - 5,038)
I6: Prepared by Pushti Gandhi
B7: Weighted Average Cost of Capital
B9: All figures are in INR unless stated otherwise
B11: Peer Comps
H12: Debt / | I12: Debt / | J12: Levered | K12: Unlevered
B13: Name of the Comp | D13: Country | E13: Total Debt | F13: Total Equity | G13: Tax Rate 1 | H13: Equity | I13: Capital | J13: Beta 2 | K13: Beta 3
B15: Hindustan Unilever | D15: India | E15: ='Beta Comps'!E6 -> 1478 | F15: ='Beta Comps'!I6 -> 453887.93 | G15: 0.2517 | H15: =E15/F15 -> 0.0032563104 | I15: =E15/(E15+F15) -> 0.0032457413 | J15: 0.489 | K15: =J15/(1+(1-G15)*H15) -> 0.48781135
B16: ITC | D16: India | E16: ='Beta Comps'!E7 -> 2399.06 | F16: ='Beta Comps'!I7 -> 325963.52 | G16: 0.2517 | H16: =E16/F16 -> 0.0073599033 | I16: =E16/(E16+F16) -> 0.0073061309 | J16: 0.497 | K16: =J16/(1+(1-G16)*H16) -> 0.49427781
B17: Nestle India | D17: India | E17: ='Beta Comps'!E8 -> 444.16 | F17: ='Beta Comps'!I8 -> 264871.16 | G17: 0.2517 | H17: =E17/F17 -> 0.0016768908 | I17: =E17/(E17+F17) -> 0.0016740835 | J17: 0.807 | K17: =J17/(1+(1-G17)*H17) -> 0.80598863
B18: Varun Beverages | D18: India | E18: ='Beta Comps'!E9 -> 2508.18 | F18: ='Beta Comps'!I9 -> 140605.64 | G18: 0.2517 | H18: =E18/F18 -> 0.017838402 | I18: =E18/(E18+F18) -> 0.017525771 | J18: 0.958 | K18: =J18/(1+(1-G18)*H18) -> 0.94538061
B19: Britannia Inds. | D19: India | E19: ='Beta Comps'!E10 -> 1380.28 | F19: ='Beta Comps'!I10 -> 119471.15 | G19: 0.2517 | H19: =E19/F19 -> 0.011553249 | I19: =E19/(E19+F19) -> 0.011421296 | J19: =Beta!O13 -> 0.51749256 | K19: =J19/(1+(1-G19)*H19) -> 0.51305703
F21: Average | G21: =AVERAGE(G15:G19) -> 0.2517 | H21: =AVERAGE(H15:H19) -> 0.0083369513 | I21: =AVERAGE(I15:I19) -> 0.0082346046 | J21: =AVERAGE(J15:J19) -> 0.65369851 | K21: =AVERAGE(K15:K19) -> 0.64930309
F22: Median | G22: =MEDIAN(G15:G19) -> 0.2517 | H22: =MEDIAN(H15:H19) -> 0.0073599033 | I22: =MEDIAN(I15:I19) -> 0.0073061309 | J22: =MEDIAN(J15:J19) -> 0.51749256 | K22: =MEDIAN(K15:K19) -> 0.51305703
B25: Cost of Debt | G25: Cost of Equity
B27: Pre-Tax Cost of Debt | E27: ='Historical FS'!L27/'WACC Modelling'!E19 -> 0.081693569 | G27: Risk Free Rate | K27: 0.07021
B28: Tax Rate | E28: =G21 -> 0.2517 | G28: Equity Risk Premium | K28: ='Market Return (Rm)'!F7-'WACC Modelling'!K27 -> 0.081282308
B29: Post Tax Cost of Debt | E29: =E27*(1-E28) -> 0.061131298 | G29: Levered Beta 4 | K29: =K38 -> 0.51624471
G30: Cost of Equity | K30: =K27+(K28*K29) -> 0.11217156
B33: Capital Structure | G33: Levered Beta
D35: Current | E35: Target | G35: Comps Median Unlevered Beta | K35: =K22 -> 0.51305703
B36: Total Debt | C36: =E19 -> 1380.28 | D36: =C36/$C$38 -> 0.011421296 | E36: =I21 -> 0.0082346046 | G36: Target Debt / Equity | K36: =E40 -> 0.0083029763
B37: Market Capitalization | C37: =F19 -> 119471.15 | D37: =C37/$C$38 -> 0.9885787 | E37: =E38-E36 -> 0.9917654 | G37: Tax Rate | K37: =E28 -> 0.2517
B38: Total Capital | C38: =SUM(C36:C37) -> 120851.43 | D38: =SUM(D36:D37) -> 1 | E38: =D38 -> 1 | G38: Levered Beta | K38: =K35*(1+(1-K37)*K36) -> 0.51624471
B40: Debt / Equity | D40: =D36/D37 -> 0.011553249 | E40: =E36/E37 -> 0.0083029763 | G40: Weighted Average Cost of Capital
B42: Notes: | G42: Cost of Equity | K42: =K30 -> 0.11217156
B43: 1. Tax Rate considered as Marginal Tax Rate for the country | G43: Equity Weight | K43: =E37 -> 0.9917654
B44: 2. Levered Beta is based on 5 year monthly data
B45: 3. Unlevered Beta = Levered Beta / (1+(1-Tax Rate)*Debt/Equity) | G45: Cost of Debt | K45: =E29 -> 0.061131298
B46: 4. Levered Beta = Unlevered Beta * (1+(1-Tax Rate)*Debt/Equity) | G46: Debt Weight | K46: =E36 -> 0.0082346046
G48: WACC | K48: =(K42*K43)+(K45*K46) -> 0.11175127

Sheet Beta
B2: ='Data Sheet'!B1 -> BRITANNIA INDUSTRIES LTD
B3: (BRITANNIA) | BSE Code: 500825)
B4: INR 5,181.50 1st Sept 2026
B5: 52 Week (High - INR 6,336.95 & Low - 5,038)
J7: Prepared by Pushti Gandhi
B8: Regression Beta - 2 Years Weekly
B10: Britannia Inds. Weekly Returns | F10: NIFTY Weekly Returns | J10: Beta Drifting | N10: Beta 1 | O10: =SLOPE(D14:D118, H14:H118) -> 0.51749256
N11: Beta 2 | O11: =_xlfn.COVARIANCE.S(D13:D118,H13:H118)/_xlfn.VAR.S(H13:H118) -> 0.51749256
B12: Date | C12: Closing Price | D12: Return | F12: Date | G12: Closing Price | H12: Return
B13: 45544 | C13: 5954.6 | F13: 45544 | G13: 25356.5 | J13: Levered Raw Beta | L13: =O13 -> 0.51749256 | N13: Beta 3 | O13: =O35 -> 0.51749256
B14: 45551 | C14: 6029.79 | D14: =C14/C13-1 -> 0.012627213 | F14: 45551 | G14: 25790.95 | H14: =G14/G13-1 -> 0.017133674 | J14: Raw Beta Weight | L14: 0.75
B15: 45558 | C15: 6086.35 | D15: =C15/C14-1 -> 0.0093800945 | F15: 45558 | G15: 26178.95 | H15: =G15/G14-1 -> 0.015044037
B16: 45565 | C16: 6025.37 | D16: =C16/C15-1 -> -0.010019141 | F16: 45565 | G16: 25014.6 | H16: =G16/G15-1 -> -0.044476574 | J16: Market Beta | L16: 1
B17: 45572 | C17: 5804.49 | D17: =C17/C16-1 -> -0.03665833 | F17: 45572 | G17: 24964.25 | H17: =G17/G16-1 -> -0.0020128245 | J17: Market Beta Weight | L17: 0.25
B18: 45579 | C18: 5715.85 | D18: =C18/C17-1 -> -0.015270937 | F18: 45579 | G18: 24854.05 | H18: =G18/G17-1 -> -0.0044143125 | N18: SUMMARY OUTPUT
B19: 45586 | C19: 5504.39 | D19: =C19/C18-1 -> -0.036995373 | F19: 45586 | G19: 24180.8 | H19: =G19/G18-1 -> -0.027088141 | J19: Adjusted Beta | L19: =(L13*L14)+(L16*L17) -> 0.63811942
B20: 45593 | C20: 5527.35 | D20: =C20/C19-1 -> 0.0041712161 | F20: 45593 | G20: 24304.35 | H20: =G20/G19-1 -> 0.0051094257 | N20: Regression Statistics
B21: 45600 | C21: 5579.88 | D21: =C21/C20-1 -> 0.00950365 | F21: 45600 | G21: 24148.2 | H21: =G21/G20-1 -> -0.0064247758 | N21: Multiple R | O21: 0.32880923
B22: 45607 | C22: 4772.53 | D22: =C22/C21-1 -> -0.14468949 | F22: 45607 | G22: 23532.7 | H22: =G22/G21-1 -> -0.025488442 | N22: R Square | O22: 0.10811551
B23: 45614 | C23: 4707.24 | D23: =C23/C22-1 -> -0.013680375 | F23: 45614 | G23: 23907.25 | H23: =G23/G22-1 -> 0.015916151 | N23: Adjusted R Square | O23: 0.099456437
B24: 45621 | C24: 4797.34 | D24: =C24/C23-1 -> 0.019140728 | F24: 45621 | G24: 24131.1 | H24: =G24/G23-1 -> 0.0093632685 | N24: Standard Error | O24: 0.027361418
B25: 45628 | C25: 4729.08 | D25: =C25/C24-1 -> -0.014228718 | F25: 45628 | G25: 24677.8 | H25: =G25/G24-1 -> 0.022655411 | N25: Observations | O25: 105
B26: 45635 | C26: 4708.94 | D26: =C26/C25-1 -> -0.0042587565 | F26: 45635 | G26: 24768.3 | H26: =G26/G25-1 -> 0.0036672637
B27: 45642 | C27: 4561.36 | D27: =C27/C26-1 -> -0.031340387 | F27: 45642 | G27: 23587.5 | H27: =G27/G26-1 -> -0.047673841 | N27: ANOVA
B28: 45649 | C28: 4630.49 | D28: =C28/C27-1 -> 0.015155568 | F28: 45649 | G28: 23813.4 | H28: =G28/G27-1 -> 0.0095771065 | O28: df | P28: SS | Q28: MS | R28: F | S28: Significance F
B29: 45656 | C29: 4693.4 | D29: =C29/C28-1 -> 0.013586035 | F29: 45656 | G29: 24004.75 | H29: =G29/G28-1 -> 0.0080353918 | N29: Regression | O29: 1 | P29: 0.009347464 | Q29: 0.009347464 | R29: 12.485807 | S29: 0.00061546992
B30: 45663 | C30: 4795.44 | D30: =C30/C29-1 -> 0.021741168 | F30: 45663 | G30: 23431.5 | H30: =G30/G29-1 -> -0.02388069 | N30: Residual | O30: 103 | P30: 0.077110659 | Q30: 0.00074864717
B31: 45670 | C31: 4713.11 | D31: =C31/C30-1 -> -0.017168393 | F31: 45670 | G31: 23203.2 | H31: =G31/G30-1 -> -0.0097432943 | N31: Total | O31: 104 | P31: 0.086458123
B32: 45677 | C32: 4953.07 | D32: =C32/C31-1 -> 0.050913304 | F32: 45677 | G32: 23092.2 | H32: =G32/G31-1 -> -0.0047838229
B33: 45684 | C33: 5049.96 | D33: =C33/C32-1 -> 0.019561605 | F33: 45684 | G33: 23482.15 | H33: =G33/G32-1 -> 0.016886654 | O33: Coefficients | P33: Standard Error | Q33: t Stat | R33: P-value | S33: Lower 95% | T33: Upper 95% | U33: Lower 95.0% | V33: Upper 95.0%
B34: 45691 | C34: 4728.74 | D34: =C34/C33-1 -> -0.063608425 | F34: 45691 | G34: 23559.95 | H34: =G34/G33-1 -> 0.0033131549 | N34: Intercept | O34: -0.00085923717 | P34: 0.0026712173 | Q34: -0.32166502 | R34: 0.74835835 | S34: -0.0061569667 | T34: 0.0044384923 | U34: -0.0061569667 | V34: 0.0044384923
B35: 45698 | C35: 4795.88 | D35: =C35/C34-1 -> 0.014198285 | F35: 45698 | G35: 22929.25 | H35: =G35/G34-1 -> -0.026770006 | N35: X Variable 1 | O35: 0.51749256 | P35: 0.14645217 | Q35: 3.5335261 | R35: 0.00061546992 | S35: 0.22703923 | T35: 0.80794589 | U35: 0.22703923 | V35: 0.80794589
B36: 45705 | C36: 4691.27 | D36: =C36/C35-1 -> -0.021812472 | F36: 45705 | G36: 22795.9 | H36: =G36/G35-1 -> -0.0058157157
B37: 45712 | C37: 4461.7 | D37: =C37/C36-1 -> -0.048935576 | F37: 45712 | G37: 22124.7 | H37: =G37/G36-1 -> -0.029443891
B38: 45719 | C38: 4610.05 | D38: =C38/C37-1 -> 0.033249658 | F38: 45719 | G38: 22552.5 | H38: =G38/G37-1 -> 0.019335855
B39: 45726 | C39: 4590.63 | D39: =C39/C38-1 -> -0.0042125357 | F39: 45726 | G39: 22397.2 | H39: =G39/G38-1 -> -0.0068861545
B40: 45733 | C40: 4673.89 | D40: =C40/C39-1 -> 0.018136944 | F40: 45733 | G40: 23350.4 | H40: =G40/G39-1 -> 0.042558891
B41: 45740 | C41: 4793.21 | D41: =C41/C40-1 -> 0.025529056 | F41: 45740 | G41: 23519.35 | H41: =G41/G40-1 -> 0.0072354221
B42: 45747 | C42: 4877.19 | D42: =C42/C41-1 -> 0.017520618 | F42: 45747 | G42: 22904.45 | H42: =G42/G41-1 -> -0.02614443
B43: 45754 | C43: 5194.48 | D43: =C43/C42-1 -> 0.065055903 | F43: 45754 | G43: 22828.55 | H43: =G43/G42-1 -> -0.0033137665
B44: 45761 | C44: 5295.84 | D44: =C44/C43-1 -> 0.019513022 | F44: 45761 | G44: 23851.65 | H44: =G44/G43-1 -> 0.044816688
B45: 45768 | C45: 5262.74 | D45: =C45/C44-1 -> -0.0062501888 | F45: 45768 | G45: 24039.35 | H45: =G45/G44-1 -> 0.0078694765
B46: 45775 | C46: 5146.71 | D46: =C46/C45-1 -> -0.022047451 | F46: 45775 | G46: 24346.7 | H46: =G46/G45-1 -> 0.012785287
B47: 45782 | C47: 5277.78 | D47: =C47/C46-1 -> 0.025466754 | F47: 45782 | G47: 24008 | H47: =G47/G46-1 -> -0.013911536
... B118: 46273 | C118: 5064 | D118: =C118/C117-1 -> 0 | F118: 46273 | G118: 23635.1 | H118: =G118/G117-1 -> 0

Sheet Market Return (Rm)
B2: Return on Market
B4: Year | C4: Annual
B5: 2000 | C5: -0.1465 | E5: Average Return | F5: =AVERAGE(C5:C30) -> 0.15149231
B6: 2001 | C6: -0.1618 | E6: Dividend Yield | F6: 1.3% 1
B7: 2002 | C7: 0.0325 | E7: Total Market Return | F7: =SUM(F5:F6) -> 0.15149231
B8: 2003 | C8: 0.719
B9: 2004 | C9: 0.1068
B10: 2005 | C10: 0.3634
B11: 2006 | C11: 0.3983
B12: 2007 | C12: 0.5477
B13: 2008 | C13: -0.5179
B14: 2009 | C14: 0.7576
B15: 2010 | C15: 0.1795
B16: 2011 | C16: -0.2462
B17: 2012 | C17: 0.277
B18: 2013 | C18: 0.0676
B19: 2014 | C19: 0.3139
... B30: 2025 | C30: 0.1051

Sheet Intrinsic Growth
B2: ='Data Sheet'!B1 -> BRITANNIA INDUSTRIES LTD
B3: (BRITANNIA) | BSE Code: 500825)
B4: INR 5,181.50 1st Sept 2026
B5: 52 Week (High - INR 6,336.95 & Low - 5,038)
H7: Prepared by Pushti Gandhi
A8: # | B8: Calculation of ROIC | F8: ='Cash Flow Data'!I111 -> 44621 | G8: ='Cash Flow Data'!J111 -> 44986 | H8: ='Cash Flow Data'!K111 -> 45352 | I8: ='Cash Flow Data'!L111 -> 45717 | J8: ='Cash Flow Data'!M111 -> 46082
B10: Current Assets
B11: ='Cash Flow Data'!A144 -> Inventories | F11: ='Cash Flow Data'!I144 -> 1367 | G11: ='Cash Flow Data'!J144 -> 1193 | H11: ='Cash Flow Data'!K144 -> 1181 | I11: ='Cash Flow Data'!L144 -> 1237 | J11: ='Cash Flow Data'!M144 -> 1346
B12: ='Cash Flow Data'!A145 -> Trade receivables | F12: ='Cash Flow Data'!I145 -> 332 | G12: ='Cash Flow Data'!J145 -> 329 | H12: ='Cash Flow Data'!K145 -> 393 | I12: ='Cash Flow Data'!L145 -> 449 | J12: ='Cash Flow Data'!M145 -> 469
B13: ='Cash Flow Data'!A147 -> Loans n Advances | F13: ='Cash Flow Data'!I147 -> 63 | G13: ='Cash Flow Data'!J147 -> 83 | H13: ='Cash Flow Data'!K147 -> 62 | I13: ='Cash Flow Data'!L147 -> 67 | J13: ='Cash Flow Data'!M147 -> 55
B14: ='Cash Flow Data'!A148 -> Other asset items | F14: ='Cash Flow Data'!I148 -> 1528 | G14: ='Cash Flow Data'!J148 -> 1463 | H14: ='Cash Flow Data'!K148 -> 1263 | I14: ='Cash Flow Data'!L148 -> 914 | J14: ='Cash Flow Data'!M148 -> 1009
B15: Total Current Assets | F15: =SUM(F11:F14) -> 3290 | G15: =SUM(G11:G14) -> 3068 | H15: =SUM(H11:H14) -> 2899 | I15: =SUM(I11:I14) -> 2667 | J15: =SUM(J11:J14) -> 2879
B17: Current Liabilities
B18: ='Cash Flow Data'!A122 -> Trade Payables | F18: ='Cash Flow Data'!I122 -> 1323 | G18: ='Cash Flow Data'!J122 -> 1449 | H18: ='Cash Flow Data'!K122 -> 1627 | I18: ='Cash Flow Data'!L122 -> 1752 | J18: ='Cash Flow Data'!M122 -> 1896
B19: ='Cash Flow Data'!A123 -> Advance from Customers | F19: ='Cash Flow Data'!I123 -> 34 | G19: ='Cash Flow Data'!J123 -> 55 | H19: ='Cash Flow Data'!K123 -> 42 | I19: ='Cash Flow Data'!L123 -> 46 | J19: ='Cash Flow Data'!M123 -> 53
B20: ='Cash Flow Data'!A124 -> Other liability items | F20: ='Cash Flow Data'!I124 -> 1103 | G20: ='Cash Flow Data'!J124 -> 1285 | H20: ='Cash Flow Data'!K124 -> 1371 | I20: ='Cash Flow Data'!L124 -> 1410 | J20: ='Cash Flow Data'!M124 -> 1265
B21: Total Current Liabilities | F21: =SUM(F18:F20) -> 2460 | G21: =SUM(G18:G20) -> 2789 | H21: =SUM(H18:H20) -> 3040 | I21: =SUM(I18:I20) -> 3208 | J21: =SUM(J18:J20) -> 3214
A23: # | B23: Net Working Capital | F23: =F15-F21 -> 830 | G23: =G15-G21 -> 279 | H23: =H15-H21 -> -141 | I23: =I15-I21 -> -541 | J23: =J15-J21 -> -335
B25: Non Current Assets
B26: ='Cash Flow Data'!A128 -> Land | F26: ='Cash Flow Data'!I128 -> 334 | G26: ='Cash Flow Data'!J128 -> 376 | H26: ='Cash Flow Data'!K128 -> 384 | I26: ='Cash Flow Data'!L128 -> 395 | J26: ='Cash Flow Data'!M128 -> 397
B27: ='Cash Flow Data'!A129 -> Building | F27: ='Cash Flow Data'!I129 -> 782 | G27: ='Cash Flow Data'!J129 -> 1143 | H27: ='Cash Flow Data'!K129 -> 1298 | I27: ='Cash Flow Data'!L129 -> 1395 | J27: ='Cash Flow Data'!M129 -> 1429
B28: ='Cash Flow Data'!A130 -> Plant Machinery | F28: ='Cash Flow Data'!I130 -> 1546 | G28: ='Cash Flow Data'!J130 -> 2303 | H28: ='Cash Flow Data'!K130 -> 2543 | I28: ='Cash Flow Data'!L130 -> 2844 | J28: ='Cash Flow Data'!M130 -> 3028
B29: ='Cash Flow Data'!A131 -> Equipments | F29: ='Cash Flow Data'!I131 -> 52 | G29: ='Cash Flow Data'!J131 -> 61 | H29: ='Cash Flow Data'!K131 -> 75 | I29: ='Cash Flow Data'!L131 -> 81 | J29: ='Cash Flow Data'!M131 -> 79
B30: ='Cash Flow Data'!A132 -> Furniture n fittings | F30: ='Cash Flow Data'!I132 -> 32 | G30: ='Cash Flow Data'!J132 -> 43 | H30: ='Cash Flow Data'!K132 -> 46 | I30: ='Cash Flow Data'!L132 -> 49 | J30: ='Cash Flow Data'!M132 -> 50
B31: ='Cash Flow Data'!A133 -> Vehicles | F31: ='Cash Flow Data'!I133 -> 6 | G31: ='Cash Flow Data'!J133 -> 10 | H31: ='Cash Flow Data'!K133 -> 10 | I31: ='Cash Flow Data'!L133 -> 9 | J31: ='Cash Flow Data'!M133 -> 9
B32: ='Cash Flow Data'!A134 -> Intangible Assets | F32: ='Cash Flow Data'!I134 -> 140 | G32: ='Cash Flow Data'!J134 -> 130 | H32: ='Cash Flow Data'!K134 -> 131 | I32: ='Cash Flow Data'!L134 -> 134 | J32: ='Cash Flow Data'!M134 -> 146
B33: ='Cash Flow Data'!A135 -> Other fixed assets | F33: ='Cash Flow Data'!I135 -> 57 | G33: ='Cash Flow Data'!J135 -> 86 | H33: ='Cash Flow Data'!K135 -> 72 | I33: ='Cash Flow Data'!L135 -> 67 | J33: ='Cash Flow Data'!M135 -> 67
B34: ='Cash Flow Data'!A136 -> Gross Block | F34: =SUM(F26:F33) -> 2949 | G34: =SUM(G26:G33) -> 4152 | H34: =SUM(H26:H33) -> 4559 | I34: =SUM(I26:I33) -> 4974 | J34: =SUM(J26:J33) -> 5205
B35: ='Cash Flow Data'!A137 -> Accumulated Depreciation | F35: =-'Cash Flow Data'!I137 -> -1195 | G35: =-'Cash Flow Data'!J137 -> -1495 | H35: =-'Cash Flow Data'!K137 -> -1788 | I35: =-'Cash Flow Data'!L137 -> -2070 | J35: =-'Cash Flow Data'!M137 -> -2356
A36: # | B36: Net Non Current Assets | F36: =SUM(F34:F35) -> 1754 | G36: =SUM(G34:G35) -> 2657 | H36: =SUM(H34:H35) -> 2771 | I36: =SUM(I34:I35) -> 2904 | J36: =SUM(J34:J35) -> 2849
A38: # | B38: Invested Capital | F38: =F36+F23 -> 2584 | G38: =G36+G23 -> 2936 | H38: =H36+H23 -> 2630 | I38: =I36+I23 -> 2363 | J38: =J36+J23 -> 2514
B39: EBIT | F39: ='Historical FS'!H33 -> 2000.77 | G39: ='Historical FS'!I33 -> 2605 | H39: ='Historical FS'!J33 -> 2866.19 | I39: ='Historical FS'!K33 -> 2863.07 | J39: ='Historical FS'!L33 -> 3177.51
A41: # | B41: ROIC | F41: =F39/F38 -> 0.7742918 | G41: =G39/G38 -> 0.88726158 | H41: =H39/H38 -> 1.0898061 | I41: =I39/I38 -> 1.2116251 | J41: =J39/J38 -> 1.263926
B44: Calculation of Reinvestment Rate | F44: =F8 -> 44621 | G44: =G8 -> 44986 | H44: =H8 -> 45352 | I44: =I8 -> 45717 | J44: =J8 -> 46082
B46: Net Capex | F46: =-SUM('Cash Flow Data'!I78:I79) -> 547 | G46: =-SUM('Cash Flow Data'!J78:J79) -> 633 | H46: =-SUM('Cash Flow Data'!K78:K79) -> 488 | I46: =-SUM('Cash Flow Data'!L78:L79) -> 370 | J46: =-SUM('Cash Flow Data'!M78:M79) -> 204
B47: Change in Working Capital | G47: =G23-F23 -> -551 | H47: =H23-G23 -> -420 | I47: =I23-H23 -> -400 | J47: =J23-I23 -> 206
B49: EBIT | F49: =F39 -> 2000.77 | G49: =G39 -> 2605 | H49: =H39 -> 2866.19 | I49: =I39 -> 2863.07 | J49: =J39 -> 3177.51
B50: Marginal Tax Rate | F50: 0.2517 | G50: 0.2517 | H50: 0.2517 | I50: 0.2517 | J50: 0.2517
B51: EBIT (1-T) | F51: =F49*(1-F50) -> 1497.1762 | G51: =G49*(1-G50) -> 1949.3215 | H51: =H49*(1-H50) -> 2144.77 | I51: =I49*(1-I50) -> 2142.4353 | J51: =J49*(1-J50) -> 2377.7307
B53: Reinvestment Amount | G53: =SUM(G46:G47) -> 82 | H53: =SUM(H46:H47) -> 68 | I53: =SUM(I46:I47) -> -30 | J53: =SUM(J46:J47) -> 410
B55: Reinvestment Rate | G55: =G53/G51 -> 0.042065919 | H55: =H53/H51 -> 0.031705032 | I55: =I53/I51 -> -0.014002757 | J55: =J53/J51 -> 0.17243332
I57: 4 Year Average | J57: =AVERAGE(G55:J55) -> 0.058050378
I58: 4 Year Median | J58: =MEDIAN(G55:J55) -> 0.036885475
A62: # | B62: Calculation of Growth Rate | F62: =F44 -> 44621 | G62: =G44 -> 44986 | H62: =H44 -> 45352 | I62: =I44 -> 45717 | J62: =J44 -> 46082
B64: Reinvestment Rate | G64: =G55 -> 0.042065919 | H64: =H55 -> 0.031705032 | I64: =I55 -> -0.014002757 | J64: =J55 -> 0.17243332
B65: ROIC | F65: =F41 -> 0.7742918 | G65: =G41 -> 0.88726158 | H65: =H41 -> 1.0898061 | I65: =I41 -> 1.2116251 | J65: =J41 -> 1.263926
B67: Intrinsic Growth | G67: =G64*G65 -> 0.037323474 | H67: =H64*H65 -> 0.034552336 | I67: =I64*I65 -> -0.016966091 | J67: =J64*J65 -> 0.21794296
I69: 4 Year Average | J69: =AVERAGE(G67:J67) -> 0.068213169
I70: 4 Year Median | J70: =MEDIAN(G67:J67) -> 0.035937905

Sheet DCF Model
B2: ='Data Sheet'!B1 -> BRITANNIA INDUSTRIES LTD
B3: (BRITANNIA) | BSE Code: 500825)
B4: INR 5,181.50 1st Sept 2026
B5: 52 Week (High - INR 6,336.95 & Low - 5,038)
I7: Prepared by Pushti Gandhi
B8: Present Value of FCFF | F8: ='Data Sheet'!K16 -> 46112 | G8: =F8+365 -> 46477 | H8: =G8+365 -> 46842 | I8: =H8+365 -> 47207 | J8: =I8+365 -> 47572 | K8: =J8+365 -> 47937
B10: EBIT | F10: ='Historical FS'!L33 -> 3177.51 | G10: =F10*(1+$F$26) -> 3291.5826 | H10: =G10*(1+$F$26) -> 3409.7504 | I10: =H10*(1+$F$26) -> 3532.1605 | J10: =I10*(1+$F$26) -> 3658.965 | K10: =J10*(1+$F$26) -> 3790.3219
B12: Tax Rate | F12: 0.2517 | G12: =F12 -> 0.2517 | H12: =G12 -> 0.2517 | I12: =H12 -> 0.2517 | J12: =I12 -> 0.2517 | K12: =J12 -> 0.2517
B14: EBIT (1-T) | F14: =F10*(1-F12) -> 2377.7307 | G14: =G10*(1-G12) -> 2463.0913 | H14: =H10*(1-H12) -> 2551.5162 | I14: =I10*(1-I12) -> 2643.1157 | J14: =J10*(1-J12) -> 2738.0035 | K14: =K10*(1-K12) -> 2836.2979
B16: Less: Reinvestment Rate | F16: ='Intrinsic Growth'!J58 -> 0.036885475 | G16: =F16 -> 0.036885475 | H16: =G16 -> 0.036885475 | I16: =H16 -> 0.036885475 | J16: =I16 -> 0.036885475 | K16: =J16 -> 0.036885475
B18: Free Cash Flow to Firm (FCFF) | F18: =F14*(1-F16) -> 2290.027 | G18: =G14*(1-G16) -> 2372.239 | H18: =H14*(1-H16) -> 2457.4024 | I18: =I14*(1-I16) -> 2545.6231 | J18: =J14*(1-J16) -> 2637.011 | K18: =K14*(1-K16) -> 2731.6797
B20: Mid Year Convention | G20: 0.5 | H20: =G20+1 -> 1.5 | I20: =H20+1 -> 2.5 | J20: =I20+1 -> 3.5 | K20: =J20+1 -> 4.5
B22: Discounting Factor | G22: =1/(1+$F$28)^G20 -> 0.94841013 | H22: =1/(1+$F$28)^H20 -> 0.85307763 | I22: =1/(1+$F$28)^I20 -> 0.76732778 | J22: =1/(1+$F$28)^J20 -> 0.69019735 | K22: =1/(1+$F$28)^K20 -> 0.62081994
B24: PV of FCFF | G24: =G18*G22 -> 2249.8555 | H24: =H18*H22 -> 2096.355 | I24: =I18*I22 -> 1953.3273 | J24: =J18*J22 -> 1820.058 | K24: =K18*K22 -> 1695.8812
B26: Expected Growth | F26: 0.0359
B27: Terminal Growth | F27: 0.076
B28: WACC | F28: ='WACC Modelling'!K48 -> 0.11175127
B31: Calculation of Terminal Value | H31: Sensitivity Analysis
H32: =E51 -> 2406.7648 | I32: 0.1 | J32: 0.1118 | K32: 0.12 | L32: 0.13 | M32: 0.14 | N32: 0.15
B33: FCFF (n+1) | E33: =K18*(1+F26) -> 2829.747 | H33: 0.03 | I33: 1408.2364 | J33: 1257.8751 | K33: 1176.6063 | L33: 1095.5358 | M33: 1029.2054 | N33: 973.93008
B34: WACC | E34: =F28 -> 0.11175127 | H34: 0.04 | I34: 1581.9589 | J34: 1382.1054 | K34: 1277.9445 | L34: 1176.6063 | M34: 1095.5358 | N34: 1029.2054
B35: Terminal Growth Rate | E35: =F27 -> 0.076 | H35: 0.05 | I35: 1825.1704 | J35: 1546.5397 | K35: 1408.2364 | L35: 1277.9445 | M35: 1176.6063 | N35: 1095.5358
H36: 0.06 | I36: 2189.9876 | J36: 1774.4622 | K36: 1581.9589 | L36: 1408.2364 | M36: 1277.9445 | N36: 1176.6063
B37: Terminal Value | E37: =E33/(E34-E35) -> 79150.96 | H37: 0.076 | I37: 3406.0452 | J37: 2403.9866 | K37: 2024.1616 | L37: 1717.0764 | M37: 1505.9553 | N37: 1351.8939
H38: 0.08 | I38: 4014.074 | J38: 2660.3495 | K38: 2189.9876 | L38: 1825.1704 | M38: 1581.9589 | N38: 1408.2364
B40: Calculation of Equity Value Per Share
B42: Present Value of FCFF | E42: =SUM(G24:K24) -> 9815.4769
B43: PV of Terminal Value | E43: =E37*K22 -> 49138.494
B44: Value of Operating Assets (EV) | E44: =SUM(E42:E43) -> 58953.971
B46: Add: Cash | E46: ='Data Sheet'!K69 -> 352.44
B47: Less: Debt | E47: =SUM('Raw FS'!L10:L11) -> 1358
B48: Value of Equity | E48: =E44+E46-E47 -> 57948.411
B49: No. of Shares | E49: ='Data Sheet'!B6 -> 24.077305
B51: Equity Value per Share | E51: =E48/E49 -> 2406.7648
B53: Share Price | E53: 5000
B54: Discount/Premium (%) | E54: =E53/E51-1 -> 1.0774776
B55: Discount/Premium (times x) | E55: =E53/E51-1 -> 1.0774776

Sheet Comps Valuation
B2: ='Data Sheet'!B1 -> BRITANNIA INDUSTRIES LTD
B3: (BRITANNIA) | BSE Code: 500825)
B4: INR 5,181.50 1st Sept 2026
B5: 52 Week (High - INR 6,336.95 & Low - 5,038)
B7: (Amount in Crores)
B8: Comparable Company Valuation | O8: Prepared by Pushti Gandhi
D10: Market Data | K10: Financials | O10: Valuation
B11: Company | C11: Ticker | D11: Share Price | E11: Shares Outstanding | F11: Equity Value | G11: Net Debt | H11: Enterprise Value | K11: Revenue | L11: EBITDA | M11: Net Income | O11: EV/Revenue | P11: EV/EBITDA | Q11: P/E
B13: ='Beta Comps'!C14 -> Britannia Inds. | D13: ='Beta Comps'!D14 -> 5023 | E13: ='Beta Comps'!F14 -> 24.09 | F13: =D13*E13 -> 121004.07 | G13: ='Beta Comps'!N14 -> 1027.84 | H13: =F13+G13 -> 122031.91 | K13: ='Beta Comps'!K14 -> 19529.34 | L13: ='Beta Comps'!O14 -> 3829.3483 | M13: ='Beta Comps'!L14 -> 2610.26 | O13: =$H13/K13 -> 6.2486449 | P13: =$H13/L13 -> 31.86754 | Q13: =$F13/M13 -> 46.357095
B14: ='Beta Comps'!C15 -> Nestle India | D14: ='Beta Comps'!D15 -> 1385 | E14: ='Beta Comps'!F15 -> 192.83 | F14: =D14*E14 -> 267069.55 | G14: ='Beta Comps'!N15 -> -896.71 | H14: =F14+G14 -> 266172.84 | K14: ='Beta Comps'!K15 -> 24436.62 | L14: ='Beta Comps'!O15 -> 5802.3686 | M14: ='Beta Comps'!L15 -> 3860.49 | O14: =$H14/K14 -> 10.892375 | P14: =$H14/L14 -> 45.873135 | Q14: =$F14/M14 -> 69.180221
B15: ='Beta Comps'!C16 -> Hatsun Agro | D15: ='Beta Comps'!D16 -> 1130.7 | E15: ='Beta Comps'!F16 -> 22.27 | F15: =D15*E15 -> 25180.689 | G15: ='Beta Comps'!N16 -> 1787.06 | H15: =F15+G15 -> 26967.749 | K15: ='Beta Comps'!K16 -> 10413.16 | L15: ='Beta Comps'!O16 -> 1184.8234 | M15: ='Beta Comps'!L16 -> 365.34 | O15: =$H15/K15 -> 2.5897757 | P15: =$H15/L15 -> 22.760987 | Q15: =$F15/M15 -> 68.923986
B16: ='Beta Comps'!C17 -> Milky Mist Dairy | D16: ='Beta Comps'!D17 -> 287.77 | E16: ='Beta Comps'!F17 -> 76.98 | F16: =D16*E16 -> 22152.535 | G16: ='Beta Comps'!N17 -> 1354.71 | H16: =F16+G16 -> 23507.245 | K16: ='Beta Comps'!K17 -> 3137.41 | L16: ='Beta Comps'!O17 -> 430.125 | M16: ='Beta Comps'!L17 -> 125.15 | O16: =$H16/K16 -> 7.4925638 | P16: =$H16/L16 -> 54.652123 | Q16: =$F16/M16 -> 177.00787
B17: ='Beta Comps'!C18 -> Zydus Wellness | D17: ='Beta Comps'!D18 -> 530.45 | E17: ='Beta Comps'!F18 -> 31.82 | F17: =D17*E17 -> 16878.919 | G17: ='Beta Comps'!N18 -> 3091.7 | H17: =F17+G17 -> 19970.619 | K17: ='Beta Comps'!K18 -> 4537.1 | L17: ='Beta Comps'!O18 -> 602.91918 | M17: ='Beta Comps'!L18 -> 188.2 | O17: =$H17/K17 -> 4.4016264 | P17: =$H17/L17 -> 33.123211 | Q17: =$F17/M17 -> 89.686073
B18: ='Beta Comps'!C19 -> Bikaji Foods | D18: ='Beta Comps'!D19 -> 558.95 | E18: ='Beta Comps'!F19 -> 25.07 | F18: =D18*E18 -> 14012.877 | G18: ='Beta Comps'!N19 -> -30.76 | H18: =F18+G18 -> 13982.117 | K18: ='Beta Comps'!K19 -> 2871.7 | L18: ='Beta Comps'!O19 -> 459.55913 | M18: ='Beta Comps'!L19 -> 270.48 | O18: =$H18/K18 -> 4.8689336 | P18: =$H18/L18 -> 30.425065 | Q18: =$F18/M18 -> 51.80744
B19: ='Beta Comps'!C20 -> Godrej Agrovet | D19: ='Beta Comps'!D20 -> 660.65 | E19: ='Beta Comps'!F20 -> 19.24 | F19: =D19*E19 -> 12710.906 | G19: ='Beta Comps'!N20 -> 1272.02 | H19: =F19+G19 -> 13982.926 | K19: ='Beta Comps'!K20 -> 10473.61 | L19: ='Beta Comps'!O20 -> 983.28371 | M19: ='Beta Comps'!L20 -> 424.66 | O19: =$H19/K19 -> 1.3350627 | P19: =$H19/L19 -> 14.220642 | Q19: =$F19/M19 -> 29.93196
B20: ='Beta Comps'!C21 -> EID Parry | D20: ='Beta Comps'!D21 -> 700.9 | E20: ='Beta Comps'!F21 -> 17.8 | F20: =D20*E20 -> 12476.02 | G20: ='Beta Comps'!N21 -> 2219.55 | H20: =F20+G20 -> 14695.57 | K20: ='Beta Comps'!K21 -> 38836.49 | L20: ='Beta Comps'!O21 -> 3682.3233 | M20: ='Beta Comps'!L21 -> 1227.49 | O20: =$H20/K20 -> 0.37839594 | P20: =$H20/L20 -> 3.9908419 | Q20: =$F20/M20 -> 10.163847
B21: ='Beta Comps'!C22 -> Manorama Indust. | D21: ='Beta Comps'!D22 -> 1923 | E21: ='Beta Comps'!F22 -> 6.31 | F21: =D21*E21 -> 12134.13 | G21: ='Beta Comps'!N22 -> 264.11 | H21: =F21+G21 -> 12398.24 | K21: ='Beta Comps'!K22 -> 1472.11 | L21: ='Beta Comps'!O22 -> 420.18475 | M21: ='Beta Comps'!L22 -> 264.23 | O21: =$H21/K21 -> 8.422088 | P21: =$H21/L21 -> 29.50664 | Q21: =$F21/M21 -> 45.922605
B22: ='Beta Comps'!C23 -> Avanti Feeds | D22: ='Beta Comps'!D23 -> 767 | E22: ='Beta Comps'!F23 -> 13.62 | F22: =D22*E22 -> 10446.54 | G22: ='Beta Comps'!N23 -> -424.74 | H22: =F22+G22 -> 10021.8 | K22: ='Beta Comps'!K23 -> 6359.97 | L22: ='Beta Comps'!O23 -> 865.4616 | M22: ='Beta Comps'!L23 -> 587.43 | O22: =$H22/K22 -> 1.5757621 | P22: =$H22/L22 -> 11.579716 | Q22: =$F22/M22 -> 17.783464
B24: High | O24: =MAX(O13:O22) -> 10.892375 | P24: =MAX(P13:P22) -> 54.652123 | Q24: =MAX(Q13:Q22) -> 177.00787
B25: 75th Percentile | O25: =QUARTILE(O13:O22,3) -> 7.1815841 | P25: =QUARTILE(P13:P22,3) -> 32.809293 | Q25: =QUARTILE(Q13:Q22,3) -> 69.116162
B26: Average | O26: =AVERAGE(O13:O22) -> 4.8205229 | P26: =AVERAGE(P13:P22) -> 27.79999 | Q26: =AVERAGE(Q13:Q22) -> 60.676456
B27: Median | O27: =QUARTILE(O13:O22,2) -> 4.63528 | P27: =QUARTILE(P13:P22,2) -> 29.965852 | Q27: =QUARTILE(Q13:Q22,2) -> 49.082268
B28: 25th Percentile | O28: =QUARTILE(O13:O22,1) -> 1.8292655 | P28: =QUARTILE(P13:P22,1) -> 16.355728 | Q28: =QUARTILE(Q13:Q22,1) -> 33.929621
B29: Low | O29: =MIN(O13:O22) -> 0.37839594 | P29: =MIN(P13:P22) -> 3.9908419 | Q29: =MIN(Q13:Q22) -> 10.163847
B32: Britannia Comparable Valuation | O32: EV/Revenue | P32: EV/EBITDA | Q32: P/E
B34: Implied Enterprise Value | O34: =O$27*K13 -> 90523.958 | P34: =P$27*L13 -> 114749.69 | Q34: =Q36+Q35 -> 129145.32
B35: Net Debt | O35: =$G$13 -> 1027.84 | P35: =$G$13 -> 1027.84 | Q35: =$G$13 -> 1027.84
B36: Implied Market Value | O36: =O34-O35 -> 89496.118 | P36: =P34-P35 -> 113721.85 | Q36: =Q27*M13 -> 128117.48
B37: Shares Outstanding | O37: =$E$13 -> 24.09 | P37: =$E$13 -> 24.09 | Q37: =$E$13 -> 24.09
B38: Implied Value per Share | O38: =O36/O37 -> 3715.0734 | P38: =P36/P37 -> 4720.7077 | Q38: =Q36/Q37 -> 5318.2848
B40: (Source: The Valuation School, Screener.in) | O40: =IF(O38>$D$13,"Undervalued","Overvalued") -> Overvalued | P40: =IF(P38>$D$13,"Undervalued","Overvalued") -> Overvalued | Q40: =IF(Q38>$D$13,"Undervalued","Overvalued") -> Undervalued

Sheet VAR - Historical & Monte Carlo
B2: ='Data Sheet'!B1 -> BRITANNIA INDUSTRIES LTD
B3: (BRITANNIA) | BSE Code: 500825)
B4: INR 5,181.50 1st Sept 2026
B5: 52 Week (High - INR 6,336.95 & Low - 5,038)
K6: Prepared by Pushti Gandhi
B8: Date | C8: Adj Close | D8: Return | E8: Sorted Return | F8: Replication | G8: Simulated Return | I8: Calculation of Value At Risk - Britannia Ind Ltd (Simulation Approach)
B9: 36427 | C9: 79.56 | D9: =(C9-C10)/C10 -> -0.71363784 | E9: 0.45023697 | F9: 1 | G9: =_xlfn.NORM.INV(RAND(),M$11,M$12) -> -0.0084282129
B10: 41421 | C10: 277.83 | D10: =(C10-C11)/C11 -> 0.42119802 | E10: 0.15805927 | F10: 2 | G10: =_xlfn.NORM.INV(RAND(),M$11,M$12) -> -0.053010664 | I10: Historical Approach
B11: 40429 | C11: 195.49 | D11: =(C11-C12)/C12 -> 0.99826229 | E11: 0.13676804 | F11: 3 | G11: =_xlfn.NORM.INV(RAND(),M$11,M$12) -> -0.018459908 | I11: Mean | M11: =AVERAGE(E9:E7722) -> 0.001013421
B12: 39786 | C12: 97.83 | D12: =(C12-C13)/C13 -> -0.76102887 | E12: 0.11614375 | F12: 4 | G12: =_xlfn.NORM.INV(RAND(),M$11,M$12) -> -0.0027906187 | I12: Standard Deviation | M12: =_xlfn.STDEV.S(E9:E7722) -> 0.018497949
B13: 41801 | C13: 409.38 | D13: =(C13-C14)/C14 -> -0.80299421 | E13: 0.1066418 | F13: 5 | G13: =_xlfn.NORM.INV(RAND(),M$11,M$12) -> -0.0028727847 | I13: Min | M13: =MIN(E9:E7722) -> -0.2799433
B14: 43914 | C14: 2078.01 | D14: =(C14-C15)/C15 -> -0.16574597 | E14: 0.10610698 | F14: 6 | G14: =_xlfn.NORM.INV(RAND(),M$11,M$12) -> 0.0029030693 | I14: Max | M14: =MAX(E9:E7722) -> 0.45023697
B15: 43928 | C15: 2490.86 | D15: =(C15-C16)/C16 -> 43.71921 | E15: 0.10582511 | F15: 7 | G15: =_xlfn.NORM.INV(RAND(),M$11,M$12) -> -0.023075247 | I15: CMP | M15: 4918
B16: 36220 | C16: 55.7 | D16: =(C16-C17)/C17 -> 1.0568685 | E16: 0.1010081 | F16: 8 | G16: =_xlfn.NORM.INV(RAND(),M$11,M$12) -> -0.0030371733
B17: 35955 | C17: 27.08 | D17: =(C17-C18)/C18 -> 0.15332198 | E17: 0.099918765 | F17: 9 | G17: =_xlfn.NORM.INV(RAND(),M$11,M$12) -> 0.035929247 | I17: Monte Carlo Simulation
B18: 35886 | C18: 23.48 | D18: =(C18-C19)/C19 -> 1.9910828 | E18: 0.099765808 | F18: 10 | G18: =_xlfn.NORM.INV(RAND(),M$11,M$12) -> 0.020936576 | I18: Mean | M18: =AVERAGE(G9:G7722) -> 0.001107116
B19: 35097 | C19: 7.85 | D19: =(C19-C20)/C20 -> -0.95005726 | E19: 0.096368715 | F19: 11 | G19: =_xlfn.NORM.INV(RAND(),M$11,M$12) -> 0.023624746 | I19: Standard Deviation | M19: =_xlfn.STDEV.S(G9:G7722) -> 0.01857994
B20: 40563 | C20: 157.18 | D20: =(C20-C21)/C21 -> -0.93761263 | E20: 0.095483691 | F20: 12 | G20: =_xlfn.NORM.INV(RAND(),M$11,M$12) -> -0.025654557 | I20: Min | M20: =MIN(G9:G7722) -> -0.069880144
B21: 43728 | C21: 2519.42 | D21: =(C21-C22)/C22 -> 0.84721754 | E21: 0.093526741 | F21: 13 | G21: =_xlfn.NORM.INV(RAND(),M$11,M$12) -> -0.0036268338 | I21: Max | M21: =MAX(G9:G7722) -> 0.067371694
B22: 42590 | C22: 1363.9 | D22: =(C22-C23)/C23 -> 156.31257 | E22: 0.092754761 | F22: 14 | G22: =_xlfn.NORM.INV(RAND(),M$11,M$12) -> -0.011084946 | I22: CMP | M22: 4918
B23: 35104 | C23: 8.67 | D23: =(C23-C24)/C24 -> -0.16312741 | E23: 0.091939547 | F23: 15 | G23: =_xlfn.NORM.INV(RAND(),M$11,M$12) -> -0.033254163
B24: 35304 | C24: 10.36 | D24: =(C24-C25)/C25 -> -0.89773961 | E24: 0.090526316 | F24: 16 | G24: =_xlfn.NORM.INV(RAND(),M$11,M$12) -> -0.0022550133
B25: 39801 | C25: 101.31 | D25: =(C25-C26)/C26 -> 2.963615 | E25: 0.089237716 | F25: 17 | G25: =_xlfn.NORM.INV(RAND(),M$11,M$12) -> 0.0070169635 | I25: Percentile | J25: Confidence | K25: VAR% | L25: Stock Price | M25: VAR (INR)
B26: 35900 | C26: 25.56 | D26: =(C26-C27)/C27 -> -0.99344661 | E26: 0.089049851 | F26: 18 | G26: =_xlfn.NORM.INV(RAND(),M$11,M$12) -> -0.011615433 | I26: 0.05 | J26: =100%-I26 -> 0.95 | K26: =_xlfn.PERCENTILE.INC($G$9:$G$7722,J26) -> 0.031661784 | L26: =$M$15*(1-K26) -> 4762.2873 | M26: =$M$15-L26 -> 155.71265
B27: 44872 | C27: 3900.27 | D27: =(C27-C28)/C28 -> 0.65059354 | E27: 0.088074966 | F27: 19 | G27: =_xlfn.NORM.INV(RAND(),M$11,M$12) -> -0.013711649 | I27: 0.01 | J27: =100%-I27 -> 0.99 | K27: =_xlfn.PERCENTILE.INC($G$9:$G$7722,J27) -> 0.04468126 | L27: =$M$15*(1-K27) -> 4698.2576 | M27: =$M$15-L27 -> 219.74243
B28: 43921 | C28: 2362.95 | D28: =(C28-C29)/C29 -> 22.82006 | E28: 0.086993523 | F28: 20 | G28: =_xlfn.NORM.INV(RAND(),M$11,M$12) -> -0.031580336 | I28: 0.005 | J28: =100%-I28 -> 0.995 | K28: =_xlfn.PERCENTILE.INC($G$9:$G$7722,J28) -> 0.049163634 | L28: =$M$15*(1-K28) -> 4676.2132 | M28: =$M$15-L28 -> 241.78675
B29: 38624 | C29: 99.2 | D29: =(C29-C30)/C30 -> 1.4566617 | E29: 0.086408937 | F29: 21 | G29: =_xlfn.NORM.INV(RAND(),M$11,M$12) -> -0.013656236 | I29: 0.1 | J29: =100%-I29 -> 0.9 | K29: =_xlfn.PERCENTILE.INC($G$9:$G$7722,J29) -> 0.024909885 | L29: =$M$15*(1-K29) -> 4795.4932 | M29: =$M$15-L29 -> 122.50681
B30: 36651 | C30: 40.38 | D30: =(C30-C31)/C31 -> 2.0990023 | E30: 0.084900591 | F30: 22 | G30: =_xlfn.NORM.INV(RAND(),M$11,M$12) -> 0.022728917
B31: 35492 | C31: 13.03 | D31: =(C31-C32)/C32 -> -0.40502283 | E31: 0.08312552 | F31: 23 | G31: =_xlfn.NORM.INV(RAND(),M$11,M$12) -> 0.0019041624
B32: 35873 | C32: 21.9 | D32: =(C32-C33)/C33 -> -0.21477232 | E32: 0.082550667 | F32: 24 | G32: =_xlfn.NORM.INV(RAND(),M$11,M$12) -> 0.0048621725
B33: 35982 | C33: 27.89 | D33: =(C33-C34)/C34 -> 1.547032 | E33: 0.08142691 | F33: 25 | G33: =_xlfn.NORM.INV(RAND(),M$11,M$12) -> -0.041845324
B34: 35201 | C34: 10.95 | D34: =(C34-C35)/C35 -> -0.83044286 | E34: 0.08094768 | F34: 26 | G34: =_xlfn.NORM.INV(RAND(),M$11,M$12) -> 0.035551471
B35: 36319 | C35: 64.58 | D35: =(C35-C36)/C36 -> 0.47375628 | E35: 0.080113731 | F35: 27 | G35: =_xlfn.NORM.INV(RAND(),M$11,M$12) -> -0.020993501
B36: 36168 | C36: 43.82 | D36: =(C36-C37)/C37 -> -0.34704217 | E36: 0.080108455 | F36: 28 | G36: =_xlfn.NORM.INV(RAND(),M$11,M$12) -> -0.003304196
B37: 36250 | C37: 67.11 | D37: =(C37-C38)/C38 -> 0.22329566 | E37: 0.079980689 | F37: 29 | G37: =_xlfn.NORM.INV(RAND(),M$11,M$12) -> 0.014110871
B38: 36426 | C38: 54.86 | D38: =(C38-C39)/C39 -> -0.066848103 | E38: 0.07992126 | F38: 30 | G38: =_xlfn.NORM.INV(RAND(),M$11,M$12) -> -0.04262441
B39: 36532 | C39: 58.79 | D39: =(C39-C40)/C40 -> 0.24239222 | E39: 0.079904482 | F39: 31 | G39: =_xlfn.NORM.INV(RAND(),M$11,M$12) -> 0.0096553505
B40: 36171 | C40: 47.32 | D40: =(C40-C41)/C41 -> -0.01784973 | E40: 0.079872204 | F40: 32 | G40: =_xlfn.NORM.INV(RAND(),M$11,M$12) -> -0.021614124
B41: 36181 | C41: 48.18 | D41: =(C41-C42)/C42 -> -0.31823971 | E41: 0.07978485 | F41: 33 | G41: =_xlfn.NORM.INV(RAND(),M$11,M$12) -> 0.0074238307
... B7722: 36425 | C7722: 50.8 | D7722: =(C7722-C7723)/C7723 -> #DIV/0! | E7722: -0.2799433 | F7722: 7714 | G7722: =_xlfn.NORM.INV(RAND(),M$11,M$12) -> -0.0075065614

Sheet Football Field Analysis
B2: ='Data Sheet'!B1 -> BRITANNIA INDUSTRIES LTD
B3: (BRITANNIA) | BSE Code: 500825)
B4: INR 5,181.50 1st Sept 2026
B5: 52 Week (High - INR 6,336.95 & Low - 5,038) | N5: Prepared by Pushti Gandhi
K10: Football Field Analysis
M11: OpenLow | N11: Low | O11: OpenHigh | P11: High
K12: Comps | M12: 3715.07 | N12: 3715.07 | O12: 5318.28 | P12: 5318.28
K13: DCF Bear | M13: 973.9 | N13: 973.9 | O13: 1408.2 | P13: 1408.2
K14: DCF Base | M14: 1257.9 | N14: 1257.9 | O14: 2660.3 | P14: 2660.3
K15: DCF Bull | M15: 1408.2 | N15: 1408.2 | O15: 4014.1 | P15: 4014.1
K16: 52 Weeks High/Low | M16: 4905 | N16: 4905 | O16: 6271 | P16: 6271

Sheet Dupont Analysis
B2: ='Data Sheet'!B1 -> BRITANNIA INDUSTRIES LTD
B3: (BRITANNIA) | BSE Code: 500825)
B4: INR 5,181.50 1st Sept 2026
B5: 52 Week (High - INR 6,336.95 & Low - 5,038)
H6: Prepared by Pushti Gandhi
B8: Dupont Analysis - Return on Equity & Return on Asset
B10: Return on Equity - ROE
C11: ='Historical FS'!E9 -> 43555 | D11: ='Historical FS'!F9 -> 43920 | E11: ='Historical FS'!G9 -> 44285 | F11: ='Historical FS'!H9 -> 44650 | G11: ='Historical FS'!I9 -> 45015 | H11: ='Historical FS'!J9 -> 45380 | I11: ='Historical FS'!K9 -> 45745 | J11: ='Historical FS'!L9 -> 46110
B12: Net Profit | C12: ='Data Sheet'!D30 -> 1159.12 | D12: ='Data Sheet'!E30 -> 1402.63 | E12: ='Data Sheet'!F30 -> 1863.9 | F12: ='Data Sheet'!G30 -> 1524.82 | G12: ='Data Sheet'!H30 -> 2321.77 | H12: ='Data Sheet'!I30 -> 2139.81 | I12: ='Data Sheet'!J30 -> 2178.73 | J12: ='Data Sheet'!K30 -> 2533.49
B13: Average Shareholder Equity | C13: =(('Data Sheet'!D57+'Data Sheet'!D58)+('Data Sheet'!C57+'Data Sheet'!C58))/2 -> 3829.74 | D13: =(('Data Sheet'!E57+'Data Sheet'!E58)+('Data Sheet'!D57+'Data Sheet'!D58))/2 -> 4328.04 | E13: =(('Data Sheet'!F57+'Data Sheet'!F58)+('Data Sheet'!E57+'Data Sheet'!E58))/2 -> 3975.245 | F13: =(('Data Sheet'!G57+'Data Sheet'!G58)+('Data Sheet'!F57+'Data Sheet'!F58))/2 -> 3052.88 | G13: =(('Data Sheet'!H57+'Data Sheet'!H58)+('Data Sheet'!G57+'Data Sheet'!G58))/2 -> 3046.185 | H13: =(('Data Sheet'!I57+'Data Sheet'!I58)+('Data Sheet'!H57+'Data Sheet'!H58))/2 -> 3737.895 | I13: =(('Data Sheet'!J57+'Data Sheet'!J58)+('Data Sheet'!I57+'Data Sheet'!I58))/2 -> 4148.62 | J13: =(('Data Sheet'!K57+'Data Sheet'!K58)+('Data Sheet'!J57+'Data Sheet'!J58))/2 -> 4731.14
B14: Return on Equity (ROE) | C14: =C12/C13 -> 0.30266284 | D14: =D12/D13 -> 0.32407972 | E14: =E12/E13 -> 0.46887676 | F14: =F12/F13 -> 0.49946935 | G14: =G12/G13 -> 0.76218943 | H14: =H12/H13 -> 0.57246391 | I14: =I12/I13 -> 0.52516982 | J14: =J12/J13 -> 0.5354925
B16: ROE - Dupont Equation
C17: =C11 -> 43555 | D17: =D11 -> 43920 | E17: =E11 -> 44285 | F17: =F11 -> 44650 | G17: =G11 -> 45015 | H17: =H11 -> 45380 | I17: =I11 -> 45745 | J17: =J11 -> 46110
B18: Net Profit | C18: =C12 -> 1159.12 | D18: =D12 -> 1402.63 | E18: =E12 -> 1863.9 | F18: =F12 -> 1524.82 | G18: =G12 -> 2321.77 | H18: =H12 -> 2139.81 | I18: =I12 -> 2178.73 | J18: =J12 -> 2533.49
B19: Revenues | C19: ='Data Sheet'!D17 -> 11054.67 | D19: ='Data Sheet'!E17 -> 11599.55 | E19: ='Data Sheet'!F17 -> 13136.14 | F19: ='Data Sheet'!G17 -> 14136.26 | G19: ='Data Sheet'!H17 -> 16300.55 | H19: ='Data Sheet'!I17 -> 16769.27 | I19: ='Data Sheet'!J17 -> 17942.67 | J19: ='Data Sheet'!K17 -> 19151.59
B20: Net Profit Margin (A) | C20: =C18/C19 -> 0.10485342 | D20: =D18/D19 -> 0.12092107 | E20: =E18/E19 -> 0.141891 | F20: =F18/F19 -> 0.10786587 | G20: =G18/G19 -> 0.14243507 | H20: =H18/H19 -> 0.12760305 | I20: =I18/I19 -> 0.1214273 | J20: =J18/J19 -> 0.13228614
B22: Revenues | C22: =C19 -> 11054.67 | D22: =D19 -> 11599.55 | E22: =E19 -> 13136.14 | F22: =F19 -> 14136.26 | G22: =G19 -> 16300.55 | H22: =H19 -> 16769.27 | I22: =I19 -> 17942.67 | J22: =J19 -> 19151.59
B23: Average Total Asset | C23: =('Data Sheet'!D66+'Data Sheet'!C66)/2 -> 5712.935 | D23: =('Data Sheet'!E66+'Data Sheet'!D66)/2 -> 7033.745 | E23: =('Data Sheet'!F66+'Data Sheet'!E66)/2 -> 7914.815 | F23: =('Data Sheet'!G66+'Data Sheet'!F66)/2 -> 7763.345 | G23: =('Data Sheet'!H66+'Data Sheet'!G66)/2 -> 8438.725 | H23: =('Data Sheet'!I66+'Data Sheet'!H66)/2 -> 9211.175 | I23: =('Data Sheet'!J66+'Data Sheet'!I66)/2 -> 8954.125 | J23: =('Data Sheet'!K66+'Data Sheet'!J66)/2 -> 9283.535
B24: Asset Turnover Ratio (B) | C24: =C22/C23 -> 1.9350246 | D24: =D22/D23 -> 1.6491286 | E24: =E22/E23 -> 1.6596901 | F24: =F22/F23 -> 1.8208981 | G24: =G22/G23 -> 1.9316366 | H24: =H22/H23 -> 1.8205354 | I24: =I22/I23 -> 2.003844 | J24: =J22/J23 -> 2.0629631
B26: Average Total Asset | C26: =C23 -> 5712.935 | D26: =D23 -> 7033.745 | E26: =E23 -> 7914.815 | F26: =F23 -> 7763.345 | G26: =G23 -> 8438.725 | H26: =H23 -> 9211.175 | I26: =I23 -> 8954.125 | J26: =J23 -> 9283.535
B27: Average Shareholder Equity | C27: =C13 -> 3829.74 | D27: =D13 -> 4328.04 | E27: =E13 -> 3975.245 | F27: =F13 -> 3052.88 | G27: =G13 -> 3046.185 | H27: =H13 -> 3737.895 | I27: =I13 -> 4148.62 | J27: =J13 -> 4731.14
B28: Equity Multiplier (C) | C28: =C26/C27 -> 1.4917292 | D28: =D26/D27 -> 1.6251571 | E28: =E26/E27 -> 1.9910257 | F28: =F26/F27 -> 2.5429578 | G28: =G26/G27 -> 2.7702602 | H28: =H26/H27 -> 2.464268 | I28: =I26/I27 -> 2.1583382 | J28: =J26/J27 -> 1.9622195
B30: Return on Equity (A*B*C) | C30: =C20*C24*C28 -> 0.30266284 | D30: =D20*D24*D28 -> 0.32407972 | E30: =E20*E24*E28 -> 0.46887676 | F30: =F20*F24*F28 -> 0.49946935 | G30: =G20*G24*G28 -> 0.76218943 | H30: =H20*H24*H28 -> 0.57246391 | I30: =I20*I24*I28 -> 0.52516982 | J30: =J20*J24*J28 -> 0.5354925
B32: Return on Assets (ROA)
C33: =C17 -> 43555 | D33: =D17 -> 43920 | E33: =E17 -> 44285 | F33: =F17 -> 44650 | G33: =G17 -> 45015 | H33: =H17 -> 45380 | I33: =I17 -> 45745 | J33: =J17 -> 46110
B34: Net Profit | C34: =C18 -> 1159.12 | D34: =D18 -> 1402.63 | E34: =E18 -> 1863.9 | F34: =F18 -> 1524.82 | G34: =G18 -> 2321.77 | H34: =H18 -> 2139.81 | I34: =I18 -> 2178.73 | J34: =J18 -> 2533.49
B35: Average Total Asset | C35: =C23 -> 5712.935 | D35: =D23 -> 7033.745 | E35: =E23 -> 7914.815 | F35: =F23 -> 7763.345 | G35: =G23 -> 8438.725 | H35: =H23 -> 9211.175 | I35: =I23 -> 8954.125 | J35: =J23 -> 9283.535
B36: Return on Asset | C36: =C34/C35 -> 0.20289396 | D36: =D34/D35 -> 0.19941439 | E36: =E34/E35 -> 0.23549508 | F36: =F34/F35 -> 0.19641276 | G36: =G34/G35 -> 0.2751328 | H36: =H34/H35 -> 0.23230587 | I36: =I34/I35 -> 0.24332137 | J36: =J34/J35 -> 0.27290143
B38: ROA - Dupont Equation
C39: =C33 -> 43555 | D39: =D33 -> 43920 | E39: =E33 -> 44285 | F39: =F33 -> 44650 | G39: =G33 -> 45015 | H39: =H33 -> 45380 | I39: =I33 -> 45745 | J39: =J33 -> 46110
B40: Net Profit | C40: =C34 -> 1159.12 | D40: =D34 -> 1402.63 | E40: =E34 -> 1863.9 | F40: =F34 -> 1524.82 | G40: =G34 -> 2321.77 | H40: =H34 -> 2139.81 | I40: =I34 -> 2178.73 | J40: =J34 -> 2533.49
B41: Revenues | C41: =C19 -> 11054.67 | D41: =D19 -> 11599.55 | E41: =E19 -> 13136.14 | F41: =F19 -> 14136.26 | G41: =G19 -> 16300.55 | H41: =H19 -> 16769.27 | I41: =I19 -> 17942.67 | J41: =J19 -> 19151.59
B42: Net Profit Margin (A) | C42: =C40/C41 -> 0.10485342 | D42: =D40/D41 -> 0.12092107 | E42: =E40/E41 -> 0.141891 | F42: =F40/F41 -> 0.10786587 | G42: =G40/G41 -> 0.14243507 | H42: =H40/H41 -> 0.12760305 | I42: =I40/I41 -> 0.1214273 | J42: =J40/J41 -> 0.13228614
B44: Revenues | C44: =C19 -> 11054.67 | D44: =D19 -> 11599.55 | E44: =E19 -> 13136.14 | F44: =F19 -> 14136.26 | G44: =G19 -> 16300.55 | H44: =H19 -> 16769.27 | I44: =I19 -> 17942.67 | J44: =J19 -> 19151.59
B45: Average Total Asset | C45: =C23 -> 5712.935 | D45: =D23 -> 7033.745 | E45: =E23 -> 7914.815 | F45: =F23 -> 7763.345 | G45: =G23 -> 8438.725 | H45: =H23 -> 9211.175 | I45: =I23 -> 8954.125 | J45: =J23 -> 9283.535
B46: Asset Turnover Ratio (B) | C46: =C44/C45 -> 1.9350246 | D46: =D44/D45 -> 1.6491286 | E46: =E44/E45 -> 1.6596901 | F46: =F44/F45 -> 1.8208981 | G46: =G44/G45 -> 1.9316366 | H46: =H44/H45 -> 1.8205354 | I46: =I44/I45 -> 2.003844 | J46: =J44/J45 -> 2.0629631
B48: Return on Assets (A*B) | C48: =C42*C46 -> 0.20289396 | D48: =D42*D46 -> 0.19941439 | E48: =E42*E46 -> 0.23549508 | F48: =F42*F46 -> 0.19641276 | G48: =G42*G46 -> 0.2751328 | H48: =H42*H46 -> 0.23230587 | I48: =I42*I46 -> 0.24332137 | J48: =J42*J46 -> 0.27290143
B51: DuPont Summary
B53: * Throughout the whole analysis period, the ROE ratio remained high, increasing from 30.27% in FY19 to 32.41% in FY20 during pre-covid.
B54: It has been drastically increased to 76.22% in FY23 and then decreasing down to 53.55% in FY26, which indicates an effective value creation
B55: process driven primarily by strong net profit margins and optimized asset utilization
B56: * The net profit margin increased from 10.49% in FY19 to 14.24% in F23 and then decreased to 13.23% in FY26, hitting notable peaks during
B57: years of benign input costs and optimized pricing strategies
B58: * The Asset Turnover Ratio consistently ranged between 1.65x and 1.94x from FY19 - FY24 and then gradually increasing to 2.06x in FY26.
B59: This indicates effective use of fixed and current assets and generating steady top-line revenue relative to total asset investments
B60: * Equity Multiplier ranged dynamically from 1.49x in FY19 to peaks near 2.77x in FY23 during periods of capital restructuring. It gradually
B61: reduced to 1.96 in FY26 indicating company is using less financial leverage and has stronger equity position. Sound financial management
B62: and effective debt policies helped maintain long term solvency while improving returns on equity
B63: * ROA has been strong indicator of performance with its values ranging between 19.94% to 27.29% supported by high net profit margins
... B68: any investments

Sheet Financial Summary
B2: ='Data Sheet'!B1 -> BRITANNIA INDUSTRIES LTD
B3: (BRITANNIA) | BSE Code: 500825)
B4: INR 5,181.50 1st Sept 2026
B5: 52 Week (High - INR 6,336.95 & Low - 5,038)
M6: Prepared by Pushti Gandhi
B8: Britannia Industries Limited is an Indian multinational food products company, which sells biscuits, breads, and dairy products. Founded
B9: in 1892, it is one of India's oldest existing companies and currently part of the Wadia Group headed by Nusli Wadia. As of 2023, about 80%
B10: of its revenues came from biscuit products. It is one of India's leading food companies with a 100 year legacy and annual revenues in excess
B11: of Rs. 16,000 Cr. Britannia is among the most trusted food brands, and manufactures India's favorite brands like Good Day, Tiger, NutriChoice,
B12: Milk Bikis and Marigold.
B14: Financial Summary
B42: Recent Updates
B44: * The revenue grew at a steady pace over the multi-year cycle, capping at ₹19,152 crore in FY26. Net profit initially contracted in FY24 due to sudden
B45: post pandemic raw material inflation (wheat, sugar, & packaging) but rebounded aggressively by 16.4% in FY26 due to structural premium strategies
B46: and direct cost corrections.
B47: * There is a distinct transition in Britannia from a highly leveraged, high return structure to a more capital efficient, deleveraged, and fundamentally
B48: stable framework.
... B54: long term revenue streams, Britannia shifted its strategy from traditional volume push systems toward an agile, high margin ecosystem.

Sheet Altman's Z Score Analysis
B2: ='Data Sheet'!B1 -> BRITANNIA INDUSTRIES LTD
B3: (BRITANNIA) | BSE Code: 500825)
B4: INR 5,181.50 1st Sept 2026
B5: 52 Week (High - INR 6,336.95 & Low - 5,038)
L6: Prepared by Pushti Gandhi
B7: About the Company
B8: Britannia Industries Limited is an Indian multinational food products company, which sells biscuits, breads, and dairy products. Founded
B9: in 1892, it is one of India's oldest existing companies and currently part of the Wadia Group headed by Nusli Wadia. As of 2023, about 80%
B10: of its revenues came from biscuit products. It is one of India's leading food companies with a 100 year legacy and annual revenues in excess
B11: of Rs. 16,000 Cr. Britannia is among the most trusted food brands, and manufactures India's favorite brands like Good Day, Tiger, NutriChoice,
B12: Milk Bikis and Marigold.
B14: Financial Summary
B45: Recent Updates
B47: * Britannia maintained an exceptionally strong Altman Z-Score throughout the analysis period, indicating a very low probability of financial distress.
B48: * Strong EBIT-to-Assets, Sales-to-Assets, and Market Cap-to-Long Term Liabilities ratios highlight the company's operational strength and robust financials.

Sheet Altman Z-Score Analysis Calc
B2: ='Data Sheet'!B1 -> BRITANNIA INDUSTRIES LTD
B3: (BRITANNIA) | BSE Code: 500825)
B4: INR 5,181.50 1st Sept 2026
B5: 52 Week (High - INR 6,336.95 & Low - 5,038)
H6: Prepared by Pushti Gandhi
B8: Altman's Z Score Analysis Calculation
B10: Working Capital / Total Assets
C11: ='Dupont Analysis'!C11 -> 43555 | D11: ='Dupont Analysis'!D11 -> 43920 | E11: ='Dupont Analysis'!E11 -> 44285 | F11: ='Dupont Analysis'!F11 -> 44650 | G11: ='Dupont Analysis'!G11 -> 45015 | H11: ='Dupont Analysis'!H11 -> 45380 | I11: ='Dupont Analysis'!I11 -> 45745 | J11: ='Dupont Analysis'!J11 -> 46110
B12: Working Capital | C12: ='Data Sheet'!D65-'Data Sheet'!D60 -> 1143.45 | D12: ='Data Sheet'!E65-'Data Sheet'!E60 -> 1129.46 | E12: ='Data Sheet'!F65-'Data Sheet'!F60 -> 964.44 | F12: ='Data Sheet'!G65-'Data Sheet'!G60 -> 988.04 | G12: ='Data Sheet'!H65-'Data Sheet'!H60 -> 447.18 | H12: ='Data Sheet'!I65-'Data Sheet'!I60 -> 281.08 | I12: ='Data Sheet'!J65-'Data Sheet'!J60 -> -256.2 | J12: ='Data Sheet'!K65-'Data Sheet'!K60 -> -11.88
B13: Total Assets | C13: ='Data Sheet'!D66 -> 6237.95 | D13: ='Data Sheet'!E66 -> 7829.54 | E13: ='Data Sheet'!F66 -> 8000.09 | F13: ='Data Sheet'!G66 -> 7526.6 | G13: ='Data Sheet'!H66 -> 9350.85 | H13: ='Data Sheet'!I66 -> 9071.5 | I13: ='Data Sheet'!J66 -> 8836.75 | J13: ='Data Sheet'!K66 -> 9730.32
B14: Working Capital / Total Assets (A) | C14: =C12/C13 -> 0.18330541 | D14: =D12/D13 -> 0.14425624 | E14: =E12/E13 -> 0.12055364 | F14: =F12/F13 -> 0.13127308 | G14: =G12/G13 -> 0.04782239 | H14: =H12/H13 -> 0.030984953 | I14: =I12/I13 -> -0.028992559 | J14: =J12/J13 -> -0.0012209259
B16: Retained Earnings / Total Assets
C17: =C11 -> 43555 | D17: =D11 -> 43920 | E17: =E11 -> 44285 | F17: =F11 -> 44650 | G17: =G11 -> 45015 | H17: =H11 -> 45380 | I17: =I11 -> 45745 | J17: =J11 -> 46110
B18: Retained Earnings | C18: ='Historical FS'!E45*'Historical FS'!E47*'Historical FS'!E53 -> 588.56 | D18: ='Historical FS'!F45*'Historical FS'!F47*'Historical FS'!F53 -> 289.02 | E18: ='Historical FS'!G45*'Historical FS'!G47*'Historical FS'!G53 -> 0 | F18: ='Historical FS'!H45*'Historical FS'!H47*'Historical FS'!H53 -> 0 | G18: ='Historical FS'!I45*'Historical FS'!I47*'Historical FS'!I53 -> 0 | H18: ='Historical FS'!J45*'Historical FS'!J47*'Historical FS'!J53 -> 152.32 | I18: ='Historical FS'!K45*'Historical FS'!K47*'Historical FS'!K53 -> 168.81 | J18: ='Historical FS'!L45*'Historical FS'!L47*'Historical FS'!L53 -> 132.84
B19: Total Assets | C19: =C13 -> 6237.95 | D19: =D13 -> 7829.54 | E19: =E13 -> 8000.09 | F19: =F13 -> 7526.6 | G19: =G13 -> 9350.85 | H19: =H13 -> 9071.5 | I19: =I13 -> 8836.75 | J19: =J13 -> 9730.32
B20: Retained Earnings / Total Assets (B) | C20: =C18/C19 -> 0.09435151 | D20: =D18/D19 -> 0.036914046 | E20: =E18/E19 -> 0 | F20: =F18/F19 -> 0 | G20: =G18/G19 -> 0 | H20: =H18/H19 -> 0.016791049 | I20: =I18/I19 -> 0.019103177 | J20: =J18/J19 -> 0.013652172
B22: EBIT / Total Assets
C23: =C17 -> 43555 | D23: =D17 -> 43920 | E23: =E17 -> 44285 | F23: =F17 -> 44650 | G23: =G17 -> 45015 | H23: =H17 -> 45380 | I23: =I17 -> 45745 | J23: =J17 -> 46110
B24: EBIT | C24: ='Historical FS'!E33 -> 1570.57 | D24: ='Historical FS'!F33 -> 1658.37 | E24: ='Historical FS'!G33 -> 2311.44 | F24: ='Historical FS'!H33 -> 2000.77 | G24: ='Historical FS'!I33 -> 2605 | H24: ='Historical FS'!J33 -> 2866.19 | I24: ='Historical FS'!K33 -> 2863.07 | J24: ='Historical FS'!L33 -> 3177.51
B25: Total Assets | C25: =C13 -> 6237.95 | D25: =D13 -> 7829.54 | E25: =E13 -> 8000.09 | F25: =F13 -> 7526.6 | G25: =G13 -> 9350.85 | H25: =H13 -> 9071.5 | I25: =I13 -> 8836.75 | J25: =J13 -> 9730.32
B26: EBIT / Total Assets (C) | C26: =C24/C25 -> 0.25177663 | D26: =D24/D25 -> 0.21180938 | E26: =E24/E25 -> 0.28892675 | F26: =F24/F25 -> 0.26582654 | G26: =G24/G25 -> 0.2785843 | H26: =H24/H25 -> 0.31595546 | I26: =I24/I25 -> 0.32399581 | J26: =J24/J25 -> 0.32655761
B28: Market Cap / Long Term Liabilities
C29: =C23 -> 43555 | D29: =D23 -> 43920 | E29: =E23 -> 44285 | F29: =F23 -> 44650 | G29: =G23 -> 45015 | H29: =H23 -> 45380 | I29: =I23 -> 45745 | J29: =J23 -> 46110
B30: Market Cap | C30: =('Data Sheet'!D90*'Data Sheet'!D70)/10000000 -> 74150.21 | D30: =('Data Sheet'!E90*'Data Sheet'!E70)/10000000 -> 64620.388 | E30: =('Data Sheet'!F90*'Data Sheet'!F70)/10000000 -> 87315.962 | F30: =('Data Sheet'!G90*'Data Sheet'!G70)/10000000 -> 77232.01 | G30: =('Data Sheet'!H90*'Data Sheet'!H70)/10000000 -> 104106.89 | H30: =('Data Sheet'!I90*'Data Sheet'!I70)/10000000 -> 118296.44 | I30: =('Data Sheet'!J90*'Data Sheet'!J70)/10000000 -> 118914.27 | J30: =('Data Sheet'!K90*'Data Sheet'!K70)/10000000 -> 130622.88
B31: Long Term Liabilities | C31: ='Data Sheet'!D59 -> 156.02 | D31: ='Data Sheet'!E59 -> 1537.59 | E31: ='Data Sheet'!F59 -> 2106.94 | F31: ='Data Sheet'!G59 -> 2481.2 | G31: ='Data Sheet'!H59 -> 2997.37 | H31: ='Data Sheet'!I59 -> 2064.96 | I31: ='Data Sheet'!J59 -> 1246.51 | J31: ='Data Sheet'!K59 -> 1380.28
B32: Market Cap / Long Term Liabilities (D) | C32: =C30/C31 -> 475.26093 | D32: =D30/D31 -> 42.02706 | E32: =E30/E31 -> 41.442073 | F32: =F30/F31 -> 31.126878 | G32: =G30/G31 -> 34.732746 | H32: =H30/H31 -> 57.287522 | I32: =I30/I31 -> 95.397766 | J32: =J30/J31 -> 94.635057
B34: Sales / Total Assets
C35: =C29 -> 43555 | D35: =D29 -> 43920 | E35: =E29 -> 44285 | F35: =F29 -> 44650 | G35: =G29 -> 45015 | H35: =H29 -> 45380 | I35: =I29 -> 45745 | J35: =J29 -> 46110
B36: Sales | C36: ='Data Sheet'!D17 -> 11054.67 | D36: ='Data Sheet'!E17 -> 11599.55 | E36: ='Data Sheet'!F17 -> 13136.14 | F36: ='Data Sheet'!G17 -> 14136.26 | G36: ='Data Sheet'!H17 -> 16300.55 | H36: ='Data Sheet'!I17 -> 16769.27 | I36: ='Data Sheet'!J17 -> 17942.67 | J36: ='Data Sheet'!K17 -> 19151.59
B37: Total Assets | C37: =C13 -> 6237.95 | D37: =D13 -> 7829.54 | E37: =E13 -> 8000.09 | F37: =F13 -> 7526.6 | G37: =G13 -> 9350.85 | H37: =H13 -> 9071.5 | I37: =I13 -> 8836.75 | J37: =J13 -> 9730.32
B38: Sales / Total Assets (E) | C38: =C36/C37 -> 1.7721639 | D38: =D36/D37 -> 1.481511 | E38: =E36/E37 -> 1.641999 | F38: =F36/F37 -> 1.8781734 | G38: =G36/G37 -> 1.7432159 | H38: =H36/H37 -> 1.8485664 | I38: =I36/I37 -> 2.0304603 | J38: =J36/J37 -> 1.9682385
B40: Altman's Z Score
C41: =C35 -> 43555 | D41: =D35 -> 43920 | E41: =E35 -> 44285 | F41: =F35 -> 44650 | G41: =G35 -> 45015 | H41: =H35 -> 45380 | I41: =I35 -> 45745 | J41: =J35 -> 46110
B43: Final Score | C43: =(C14*1.2)+(C20*1.4)+(C26*3.3)+(C32*0.6)+(C38*1) -> 288.11164 | D43: =(D14*1.2)+(D20*1.4)+(D26*3.3)+(D32*0.6)+(D38*1) -> 27.621505 | E43: =(E14*1.2)+(E20*1.4)+(E26*3.3)+(E32*0.6)+(E38*1) -> 27.605366 | F43: =(F14*1.2)+(F20*1.4)+(F26*3.3)+(F32*0.6)+(F38*1) -> 21.589056 | G43: =(G14*1.2)+(G20*1.4)+(G26*3.3)+(G32*0.6)+(G38*1) -> 23.559578 | H43: =(H14*1.2)+(H20*1.4)+(H26*3.3)+(H32*0.6)+(H38*1) -> 37.324422 | I43: =(I14*1.2)+(I20*1.4)+(I26*3.3)+(I32*0.6)+(I38*1) -> 60.330259 | J43: =(J14*1.2)+(J20*1.4)+(J26*3.3)+(J32*0.6)+(J38*1) -> 59.844561
B44: Financial Stability | C44: =IF(C43<1.81,"Distressed",IF(C43>3,"Strong","Grey Zone")) -> Strong | D44: =IF(D43<1.81,"Distressed",IF(D43>3,"Strong","Grey Zone")) -> Strong | E44: =IF(E43<1.81,"Distressed",IF(E43>3,"Strong","Grey Zone")) -> Strong | F44: =IF(F43<1.81,"Distressed",IF(F43>3,"Strong","Grey Zone")) -> Strong | G44: =IF(G43<1.81,"Distressed",IF(G43>3,"Strong","Grey Zone")) -> Strong | H44: =IF(H43<1.81,"Distressed",IF(H43>3,"Strong","Grey Zone")) -> Strong | I44: =IF(I43<1.81,"Distressed",IF(I43>3,"Strong","Grey Zone")) -> Strong | J44: =IF(J43<1.81,"Distressed",IF(J43>3,"Strong","Grey Zone")) -> Strong
B47: Disclaimer: This report is made as part of educational assignment and is meant for educational purpose only. The author of the report is not liable
B48: for any losses due to actions taken on basis of this report. It is advisable to consult SEBI registered research analyst before making any investments

Sheet Sheet2
B2: Date | C2: Adj Close
B3: 46287 | C3: 4918
B4: 46286 | C4: 5023
B5: 46283 | C5: 4998
B6: 46282 | C6: 4982
B7: 46281 | C7: 4999.5
B8: 46280 | C8: 4947.5
B9: 46279 | C9: 4962
B10: 46276 | C10: 4962
B11: 46275 | C11: 5009
B12: 46274 | C12: 5090
B13: 46273 | C13: 5064
B14: 46272 | C14: 5042.5
... B7717: 35066 | C7717: 7.26

Sheet Cash Flow Data
B2: 42064 | C2: 42430 | D2: 42795 | E2: 43160 | F2: 43525 | G2: 43891 | H2: 44256 | I2: 44621 | J2: 44986 | K2: 45352 | L2: 45717 | M2: 46082 | N2: TTM
A3: Sales - | B3: 7858 | C3: 8397 | D3: 9054 | E3: 9914 | F3: 11055 | G3: 11600 | H3: 13136 | I3: 14136 | J3: 16301 | K3: 16769 | L3: 17943 | M3: 19152 | N3: 19529
A4: Sales Growth % | B4: 0.1368 | C4: 0.0686 | D4: 0.0782 | E4: 0.095 | F4: 0.1151 | G4: 0.0493 | H4: 0.1325 | I4: 0.0761 | J4: 0.1531 | K4: 0.0288 | L4: 0.07 | M4: 0.0674
A5: Expenses - | B5: 6988 | C5: 7174 | D5: 7776 | E5: 8413 | F5: 9322 | G5: 9756 | H5: 10627 | I5: 11935 | J5: 13470 | K5: 13603 | L5: 14766 | M5: 15637 | N5: 15929
A6: Material Cost % + | B6: 0.6 | C6: 0.6 | D6: 0.62 | E6: 0.62 | F6: 0.59 | G6: 0.6 | H6: 0.58 | I6: 0.62 | J6: 0.59 | K6: 0.57 | L6: 0.59 | M6: 0.58
A7: Manufacturing Cost % | B7: 0.08 | C7: 0.07 | D7: 0.07 | E7: 0.06 | F7: 0.07 | G7: 0.07 | H7: 0.06 | I7: 0.07 | J7: 0.07 | K7: 0.07 | L7: 0.07 | M7: 0.07
A8: Employee Cost % | B8: 0.04 | C8: 0.04 | D8: 0.04 | E8: 0.04 | F8: 0.04 | G8: 0.04 | H8: 0.04 | I8: 0.04 | J8: 0.04 | K8: 0.04 | L8: 0.04 | M8: 0.04
A9: Other Cost % | B9: 0.17 | C9: 0.14 | D9: 0.13 | E9: 0.13 | F9: 0.14 | G9: 0.13 | H9: 0.12 | I9: 0.12 | J9: 0.13 | K9: 0.13 | L9: 0.12 | M9: 0.13
A10: Operating Profit | B10: 870 | C10: 1224 | D10: 1278 | E10: 1501 | F10: 1732 | G10: 1843 | H10: 2509 | I10: 2201 | J10: 2831 | K10: 3167 | L10: 3176 | M10: 3514 | N10: 3600
A11: OPM % | B11: 0.11 | C11: 0.15 | D11: 0.14 | E11: 0.15 | F11: 0.16 | G11: 0.16 | H11: 0.19 | I11: 0.16 | J11: 0.17 | K11: 0.19 | L11: 0.18 | M11: 0.18 | N11: 0.18
A12: Other Income - | B12: 228 | C12: 115 | D12: 151 | E12: 166 | F12: 206 | G12: 263 | H12: 313 | I12: 222 | J12: 597 | K12: 211 | L12: 202 | M12: 224 | N12: 228
A13: Exceptional items | B13: 183 | C13: -9 | D13: 0 | E13: 0 | F13: 1 | G13: -17 | H13: 0 | I13: 0 | J13: 376 | K13: -2 | L13: -24 | M13: 1
A14: Other income normal | B14: 45 | C14: 124 | D14: 151 | E14: 166 | F14: 205 | G14: 280 | H14: 313 | I14: 222 | J14: 220 | K14: 214 | L14: 226 | M14: 223
A15: Interest | B15: 4 | C15: 5 | D15: 5 | E15: 8 | F15: 9 | G15: 77 | H15: 111 | I15: 144 | J15: 169 | K15: 164 | L15: 139 | M15: 113 | N15: 109
A16: Depreciation | B16: 144 | C16: 113 | D16: 119 | E16: 142 | F16: 162 | G16: 185 | H16: 198 | I16: 201 | J16: 226 | K16: 300 | L16: 313 | M16: 337 | N16: 334
A17: Profit before tax | B17: 950 | C17: 1220 | D17: 1304 | E17: 1518 | F17: 1768 | G17: 1844 | H17: 2514 | I17: 2078 | J17: 3033 | K17: 2913 | L17: 2927 | M17: 3289 | N17: 3385
A18: Tax % | B18: 0.28 | C18: 0.32 | D18: 0.32 | E18: 0.34 | F18: 0.35 | G18: 0.24 | H18: 0.26 | I18: 0.27 | J18: 0.24 | K18: 0.27 | L18: 0.26 | M18: 0.23
A19: Net Profit - | B19: 689 | C19: 825 | D19: 885 | E19: 1004 | F19: 1155 | G19: 1394 | H19: 1851 | I19: 1516 | J19: 2316 | K19: 2134 | L19: 2178 | M19: 2537 | N19: 2610
A20: Profit from Associates | B20: 0 | C20: 0 | D20: 0 | E20: 0 | F20: 0 | G20: 0 | H20: 0 | I20: 0 | J20: 0 | K20: 0 | L20: 0 | M20: 0
A21: Minority share | B21: 0 | C21: 0 | D21: 0 | E21: 0 | F21: 4 | G21: 9 | H21: 13 | I21: 9 | J21: 5 | K21: 6 | L21: 1 | M21: -4
A22: Exceptional items AT | B22: 126 | C22: -6 | D22: 0 | E22: 0 | F22: 1 | G22: -13 | H22: 0 | I22: 0 | J22: 287 | K22: -2 | L22: -18 | M22: 1
A23: Profit excl Excep | B23: 562 | C23: 831 | D23: 885 | E23: 1004 | F23: 1155 | G23: 1406 | H23: 1851 | I23: 1516 | J23: 2029 | K23: 2136 | L23: 2195 | M23: 2536
A24: Profit for PE | B24: 562 | C24: 831 | D24: 884 | E24: 1004 | F24: 1158 | G24: 1415 | H24: 1864 | I24: 1525 | J24: 2035 | K24: 2142 | L24: 2196 | M24: 2532
A25: Profit for EPS | B25: 689 | C25: 825 | D25: 884 | E25: 1004 | F25: 1159 | G25: 1403 | H25: 1864 | I25: 1525 | J25: 2322 | K25: 2140 | L25: 2179 | M25: 2533
A26: Profit Growth % | B26: 0.46 | C26: 0.48 | D26: 0.06 | E26: 0.14 | F26: 0.15 | G26: 0.22 | H26: 0.32 | I26: -0.18 | J26: 0.33 | K26: 0.05 | L26: 0.03 | M26: 0.15
A27: EPS in Rs | B27: 28.71 | C27: 34.36 | D27: 36.85 | E27: 41.83 | F27: 48.23 | G27: 58.33 | H27: 77.38 | I27: 63.31 | J27: 96.39 | K27: 88.84 | L27: 90.45 | M27: 105.18 | N27: 108.11
A28: Dividend Payout % | B28: 0.28 | C28: 0.29 | D28: 0.3 | E28: 0.3 | F28: 0.31 | G28: 0.6 | H28: 2.04 | I28: 0.89 | J28: 0.75 | K28: 0.83 | L28: 0.83 | M28: 0.86
B31: 42064 | C31: 42430 | D31: 42795 | E31: 43160 | F31: 43525 | G31: 43891 | H31: 44256 | I31: 44621 | J31: 44986 | K31: 45352 | L31: 45717 | M31: 46082
A32: Equity Capital | B32: 24 | C32: 24 | D32: 24 | E32: 24 | F32: 24 | G32: 24 | H32: 24 | I32: 24 | J32: 24 | K32: 24 | L32: 24 | M32: 24
A33: Reserves | B33: 1221 | C33: 2068 | D33: 2672 | E33: 3382 | F33: 4229 | G33: 4379 | H33: 3524 | I33: 2534 | J33: 3510 | K33: 3917 | L33: 4332 | M33: 5082
A34: Borrowings - | B34: 145 | C34: 131 | D34: 125 | E34: 201 | F34: 156 | G34: 1538 | H34: 2107 | I34: 2481 | J34: 2997 | K34: 2065 | L34: 1247 | M34: 1380
A35: Long term Borrowings | B35: 43 | C35: 38 | D35: 31 | E35: 85 | F35: 62 | G35: 766 | H35: 748 | I35: 707 | J35: 1552 | K35: 905 | L35: 713 | M35: 286
A36: Short term Borrowings | B36: 97 | C36: 86 | D36: 84 | E36: 94 | F36: 76 | G36: 748 | H36: 1339 | I36: 1759 | J36: 1429 | K36: 1136 | L36: 512 | M36: 1072
A37: Lease Liabilities | B37: 0 | C37: 0 | D37: 0 | E37: 0 | F37: 0 | G37: 0 | H37: 0 | I37: 16 | J37: 17 | K37: 24 | L37: 22 | M37: 22
A38: Other Borrowings | B38: 5 | C38: 7 | D38: 9 | E38: 22 | F38: 18 | G38: 24 | H38: 20 | I38: 0 | J38: 0 | K38: 0 | L38: 0 | M38: 0
A39: Other Liabilities - | B39: 1403 | C39: 1271 | D39: 1288 | E39: 1581 | F39: 1829 | G39: 1889 | H39: 2345 | I39: 2487 | J39: 2819 | K39: 3065 | L39: 3235 | M39: 3243
A40: Non controlling int | B40: 2 | C40: 2 | D40: 3 | E40: 13 | F40: 33 | G40: 36 | H40: 36 | I40: 28 | J40: 30 | K40: 24 | L40: 26 | M40: 29
A41: Trade Payables | B41: 703 | C41: 769 | D41: 757 | E41: 994 | F41: 1141 | G41: 1047 | H41: 1315 | I41: 1323 | J41: 1449 | K41: 1627 | L41: 1752 | M41: 1896
A42: Advance from Customers | B42: 18 | C42: 16 | D42: 17 | E42: 31 | F42: 41 | G42: 78 | H42: 55 | I42: 34 | J42: 55 | K42: 42 | L42: 46 | M42: 53
A43: Other liability items | B43: 680 | C43: 483 | D43: 511 | E43: 543 | F43: 615 | G43: 729 | H43: 940 | I43: 1103 | J43: 1285 | K43: 1371 | L43: 1410 | M43: 1265
... A64: Total Assets | B64: 2793 | C64: 3494 | D64: 4109 | E64: 5188 | F64: 6238 | G64: 7830 | H64: 8000 | I64: 7527 | J64: 9351 | K64: 9072 | L64: 8837 | M64: 9730
B67: 42064 | C67: 42430 | D67: 42795 | E67: 43160 | F67: 43525 | G67: 43891 | H67: 44256 | I67: 44621 | J67: 44986 | K67: 45352 | L67: 45717 | M67: 46082
A68: Cash from Operating Activity - | B68: 584 | C68: 959 | D68: 441 | E68: 1249 | F68: 1156 | G68: 1485 | H68: 1851 | I68: 1300 | J68: 2526 | K68: 2573 | L68: 2491 | M68: 2612
A69: Profit from operations | B69: 861 | C69: 1230 | D69: 1289 | E69: 1517 | F69: 1754 | G69: 1860 | H69: 2540 | I69: 2214 | J69: 2846 | K69: 3177 | L69: 3174 | M69: 3555
A70: Receivables | B70: -25 | C70: -32 | D70: -9 | E70: -125 | F70: -87 | G70: 79 | H70: 61 | I70: -72 | J70: 1 | K70: -64 | L70: -53 | M70: -13
A71: Inventory | B71: 17 | C71: -35 | D71: -221 | E71: 9 | F71: -127 | G71: 43 | H71: -351 | I71: -275 | J71: 177 | K71: 13 | L71: -54 | M71: -105
A72: Payables | B72: 0 | C72: 0 | D72: 0 | E72: 0 | F72: 0 | G72: 0 | H72: 0 | I72: 64 | J72: 292 | K72: 237 | L72: 202 | M72: 25
A73: Loans Advances | B73: 14 | C73: 0 | D73: 0 | E73: 0 | F73: 0 | G73: 0 | H73: 0 | I73: 0 | J73: 0 | K73: 0 | L73: 0 | M73: 0
A74: Other WC items | B74: 18 | C74: 200 | D74: -221 | E74: 345 | F74: 211 | G74: 6 | H74: 234 | I74: -44 | J74: -65 | K74: -25 | L74: -89 | M74: -28
A75: Working capital changes | B75: 25 | C75: 133 | D75: -451 | E75: 228 | F75: -2 | G75: 127 | H75: -56 | I75: -327 | J75: 406 | K75: 161 | L75: 6 | M75: -121
A76: Direct taxes | B76: -301 | C76: -403 | D76: -397 | E76: -496 | F76: -596 | G76: -503 | H76: -633 | I76: -587 | J76: -726 | K76: -765 | L76: -689 | M76: -822
A77: Cash from Investing Activity - | B77: -450 | C77: -705 | D77: -150 | E77: -957 | F77: -852 | G77: -1526 | H77: 459 | I77: 914 | J77: -1507 | K77: 485 | L77: 69 | M77: -741
A78: Fixed assets purchased | B78: -118 | C78: -251 | D78: -360 | E78: -423 | F78: -401 | G78: -244 | H78: -242 | I78: -550 | J78: -711 | K78: -553 | L78: -375 | M78: -206
A79: Fixed assets sold | B79: 164 | C79: 1 | D79: 8 | E79: 2 | F79: 2 | G79: 1 | H79: 2 | I79: 3 | J79: 78 | K79: 65 | L79: 5 | M79: 2
... A100: CFO/OP | B100: 1.02 | C100: 1.11 | D100: 0.66 | E100: 1.16 | F100: 1.01 | G100: 1.08 | H100: 0.99 | I100: 0.86 | J100: 1.15 | K100: 1.05 | L100: 1 | M100: 0.98
A103: For LTM - put if error (sum of last 4 quarters)
A104: COGS | B104: RM cost, power fuel, other manf exp & empl cost
A106: COGS = (Raw mtrl cost + Power & Fuel + Other mfr exp + Employee cost) - 1*Change in inventory
A111: Particulars | B111: 42064 | C111: 42430 | D111: 42795 | E111: 43160 | F111: 43525 | G111: 43891 | H111: 44256 | I111: 44621 | J111: 44986 | K111: 45352 | L111: 45717 | M111: 46082
A113: Equity Capital | B113: 24 | C113: 24 | D113: 24 | E113: 24 | F113: 24 | G113: 24 | H113: 24 | I113: 24 | J113: 24 | K113: 24 | L113: 24 | M113: 24
A114: Reserves | B114: 1221 | C114: 2068 | D114: 2672 | E114: 3382 | F114: 4229 | G114: 4379 | H114: 3524 | I114: 2534 | J114: 3510 | K114: 3917 | L114: 4332 | M114: 5082
A115: Borrowings -
A116: Long term Borrowings | B116: 43 | C116: 38 | D116: 31 | E116: 85 | F116: 62 | G116: 766 | H116: 748 | I116: 707 | J116: 1552 | K116: 905 | L116: 713 | M116: 286
A117: Short term Borrowings | B117: 97 | C117: 86 | D117: 84 | E117: 94 | F117: 76 | G117: 748 | H117: 1339 | I117: 1759 | J117: 1429 | K117: 1136 | L117: 512 | M117: 1072
A118: Lease Liabilities | B118: 0 | C118: 0 | D118: 0 | E118: 0 | F118: 0 | G118: 0 | H118: 0 | I118: 16 | J118: 17 | K118: 24 | L118: 22 | M118: 22
A119: Other Borrowings | B119: 5 | C119: 7 | D119: 9 | E119: 22 | F119: 18 | G119: 24 | H119: 20 | I119: 0 | J119: 0 | K119: 0 | L119: 0 | M119: 0
A120: Other Liabilities -
A121: Non controlling int | B121: 2 | C121: 2 | D121: 3 | E121: 13 | F121: 33 | G121: 36 | H121: 36 | I121: 28 | J121: 30 | K121: 24 | L121: 26 | M121: 29
A122: Trade Payables | B122: 703 | C122: 769 | D122: 757 | E122: 994 | F122: 1141 | G122: 1047 | H122: 1315 | I122: 1323 | J122: 1449 | K122: 1627 | L122: 1752 | M122: 1896
A123: Advance from Customers | B123: 18 | C123: 16 | D123: 17 | E123: 31 | F123: 41 | G123: 78 | H123: 55 | I123: 34 | J123: 55 | K123: 42 | L123: 46 | M123: 53
A124: Other liability items | B124: 680 | C124: 483 | D124: 511 | E124: 543 | F124: 615 | G124: 729 | H124: 940 | I124: 1103 | J124: 1285 | K124: 1371 | L124: 1410 | M124: 1265
A125: Total Liabilities | B125: 2793 | C125: 3494 | D125: 4109 | E125: 5188 | F125: 6238 | G125: 7830 | H125: 8000 | I125: 7527 | J125: 9351 | K125: 9072 | L125: 8837 | M125: 9730
A127: Fixed Assets -
A128: Land | B128: 107 | C128: 105 | D128: 128 | E128: 246 | F128: 247 | G128: 319 | H128: 326 | I128: 334 | J128: 376 | K128: 384 | L128: 395 | M128: 397
A129: Building | B129: 346 | C129: 316 | D129: 376 | E129: 515 | F129: 660 | G129: 732 | H129: 758 | I129: 782 | J129: 1143 | K129: 1298 | L129: 1395 | M129: 1429
A130: Plant Machinery | B130: 981 | C130: 447 | D130: 641 | E130: 705 | F130: 1053 | G130: 1305 | H130: 1407 | I130: 1546 | J130: 2303 | K130: 2543 | L130: 2844 | M130: 3028
A131: Equipments | B131: 58 | C131: 16 | D131: 22 | E131: 25 | F131: 31 | G131: 40 | H131: 46 | I131: 52 | J131: 61 | K131: 75 | L131: 81 | M131: 79
A132: Furniture n fittings | B132: 24 | C132: 22 | D132: 25 | E132: 25 | F132: 28 | G132: 31 | H132: 32 | I132: 32 | J132: 43 | K132: 46 | L132: 49 | M132: 50
A133: Vehicles | B133: 4 | C133: 2 | D133: 2 | E133: 2 | F133: 3 | G133: 5 | H133: 5 | I133: 6 | J133: 10 | K133: 10 | L133: 9 | M133: 9
A134: Intangible Assets | B134: 145 | C134: 116 | D134: 128 | E134: 128 | F134: 134 | G134: 143 | H134: 139 | I134: 140 | J134: 130 | K134: 131 | L134: 134 | M134: 146
A135: Other fixed assets | B135: 44 | C135: 17 | D135: 36 | E135: 36 | F135: 40 | G135: 43 | H135: 46 | I135: 57 | J135: 86 | K135: 72 | L135: 67 | M135: 67
A136: Gross Block | B136: 1710 | C136: 1041 | D136: 1359 | E136: 1684 | F136: 2195 | G136: 2618 | H136: 2760 | I136: 2948 | J136: 4150 | K136: 4559 | L136: 4974 | M136: 5206
A137: Accumulated Depreciation | B137: 866 | C137: 91 | D137: 199 | E137: 338 | F137: 507 | G137: 739 | H137: 967 | I137: 1195 | J137: 1495 | K137: 1788 | L137: 2070 | M137: 2356
A138: Net Block | B138: =B136-B137 -> 844 | C138: =C136-C137 -> 950 | D138: =D136-D137 -> 1160 | E138: =E136-E137 -> 1346 | F138: =F136-F137 -> 1688 | G138: =G136-G137 -> 1879 | H138: =H136-H137 -> 1793 | I138: =I136-I137 -> 1753 | ... M138: =M136-M137 -> 2850
A140: CWIP | B140: 48 | C140: 90 | D140: 30 | E140: 203 | F140: 101 | G140: 40 | H140: 117 | I140: 536 | J140: 105 | K140: 188 | L140: 89 | M140: 39
A141: Investments | B141: 518 | C141: 788 | D141: 487 | E141: 1079 | F141: 1476 | G141: 2893 | H141: 2781 | I141: 1762 | J141: 3324 | K141: 2767 | L141: 2865 | M141: 3610
A143: Other Assets -
A144: Inventories | B144: 404 | C144: 441 | D144: 661 | E144: 653 | F144: 781 | G144: 741 | H144: 1091 | I144: 1367 | J144: 1193 | K144: 1181 | L144: 1237 | M144: 1346
A145: Trade receivables | B145: 136 | C145: 171 | D145: 179 | E145: 305 | F145: 394 | G145: 320 | H145: 257 | I145: 332 | J145: 329 | K145: 393 | L145: 449 | M145: 469
A146: Cash Equivalents | B146: 226 | C146: 88 | D146: 121 | E146: 186 | F146: 110 | G146: 123 | H146: 211 | I146: 185 | J146: 198 | K146: 446 | L146: 312 | M146: 352
A147: Loans n Advances | B147: -3 | C147: 8 | D147: 217 | E147: 150 | F147: 63 | G147: 50 | H147: 45 | I147: 63 | J147: 83 | K147: 62 | L147: 67 | M147: 55
A148: Other asset items | B148: 620 | C148: 958 | D148: 1254 | E148: 1267 | F148: 1623 | G148: 1784 | H148: 1705 | I148: 1528 | J148: 1463 | K148: 1263 | L148: 914 | M148: 1009
A149: Total Assets | B149: 2793 | C149: 3494 | D149: 4109 | E149: 5188 | F149: 6238 | G149: 7830 | H149: 8000 | I149: 7527 | J149: 9351 | K149: 9072 | L149: 8837 | M149: 9730

Sheet Britannia
A1: Britannia Industries Limited NSE
A3: Date | B3: Adj Close
